Workbook

Sheet Inputs
A1: SPIA Inputs
A3: Issue Age | B3: 65 | D3: Notes
A4: Sex | B4: male | D4: All rates are decimals.
A5: Annual Benefit | B5: 100000 | D5: Valuation date interpreted as 12/31/Valuation Year.
A6: Payment Frequency | B6: 12 | D6: Monthly expenses assumed paid while in-force.
A7: Valuation Year | B7: 2025
A8: Horizon Age | B8: 110
A9: Spread | B9: 0
A10: Policy Expense Dollars | B10: 250
A11: Premium Expense Rate | B11: 0.01
A12: Monthly Expense Dollars | B12: 25
A15: Derived
A16: Monthly Benefit | B16: =B5/B6 -> 8333.3333
A17: Projection Months | B17: =(B8-B3)*B6 -> 540

Sheet YieldCurve
A1: Treasury Zero Curve
A3: maturity_years | B3: zero_rate
A4: 0.5 | B4: 0.03725093
A5: 1 | B5: 0.0369537
A6: 1.5 | B6: 0.03725465
A7: 2 | B7: 0.03755667
A8: 2.5 | B8: 0.03755441
A9: 3 | B9: 0.0375529
A10: 3.5 | B10: 0.03778571
A11: 4 | B11: 0.03801957
A12: 4.5 | B12: 0.03825472
A13: 5 | B13: 0.03849135
A14: 5.5 | B14: 0.03897383
A15: 6 | B15: 0.03945938
... A63: 30 | B63: 0.04945471

Sheet RP2014_Qx
A1: RP-2014 Male Healthy Annuitant Base Qx (2014)
A3: age | B3: qx
A4: 50 | B4: 0.002768
A5: 51 | B5: 0.002905
A6: 52 | B6: 0.003057
A7: 53 | B7: 0.003225
A8: 54 | B8: 0.003412
A9: 55 | B9: 0.003622
A10: 56 | B10: 0.003858
A11: 57 | B11: 0.004128
A12: 58 | B12: 0.004436
A13: 59 | B13: 0.004789
A14: 60 | B14: 0.005191
A15: 61 | B15: 0.005646
... A74: 120 | B74: 1

Sheet MP2016_Long
A1: MP-2016 Male Improvement Rates (Long)
A3: age | B3: year | C3: improvement_rate
A4: 21 | B4: 1951 | C4: -0.0146
A5: 21 | B5: 1952 | C5: -0.0062
A6: 21 | B6: 1953 | C6: 0.002
A7: 21 | B7: 1954 | C7: 0.0092
A8: 21 | B8: 1955 | C8: 0.0151
A9: 21 | B9: 1956 | C9: 0.0193
A10: 21 | B10: 1957 | C10: 0.0215
A11: 21 | B11: 1958 | C11: 0.0211
A12: 21 | B12: 1959 | C12: 0.018
A13: 21 | B13: 1960 | C13: 0.0121
A14: 21 | B14: 1961 | C14: 0.0038
A15: 21 | B15: 1962 | C15: -0.0059
... A8103: 120 | B8103: 2031 | C8103: 0

Sheet MonthlyCurve
A1: Monthly Interpolated Zero Curve
A3: Month | B3: t_years | C3: BracketIndex | D3: LowerMat | E3: UpperMat | F3: LowerZero | G3: UpperZero | H3: InterpWeight | I3: ZeroRateInterpolated | J3: DiscountFactor
A4: 1 | B4: =A4/Inputs!$B$6 -> 0.083333333 | C4: =IF(B4<=INDEX(YieldCurve!$A$4:$A$63,1),1,IF(B4>=INDEX(YieldCurve!$A$4:$A$63,ROWS(YieldCurve!$A$4:$A$63)),ROWS(YieldCurve!$A$4:$A$63)-1,MATCH(B4,YieldCurve!$A$4:$A$63,1))) -> 1 | D4: =INDEX(YieldCurve!$A$4:$A$63,C4) -> 0.5 | E4: =INDEX(YieldCurve!$A$4:$A$63,C4+1) -> 1 | F4: =INDEX(YieldCurve!$B$4:$B$63,C4) -> 0.03725093 | G4: =INDEX(YieldCurve!$B$4:$B$63,C4+1) -> 0.0369537 | H4: =IF(E4=D4,0,(B4-D4)/(E4-D4)) -> -0.83333333 | I4: =IF(B4<=INDEX(YieldCurve!$A$4:$A$63,1),INDEX(YieldCurve!$B$4:$B$63,1),IF(B4>=INDEX(YieldCurve!$A$4:$A$63,ROWS(YieldCurve!$A$4:$A$63)),INDEX(YieldCurve!$B$4:$B$63,ROWS(YieldCurve!$B$4:$B$63)),F4+H4*(G4-F4))) -> 0.03725093 | J4: =EXP(-(I4+Inputs!$B$9)*B4) -> 0.99690057
A5: 2 | B5: =A5/Inputs!$B$6 -> 0.16666667 | C5: =IF(B5<=INDEX(YieldCurve!$A$4:$A$63,1),1,IF(B5>=INDEX(YieldCurve!$A$4:$A$63,ROWS(YieldCurve!$A$4:$A$63)),ROWS(YieldCurve!$A$4:$A$63)-1,MATCH(B5,YieldCurve!$A$4:$A$63,1))) -> 1 | D5: =INDEX(YieldCurve!$A$4:$A$63,C5) -> 0.5 | E5: =INDEX(YieldCurve!$A$4:$A$63,C5+1) -> 1 | F5: =INDEX(YieldCurve!$B$4:$B$63,C5) -> 0.03725093 | G5: =INDEX(YieldCurve!$B$4:$B$63,C5+1) -> 0.0369537 | H5: =IF(E5=D5,0,(B5-D5)/(E5-D5)) -> -0.66666667 | I5: =IF(B5<=INDEX(YieldCurve!$A$4:$A$63,1),INDEX(YieldCurve!$B$4:$B$63,1),IF(B5>=INDEX(YieldCurve!$A$4:$A$63,ROWS(YieldCurve!$A$4:$A$63)),INDEX(YieldCurve!$B$4:$B$63,ROWS(YieldCurve!$B$4:$B$63)),F5+H5*(G5-F5))) -> 0.03725093 | J5: =EXP(-(I5+Inputs!$B$9)*B5) -> 0.99381074
A6: 3 | B6: =A6/Inputs!$B$6 -> 0.25 | C6: =IF(B6<=INDEX(YieldCurve!$A$4:$A$63,1),1,IF(B6>=INDEX(YieldCurve!$A$4:$A$63,ROWS(YieldCurve!$A$4:$A$63)),ROWS(YieldCurve!$A$4:$A$63)-1,MATCH(B6,YieldCurve!$A$4:$A$63,1))) -> 1 | D6: =INDEX(YieldCurve!$A$4:$A$63,C6) -> 0.5 | E6: =INDEX(YieldCurve!$A$4:$A$63,C6+1) -> 1 | F6: =INDEX(YieldCurve!$B$4:$B$63,C6) -> 0.03725093 | G6: =INDEX(YieldCurve!$B$4:$B$63,C6+1) -> 0.0369537 | H6: =IF(E6=D6,0,(B6-D6)/(E6-D6)) -> -0.5 | I6: =IF(B6<=INDEX(YieldCurve!$A$4:$A$63,1),INDEX(YieldCurve!$B$4:$B$63,1),IF(B6>=INDEX(YieldCurve!$A$4:$A$63,ROWS(YieldCurve!$A$4:$A$63)),INDEX(YieldCurve!$B$4:$B$63,ROWS(YieldCurve!$B$4:$B$63)),F6+H6*(G6-F6))) -> 0.03725093 | J6: =EXP(-(I6+Inputs!$B$9)*B6) -> 0.9907305
A7: 4 | B7: =A7/Inputs!$B$6 -> 0.33333333 | C7: =IF(B7<=INDEX(YieldCurve!$A$4:$A$63,1),1,IF(B7>=INDEX(YieldCurve!$A$4:$A$63,ROWS(YieldCurve!$A$4:$A$63)),ROWS(YieldCurve!$A$4:$A$63)-1,MATCH(B7,YieldCurve!$A$4:$A$63,1))) -> 1 | D7: =INDEX(YieldCurve!$A$4:$A$63,C7) -> 0.5 | E7: =INDEX(YieldCurve!$A$4:$A$63,C7+1) -> 1 | F7: =INDEX(YieldCurve!$B$4:$B$63,C7) -> 0.03725093 | G7: =INDEX(YieldCurve!$B$4:$B$63,C7+1) -> 0.0369537 | H7: =IF(E7=D7,0,(B7-D7)/(E7-D7)) -> -0.33333333 | I7: =IF(B7<=INDEX(YieldCurve!$A$4:$A$63,1),INDEX(YieldCurve!$B$4:$B$63,1),IF(B7>=INDEX(YieldCurve!$A$4:$A$63,ROWS(YieldCurve!$A$4:$A$63)),INDEX(YieldCurve!$B$4:$B$63,ROWS(YieldCurve!$B$4:$B$63)),F7+H7*(G7-F7))) -> 0.03725093 | J7: =EXP(-(I7+Inputs!$B$9)*B7) -> 0.9876598
A8: 5 | B8: =A8/Inputs!$B$6 -> 0.41666667 | C8: =IF(B8<=INDEX(YieldCurve!$A$4:$A$63,1),1,IF(B8>=INDEX(YieldCurve!$A$4:$A$63,ROWS(YieldCurve!$A$4:$A$63)),ROWS(YieldCurve!$A$4:$A$63)-1,MATCH(B8,YieldCurve!$A$4:$A$63,1))) -> 1 | D8: =INDEX(YieldCurve!$A$4:$A$63,C8) -> 0.5 | E8: =INDEX(YieldCurve!$A$4:$A$63,C8+1) -> 1 | F8: =INDEX(YieldCurve!$B$4:$B$63,C8) -> 0.03725093 | G8: =INDEX(YieldCurve!$B$4:$B$63,C8+1) -> 0.0369537 | H8: =IF(E8=D8,0,(B8-D8)/(E8-D8)) -> -0.16666667 | I8: =IF(B8<=INDEX(YieldCurve!$A$4:$A$63,1),INDEX(YieldCurve!$B$4:$B$63,1),IF(B8>=INDEX(YieldCurve!$A$4:$A$63,ROWS(YieldCurve!$A$4:$A$63)),INDEX(YieldCurve!$B$4:$B$63,ROWS(YieldCurve!$B$4:$B$63)),F8+H8*(G8-F8))) -> 0.03725093 | J8: =EXP(-(I8+Inputs!$B$9)*B8) -> 0.98459861
A9: 6 | B9: =A9/Inputs!$B$6 -> 0.5 | C9: =IF(B9<=INDEX(YieldCurve!$A$4:$A$63,1),1,IF(B9>=INDEX(YieldCurve!$A$4:$A$63,ROWS(YieldCurve!$A$4:$A$63)),ROWS(YieldCurve!$A$4:$A$63)-1,MATCH(B9,YieldCurve!$A$4:$A$63,1))) -> 1 | D9: =INDEX(YieldCurve!$A$4:$A$63,C9) -> 0.5 | E9: =INDEX(YieldCurve!$A$4:$A$63,C9+1) -> 1 | F9: =INDEX(YieldCurve!$B$4:$B$63,C9) -> 0.03725093 | G9: =INDEX(YieldCurve!$B$4:$B$63,C9+1) -> 0.0369537 | H9: =IF(E9=D9,0,(B9-D9)/(E9-D9)) -> 0 | I9: =IF(B9<=INDEX(YieldCurve!$A$4:$A$63,1),INDEX(YieldCurve!$B$4:$B$63,1),IF(B9>=INDEX(YieldCurve!$A$4:$A$63,ROWS(YieldCurve!$A$4:$A$63)),INDEX(YieldCurve!$B$4:$B$63,ROWS(YieldCurve!$B$4:$B$63)),F9+H9*(G9-F9))) -> 0.03725093 | J9: =EXP(-(I9+Inputs!$B$9)*B9) -> 0.98154692
A10: 7 | B10: =A10/Inputs!$B$6 -> 0.58333333 | C10: =IF(B10<=INDEX(YieldCurve!$A$4:$A$63,1),1,IF(B10>=INDEX(YieldCurve!$A$4:$A$63,ROWS(YieldCurve!$A$4:$A$63)),ROWS(YieldCurve!$A$4:$A$63)-1,MATCH(B10,YieldCurve!$A$4:$A$63,1))) -> 1 | D10: =INDEX(YieldCurve!$A$4:$A$63,C10) -> 0.5 | E10: =INDEX(YieldCurve!$A$4:$A$63,C10+1) -> 1 | F10: =INDEX(YieldCurve!$B$4:$B$63,C10) -> 0.03725093 | G10: =INDEX(YieldCurve!$B$4:$B$63,C10+1) -> 0.0369537 | H10: =IF(E10=D10,0,(B10-D10)/(E10-D10)) -> 0.16666667 | I10: =IF(B10<=INDEX(YieldCurve!$A$4:$A$63,1),INDEX(YieldCurve!$B$4:$B$63,1),IF(B10>=INDEX(YieldCurve!$A$4:$A$63,ROWS(YieldCurve!$A$4:$A$63)),INDEX(YieldCurve!$B$4:$B$63,ROWS(YieldCurve!$B$4:$B$63)),F10+H10*(G10-F10))) -> 0.037201392 | J10: =EXP(-(I10+Inputs!$B$9)*B10) -> 0.97853296
A11: 8 | B11: =A11/Inputs!$B$6 -> 0.66666667 | C11: =IF(B11<=INDEX(YieldCurve!$A$4:$A$63,1),1,IF(B11>=INDEX(YieldCurve!$A$4:$A$63,ROWS(YieldCurve!$A$4:$A$63)),ROWS(YieldCurve!$A$4:$A$63)-1,MATCH(B11,YieldCurve!$A$4:$A$63,1))) -> 1 | D11: =INDEX(YieldCurve!$A$4:$A$63,C11) -> 0.5 | E11: =INDEX(YieldCurve!$A$4:$A$63,C11+1) -> 1 | F11: =INDEX(YieldCurve!$B$4:$B$63,C11) -> 0.03725093 | G11: =INDEX(YieldCurve!$B$4:$B$63,C11+1) -> 0.0369537 | H11: =IF(E11=D11,0,(B11-D11)/(E11-D11)) -> 0.33333333 | I11: =IF(B11<=INDEX(YieldCurve!$A$4:$A$63,1),INDEX(YieldCurve!$B$4:$B$63,1),IF(B11>=INDEX(YieldCurve!$A$4:$A$63,ROWS(YieldCurve!$A$4:$A$63)),INDEX(YieldCurve!$B$4:$B$63,ROWS(YieldCurve!$B$4:$B$63)),F11+H11*(G11-F11))) -> 0.037151853 | J11: =EXP(-(I11+Inputs!$B$9)*B11) -> 0.97553631
A12: 9 | B12: =A12/Inputs!$B$6 -> 0.75 | C12: =IF(B12<=INDEX(YieldCurve!$A$4:$A$63,1),1,IF(B12>=INDEX(YieldCurve!$A$4:$A$63,ROWS(YieldCurve!$A$4:$A$63)),ROWS(YieldCurve!$A$4:$A$63)-1,MATCH(B12,YieldCurve!$A$4:$A$63,1))) -> 1 | D12: =INDEX(YieldCurve!$A$4:$A$63,C12) -> 0.5 | E12: =INDEX(YieldCurve!$A$4:$A$63,C12+1) -> 1 | F12: =INDEX(YieldCurve!$B$4:$B$63,C12) -> 0.03725093 | G12: =INDEX(YieldCurve!$B$4:$B$63,C12+1) -> 0.0369537 | H12: =IF(E12=D12,0,(B12-D12)/(E12-D12)) -> 0.5 | I12: =IF(B12<=INDEX(YieldCurve!$A$4:$A$63,1),INDEX(YieldCurve!$B$4:$B$63,1),IF(B12>=INDEX(YieldCurve!$A$4:$A$63,ROWS(YieldCurve!$A$4:$A$63)),INDEX(YieldCurve!$B$4:$B$63,ROWS(YieldCurve!$B$4:$B$63)),F12+H12*(G12-F12))) -> 0.037102315 | J12: =EXP(-(I12+Inputs!$B$9)*B12) -> 0.97255686
A13: 10 | B13: =A13/Inputs!$B$6 -> 0.83333333 | C13: =IF(B13<=INDEX(YieldCurve!$A$4:$A$63,1),1,IF(B13>=INDEX(YieldCurve!$A$4:$A$63,ROWS(YieldCurve!$A$4:$A$63)),ROWS(YieldCurve!$A$4:$A$63)-1,MATCH(B13,YieldCurve!$A$4:$A$63,1))) -> 1 | D13: =INDEX(YieldCurve!$A$4:$A$63,C13) -> 0.5 | E13: =INDEX(YieldCurve!$A$4:$A$63,C13+1) -> 1 | F13: =INDEX(YieldCurve!$B$4:$B$63,C13) -> 0.03725093 | G13: =INDEX(YieldCurve!$B$4:$B$63,C13+1) -> 0.0369537 | H13: =IF(E13=D13,0,(B13-D13)/(E13-D13)) -> 0.66666667 | I13: =IF(B13<=INDEX(YieldCurve!$A$4:$A$63,1),INDEX(YieldCurve!$B$4:$B$63,1),IF(B13>=INDEX(YieldCurve!$A$4:$A$63,ROWS(YieldCurve!$A$4:$A$63)),INDEX(YieldCurve!$B$4:$B$63,ROWS(YieldCurve!$B$4:$B$63)),F13+H13*(G13-F13))) -> 0.037052777 | J13: =EXP(-(I13+Inputs!$B$9)*B13) -> 0.96959452
A14: 11 | B14: =A14/Inputs!$B$6 -> 0.91666667 | C14: =IF(B14<=INDEX(YieldCurve!$A$4:$A$63,1),1,IF(B14>=INDEX(YieldCurve!$A$4:$A$63,ROWS(YieldCurve!$A$4:$A$63)),ROWS(YieldCurve!$A$4:$A$63)-1,MATCH(B14,YieldCurve!$A$4:$A$63,1))) -> 1 | D14: =INDEX(YieldCurve!$A$4:$A$63,C14) -> 0.5 | E14: =INDEX(YieldCurve!$A$4:$A$63,C14+1) -> 1 | F14: =INDEX(YieldCurve!$B$4:$B$63,C14) -> 0.03725093 | G14: =INDEX(YieldCurve!$B$4:$B$63,C14+1) -> 0.0369537 | H14: =IF(E14=D14,0,(B14-D14)/(E14-D14)) -> 0.83333333 | I14: =IF(B14<=INDEX(YieldCurve!$A$4:$A$63,1),INDEX(YieldCurve!$B$4:$B$63,1),IF(B14>=INDEX(YieldCurve!$A$4:$A$63,ROWS(YieldCurve!$A$4:$A$63)),INDEX(YieldCurve!$B$4:$B$63,ROWS(YieldCurve!$B$4:$B$63)),F14+H14*(G14-F14))) -> 0.037003238 | J14: =EXP(-(I14+Inputs!$B$9)*B14) -> 0.96664919
A15: 12 | B15: =A15/Inputs!$B$6 -> 1 | C15: =IF(B15<=INDEX(YieldCurve!$A$4:$A$63,1),1,IF(B15>=INDEX(YieldCurve!$A$4:$A$63,ROWS(YieldCurve!$A$4:$A$63)),ROWS(YieldCurve!$A$4:$A$63)-1,MATCH(B15,YieldCurve!$A$4:$A$63,1))) -> 2 | D15: =INDEX(YieldCurve!$A$4:$A$63,C15) -> 1 | E15: =INDEX(YieldCurve!$A$4:$A$63,C15+1) -> 1.5 | F15: =INDEX(YieldCurve!$B$4:$B$63,C15) -> 0.0369537 | G15: =INDEX(YieldCurve!$B$4:$B$63,C15+1) -> 0.03725465 | H15: =IF(E15=D15,0,(B15-D15)/(E15-D15)) -> 0 | I15: =IF(B15<=INDEX(YieldCurve!$A$4:$A$63,1),INDEX(YieldCurve!$B$4:$B$63,1),IF(B15>=INDEX(YieldCurve!$A$4:$A$63,ROWS(YieldCurve!$A$4:$A$63)),INDEX(YieldCurve!$B$4:$B$63,ROWS(YieldCurve!$B$4:$B$63)),F15+H15*(G15-F15))) -> 0.0369537 | J15: =EXP(-(I15+Inputs!$B$9)*B15) -> 0.96372075
... A543: 540 | B543: =A543/Inputs!$B$6 -> 45 | C543: =IF(B543<=INDEX(YieldCurve!$A$4:$A$63,1),1,IF(B543>=INDEX(YieldCurve!$A$4:$A$63,ROWS(YieldCurve!$A$4:$A$63)),ROWS(YieldCurve!$A$4:$A$63)-1,MATCH(B543,YieldCurve!$A$4:$A$63,1))) -> 59 | D543: =INDEX(YieldCurve!$A$4:$A$63,C543) -> 29.5 | E543: =INDEX(YieldCurve!$A$4:$A$63,C543+1) -> 30 | F543: =INDEX(YieldCurve!$B$4:$B$63,C543) -> 0.04947242 | G543: =INDEX(YieldCurve!$B$4:$B$63,C543+1) -> 0.04945471 | H543: =IF(E543=D543,0,(B543-D543)/(E543-D543)) -> 31 | I543: =IF(B543<=INDEX(YieldCurve!$A$4:$A$63,1),INDEX(YieldCurve!$B$4:$B$63,1),IF(B543>=INDEX(YieldCurve!$A$4:$A$63,ROWS(YieldCurve!$A$4:$A$63)),INDEX(YieldCurve!$B$4:$B$63,ROWS(YieldCurve!$B$4:$B$63)),F543+H543*(G543-F543))) -> 0.04945471 | J543: =EXP(-(I543+Inputs!$B$9)*B543) -> 0.10801751

Sheet Projection
A1: SPIA Monthly Projection (Formula Driven)
A2: ReserveAtT0 | B2: 0 | C2: =Inputs!$B$3 -> 65 | U2: =X9 -> 1268279
A3: Month | B3: t_years | C3: AttainedAge | D3: IntAge | E3: CalendarYear | F3: MonthlyBenefit | G3: MonthlyExpense | H3: BaseQx2014 | I3: CumMP | J3: QxYear | K3: MuYear | L3: SurvInterval | M3: SurvivalToPay | N3: ZeroRateInterpolated | O3: DiscountFactor | P3: ExpBenefitCF | Q3: ExpExpenseCF | R3: ExpTotalCF | S3: PVBenefitCF | T3: PVExpenseCF | U3: ReserveAfterPayment | W3: Summary
A4: 1 | B4: =A4/Inputs!$B$6 -> 0.083333333 | C4: =Inputs!$B$3+B4 -> 65.083333 | D4: =INT(C4) -> 65 | E4: =Inputs!$B$7+1+INT((A4-1)/Inputs!$B$6) -> 2026 | F4: =Inputs!$B$16 -> 8333.3333 | G4: =Inputs!$B$12 -> 25 | H4: =IFERROR(INDEX(RP2014_Qx!$B:$B,MATCH(D4,RP2014_Qx!$A:$A,0)),"") -> 0.008048 | I4: =SUMIFS(MP2016_Long!$C:$C,MP2016_Long!$A:$A,D4,MP2016_Long!$B:$B,">=2014",MP2016_Long!$B:$B,"<"&E4) -> 0.0639 | J4: =MIN(0.999999,MAX(0,H4*EXP(I4))) -> 0.0085790537 | K4: =-LN(1-J4) -> 0.0086160656 | L4: =EXP(-K4/Inputs!$B$6) -> 0.99928225 | M4: =L4 -> 0.99928225 | N4: =IFERROR(INDEX(MonthlyCurve!$I:$I,MATCH(A4,MonthlyCurve!$A:$A,0)),"") -> 0.03725093 | O4: =IFERROR(INDEX(MonthlyCurve!$J:$J,MATCH(A4,MonthlyCurve!$A:$A,0)),"") -> 0.99690057 | P4: =F4*M4 -> 8327.3521 | Q4: =G4*M4 -> 24.982056 | R4: =P4+Q4 -> 8352.3342 | S4: =P4*O4 -> 8301.542 | T4: =Q4*O4 -> 24.904626 | U4: =SUMPRODUCT(R5:R543,O5:O543)/(M4*O4) -> 1264777.6 | W4: PV Benefits | X4: =SUM(S4:S543) -> 1264485.5
A5: 2 | B5: =A5/Inputs!$B$6 -> 0.16666667 | C5: =Inputs!$B$3+B5 -> 65.166667 | D5: =INT(C5) -> 65 | E5: =Inputs!$B$7+1+INT((A5-1)/Inputs!$B$6) -> 2026 | F5: =Inputs!$B$16 -> 8333.3333 | G5: =Inputs!$B$12 -> 25 | H5: =IFERROR(INDEX(RP2014_Qx!$B:$B,MATCH(D5,RP2014_Qx!$A:$A,0)),"") -> 0.008048 | I5: =SUMIFS(MP2016_Long!$C:$C,MP2016_Long!$A:$A,D5,MP2016_Long!$B:$B,">=2014",MP2016_Long!$B:$B,"<"&E5) -> 0.0639 | J5: =MIN(0.999999,MAX(0,H5*EXP(I5))) -> 0.0085790537 | K5: =-LN(1-J5) -> 0.0086160656 | L5: =EXP(-K5/Inputs!$B$6) -> 0.99928225 | M5: =M4*L5 -> 0.99856502 | N5: =IFERROR(INDEX(MonthlyCurve!$I:$I,MATCH(A5,MonthlyCurve!$A:$A,0)),"") -> 0.03725093 | O5: =IFERROR(INDEX(MonthlyCurve!$J:$J,MATCH(A5,MonthlyCurve!$A:$A,0)),"") -> 0.99381074 | P5: =F5*M5 -> 8321.3752 | Q5: =G5*M5 -> 24.964125 | R5: =P5+Q5 -> 8346.3393 | S5: =P5*O5 -> 8269.872 | T5: =Q5*O5 -> 24.809616 | U5: =SUMPRODUCT(R6:R543,O6:O543)/(M5*O5) -> 1261262.8 | W5: PV Monthly Expenses | X5: =SUM(T4:T543) -> 3793.4566
A6: 3 | B6: =A6/Inputs!$B$6 -> 0.25 | C6: =Inputs!$B$3+B6 -> 65.25 | D6: =INT(C6) -> 65 | E6: =Inputs!$B$7+1+INT((A6-1)/Inputs!$B$6) -> 2026 | F6: =Inputs!$B$16 -> 8333.3333 | G6: =Inputs!$B$12 -> 25 | H6: =IFERROR(INDEX(RP2014_Qx!$B:$B,MATCH(D6,RP2014_Qx!$A:$A,0)),"") -> 0.008048 | I6: =SUMIFS(MP2016_Long!$C:$C,MP2016_Long!$A:$A,D6,MP2016_Long!$B:$B,">=2014",MP2016_Long!$B:$B,"<"&E6) -> 0.0639 | J6: =MIN(0.999999,MAX(0,H6*EXP(I6))) -> 0.0085790537 | K6: =-LN(1-J6) -> 0.0086160656 | L6: =EXP(-K6/Inputs!$B$6) -> 0.99928225 | M6: =M5*L6 -> 0.9978483 | N6: =IFERROR(INDEX(MonthlyCurve!$I:$I,MATCH(A6,MonthlyCurve!$A:$A,0)),"") -> 0.03725093 | O6: =IFERROR(INDEX(MonthlyCurve!$J:$J,MATCH(A6,MonthlyCurve!$A:$A,0)),"") -> 0.9907305 | P6: =F6*M6 -> 8315.4025 | Q6: =G6*M6 -> 24.946208 | R6: =P6+Q6 -> 8340.3487 | S6: =P6*O6 -> 8238.3229 | T6: =Q6*O6 -> 24.714969 | U6: =SUMPRODUCT(R7:R543,O7:O543)/(M6*O6) -> 1257734.6 | W6: Annuity Factor | X6: =SUMPRODUCT(M4:M543,O4:O543) -> 151.73826
A7: 4 | B7: =A7/Inputs!$B$6 -> 0.33333333 | C7: =Inputs!$B$3+B7 -> 65.333333 | D7: =INT(C7) -> 65 | E7: =Inputs!$B$7+1+INT((A7-1)/Inputs!$B$6) -> 2026 | F7: =Inputs!$B$16 -> 8333.3333 | G7: =Inputs!$B$12 -> 25 | H7: =IFERROR(INDEX(RP2014_Qx!$B:$B,MATCH(D7,RP2014_Qx!$A:$A,0)),"") -> 0.008048 | I7: =SUMIFS(MP2016_Long!$C:$C,MP2016_Long!$A:$A,D7,MP2016_Long!$B:$B,">=2014",MP2016_Long!$B:$B,"<"&E7) -> 0.0639 | J7: =MIN(0.999999,MAX(0,H7*EXP(I7))) -> 0.0085790537 | K7: =-LN(1-J7) -> 0.0086160656 | L7: =EXP(-K7/Inputs!$B$6) -> 0.99928225 | M7: =M6*L7 -> 0.9971321 | N7: =IFERROR(INDEX(MonthlyCurve!$I:$I,MATCH(A7,MonthlyCurve!$A:$A,0)),"") -> 0.03725093 | O7: =IFERROR(INDEX(MonthlyCurve!$J:$J,MATCH(A7,MonthlyCurve!$A:$A,0)),"") -> 0.9876598 | P7: =F7*M7 -> 8309.4342 | Q7: =G7*M7 -> 24.928302 | R7: =P7+Q7 -> 8334.3625 | S7: =P7*O7 -> 8206.894 | T7: =Q7*O7 -> 24.620682 | U7: =SUMPRODUCT(R8:R543,O8:O543)/(M7*O7) -> 1254192.8 | W7: PV Monthly Total | X7: =X4+X5 -> 1268279
A8: 5 | B8: =A8/Inputs!$B$6 -> 0.41666667 | C8: =Inputs!$B$3+B8 -> 65.416667 | D8: =INT(C8) -> 65 | E8: =Inputs!$B$7+1+INT((A8-1)/Inputs!$B$6) -> 2026 | F8: =Inputs!$B$16 -> 8333.3333 | G8: =Inputs!$B$12 -> 25 | H8: =IFERROR(INDEX(RP2014_Qx!$B:$B,MATCH(D8,RP2014_Qx!$A:$A,0)),"") -> 0.008048 | I8: =SUMIFS(MP2016_Long!$C:$C,MP2016_Long!$A:$A,D8,MP2016_Long!$B:$B,">=2014",MP2016_Long!$B:$B,"<"&E8) -> 0.0639 | J8: =MIN(0.999999,MAX(0,H8*EXP(I8))) -> 0.0085790537 | K8: =-LN(1-J8) -> 0.0086160656 | L8: =EXP(-K8/Inputs!$B$6) -> 0.99928225 | M8: =M7*L8 -> 0.99641641 | N8: =IFERROR(INDEX(MonthlyCurve!$I:$I,MATCH(A8,MonthlyCurve!$A:$A,0)),"") -> 0.03725093 | O8: =IFERROR(INDEX(MonthlyCurve!$J:$J,MATCH(A8,MonthlyCurve!$A:$A,0)),"") -> 0.98459861 | P8: =F8*M8 -> 8303.4701 | Q8: =G8*M8 -> 24.91041 | R8: =P8+Q8 -> 8328.3805 | S8: =P8*O8 -> 8175.5851 | T8: =Q8*O8 -> 24.526755 | U8: =SUMPRODUCT(R9:R543,O9:O543)/(M8*O8) -> 1250637.5 | W8: Single Premium | X8: =(Inputs!$B$10+X7)/(1-Inputs!$B$11) -> 1281342.4
A9: 6 | B9: =A9/Inputs!$B$6 -> 0.5 | C9: =Inputs!$B$3+B9 -> 65.5 | D9: =INT(C9) -> 65 | E9: =Inputs!$B$7+1+INT((A9-1)/Inputs!$B$6) -> 2026 | F9: =Inputs!$B$16 -> 8333.3333 | G9: =Inputs!$B$12 -> 25 | H9: =IFERROR(INDEX(RP2014_Qx!$B:$B,MATCH(D9,RP2014_Qx!$A:$A,0)),"") -> 0.008048 | I9: =SUMIFS(MP2016_Long!$C:$C,MP2016_Long!$A:$A,D9,MP2016_Long!$B:$B,">=2014",MP2016_Long!$B:$B,"<"&E9) -> 0.0639 | J9: =MIN(0.999999,MAX(0,H9*EXP(I9))) -> 0.0085790537 | K9: =-LN(1-J9) -> 0.0086160656 | L9: =EXP(-K9/Inputs!$B$6) -> 0.99928225 | M9: =M8*L9 -> 0.99570123 | N9: =IFERROR(INDEX(MonthlyCurve!$I:$I,MATCH(A9,MonthlyCurve!$A:$A,0)),"") -> 0.03725093 | O9: =IFERROR(INDEX(MonthlyCurve!$J:$J,MATCH(A9,MonthlyCurve!$A:$A,0)),"") -> 0.98154692 | P9: =F9*M9 -> 8297.5103 | Q9: =G9*M9 -> 24.892531 | R9: =P9+Q9 -> 8322.4028 | S9: =P9*O9 -> 8144.3956 | T9: =Q9*O9 -> 24.433187 | U9: =SUMPRODUCT(R10:R543,O10:O543)/(M9*O9) -> 1247068.5 | W9: Reserve at t=0 | X9: =X7 -> 1268279
A10: 7 | B10: =A10/Inputs!$B$6 -> 0.58333333 | C10: =Inputs!$B$3+B10 -> 65.583333 | D10: =INT(C10) -> 65 | E10: =Inputs!$B$7+1+INT((A10-1)/Inputs!$B$6) -> 2026 | F10: =Inputs!$B$16 -> 8333.3333 | G10: =Inputs!$B$12 -> 25 | H10: =IFERROR(INDEX(RP2014_Qx!$B:$B,MATCH(D10,RP2014_Qx!$A:$A,0)),"") -> 0.008048 | I10: =SUMIFS(MP2016_Long!$C:$C,MP2016_Long!$A:$A,D10,MP2016_Long!$B:$B,">=2014",MP2016_Long!$B:$B,"<"&E10) -> 0.0639 | J10: =MIN(0.999999,MAX(0,H10*EXP(I10))) -> 0.0085790537 | K10: =-LN(1-J10) -> 0.0086160656 | L10: =EXP(-K10/Inputs!$B$6) -> 0.99928225 | M10: =M9*L10 -> 0.99498657 | N10: =IFERROR(INDEX(MonthlyCurve!$I:$I,MATCH(A10,MonthlyCurve!$A:$A,0)),"") -> 0.037201392 | O10: =IFERROR(INDEX(MonthlyCurve!$J:$J,MATCH(A10,MonthlyCurve!$A:$A,0)),"") -> 0.97853296 | P10: =F10*M10 -> 8291.5548 | Q10: =G10*M10 -> 24.874664 | R10: =P10+Q10 -> 8316.4294 | S10: =P10*O10 -> 8113.5596 | T10: =Q10*O10 -> 24.340679 | U10: =SUMPRODUCT(R11:R543,O11:O543)/(M10*O10) -> 1243449.8
A11: 8 | B11: =A11/Inputs!$B$6 -> 0.66666667 | C11: =Inputs!$B$3+B11 -> 65.666667 | D11: =INT(C11) -> 65 | E11: =Inputs!$B$7+1+INT((A11-1)/Inputs!$B$6) -> 2026 | F11: =Inputs!$B$16 -> 8333.3333 | G11: =Inputs!$B$12 -> 25 | H11: =IFERROR(INDEX(RP2014_Qx!$B:$B,MATCH(D11,RP2014_Qx!$A:$A,0)),"") -> 0.008048 | I11: =SUMIFS(MP2016_Long!$C:$C,MP2016_Long!$A:$A,D11,MP2016_Long!$B:$B,">=2014",MP2016_Long!$B:$B,"<"&E11) -> 0.0639 | J11: =MIN(0.999999,MAX(0,H11*EXP(I11))) -> 0.0085790537 | K11: =-LN(1-J11) -> 0.0086160656 | L11: =EXP(-K11/Inputs!$B$6) -> 0.99928225 | M11: =M10*L11 -> 0.99427242 | N11: =IFERROR(INDEX(MonthlyCurve!$I:$I,MATCH(A11,MonthlyCurve!$A:$A,0)),"") -> 0.037151853 | O11: =IFERROR(INDEX(MonthlyCurve!$J:$J,MATCH(A11,MonthlyCurve!$A:$A,0)),"") -> 0.97553631 | P11: =F11*M11 -> 8285.6035 | Q11: =G11*M11 -> 24.856811 | R11: =P11+Q11 -> 8310.4603 | S11: =P11*O11 -> 8082.907 | T11: =Q11*O11 -> 24.248721 | U11: =SUMPRODUCT(R12:R543,O12:O543)/(M11*O11) -> 1239806.9
A12: 9 | B12: =A12/Inputs!$B$6 -> 0.75 | C12: =Inputs!$B$3+B12 -> 65.75 | D12: =INT(C12) -> 65 | E12: =Inputs!$B$7+1+INT((A12-1)/Inputs!$B$6) -> 2026 | F12: =Inputs!$B$16 -> 8333.3333 | G12: =Inputs!$B$12 -> 25 | H12: =IFERROR(INDEX(RP2014_Qx!$B:$B,MATCH(D12,RP2014_Qx!$A:$A,0)),"") -> 0.008048 | I12: =SUMIFS(MP2016_Long!$C:$C,MP2016_Long!$A:$A,D12,MP2016_Long!$B:$B,">=2014",MP2016_Long!$B:$B,"<"&E12) -> 0.0639 | J12: =MIN(0.999999,MAX(0,H12*EXP(I12))) -> 0.0085790537 | K12: =-LN(1-J12) -> 0.0086160656 | L12: =EXP(-K12/Inputs!$B$6) -> 0.99928225 | M12: =M11*L12 -> 0.99355878 | N12: =IFERROR(INDEX(MonthlyCurve!$I:$I,MATCH(A12,MonthlyCurve!$A:$A,0)),"") -> 0.037102315 | O12: =IFERROR(INDEX(MonthlyCurve!$J:$J,MATCH(A12,MonthlyCurve!$A:$A,0)),"") -> 0.97255686 | P12: =F12*M12 -> 8279.6565 | Q12: =G12*M12 -> 24.83897 | R12: =P12+Q12 -> 8304.4955 | S12: =P12*O12 -> 8052.4368 | T12: =Q12*O12 -> 24.15731 | U12: =SUMPRODUCT(R13:R543,O13:O543)/(M12*O12) -> 1236140
A13: 10 | B13: =A13/Inputs!$B$6 -> 0.83333333 | C13: =Inputs!$B$3+B13 -> 65.833333 | D13: =INT(C13) -> 65 | E13: =Inputs!$B$7+1+INT((A13-1)/Inputs!$B$6) -> 2026 | F13: =Inputs!$B$16 -> 8333.3333 | G13: =Inputs!$B$12 -> 25 | H13: =IFERROR(INDEX(RP2014_Qx!$B:$B,MATCH(D13,RP2014_Qx!$A:$A,0)),"") -> 0.008048 | I13: =SUMIFS(MP2016_Long!$C:$C,MP2016_Long!$A:$A,D13,MP2016_Long!$B:$B,">=2014",MP2016_Long!$B:$B,"<"&E13) -> 0.0639 | J13: =MIN(0.999999,MAX(0,H13*EXP(I13))) -> 0.0085790537 | K13: =-LN(1-J13) -> 0.0086160656 | L13: =EXP(-K13/Inputs!$B$6) -> 0.99928225 | M13: =M12*L13 -> 0.99284566 | N13: =IFERROR(INDEX(MonthlyCurve!$I:$I,MATCH(A13,MonthlyCurve!$A:$A,0)),"") -> 0.037052777 | O13: =IFERROR(INDEX(MonthlyCurve!$J:$J,MATCH(A13,MonthlyCurve!$A:$A,0)),"") -> 0.96959452 | P13: =F13*M13 -> 8273.7138 | Q13: =G13*M13 -> 24.821142 | R13: =P13+Q13 -> 8298.535 | S13: =P13*O13 -> 8022.1476 | T13: =Q13*O13 -> 24.066443 | U13: =SUMPRODUCT(R14:R543,O14:O543)/(M13*O13) -> 1232449
A14: 11 | B14: =A14/Inputs!$B$6 -> 0.91666667 | C14: =Inputs!$B$3+B14 -> 65.916667 | D14: =INT(C14) -> 65 | E14: =Inputs!$B$7+1+INT((A14-1)/Inputs!$B$6) -> 2026 | F14: =Inputs!$B$16 -> 8333.3333 | G14: =Inputs!$B$12 -> 25 | H14: =IFERROR(INDEX(RP2014_Qx!$B:$B,MATCH(D14,RP2014_Qx!$A:$A,0)),"") -> 0.008048 | I14: =SUMIFS(MP2016_Long!$C:$C,MP2016_Long!$A:$A,D14,MP2016_Long!$B:$B,">=2014",MP2016_Long!$B:$B,"<"&E14) -> 0.0639 | J14: =MIN(0.999999,MAX(0,H14*EXP(I14))) -> 0.0085790537 | K14: =-LN(1-J14) -> 0.0086160656 | L14: =EXP(-K14/Inputs!$B$6) -> 0.99928225 | M14: =M13*L14 -> 0.99213305 | N14: =IFERROR(INDEX(MonthlyCurve!$I:$I,MATCH(A14,MonthlyCurve!$A:$A,0)),"") -> 0.037003238 | O14: =IFERROR(INDEX(MonthlyCurve!$J:$J,MATCH(A14,MonthlyCurve!$A:$A,0)),"") -> 0.96664919 | P14: =F14*M14 -> 8267.7754 | Q14: =G14*M14 -> 24.803326 | R14: =P14+Q14 -> 8292.5787 | S14: =P14*O14 -> 7992.0384 | T14: =Q14*O14 -> 23.976115 | U14: =SUMPRODUCT(R15:R543,O15:O543)/(M14*O14) -> 1228733.8
A15: 12 | B15: =A15/Inputs!$B$6 -> 1 | C15: =Inputs!$B$3+B15 -> 66 | D15: =INT(C15) -> 66 | E15: =Inputs!$B$7+1+INT((A15-1)/Inputs!$B$6) -> 2026 | F15: =Inputs!$B$16 -> 8333.3333 | G15: =Inputs!$B$12 -> 25 | H15: =IFERROR(INDEX(RP2014_Qx!$B:$B,MATCH(D15,RP2014_Qx!$A:$A,0)),"") -> 0.008821 | I15: =SUMIFS(MP2016_Long!$C:$C,MP2016_Long!$A:$A,D15,MP2016_Long!$B:$B,">=2014",MP2016_Long!$B:$B,"<"&E15) -> 0.0667 | J15: =MIN(0.999999,MAX(0,H15*EXP(I15))) -> 0.0094294262 | K15: =-LN(1-J15) -> 0.0094741647 | L15: =EXP(-K15/Inputs!$B$6) -> 0.9992108 | M15: =M14*L15 -> 0.99135005 | N15: =IFERROR(INDEX(MonthlyCurve!$I:$I,MATCH(A15,MonthlyCurve!$A:$A,0)),"") -> 0.0369537 | O15: =IFERROR(INDEX(MonthlyCurve!$J:$J,MATCH(A15,MonthlyCurve!$A:$A,0)),"") -> 0.96372075 | P15: =F15*M15 -> 8261.2505 | Q15: =G15*M15 -> 24.783751 | R15: =P15+Q15 -> 8286.0342 | S15: =P15*O15 -> 7961.5385 | T15: =Q15*O15 -> 23.884616 | U15: =SUMPRODUCT(R16:R543,O16:O543)/(M15*O15) -> 1225082.6
A16: 13 | B16: =A16/Inputs!$B$6 -> 1.0833333 | C16: =Inputs!$B$3+B16 -> 66.083333 | D16: =INT(C16) -> 66 | E16: =Inputs!$B$7+1+INT((A16-1)/Inputs!$B$6) -> 2027 | F16: =Inputs!$B$16 -> 8333.3333 | G16: =Inputs!$B$12 -> 25 | H16: =IFERROR(INDEX(RP2014_Qx!$B:$B,MATCH(D16,RP2014_Qx!$A:$A,0)),"") -> 0.008821 | I16: =SUMIFS(MP2016_Long!$C:$C,MP2016_Long!$A:$A,D16,MP2016_Long!$B:$B,">=2014",MP2016_Long!$B:$B,"<"&E16) -> 0.0767 | J16: =MIN(0.999999,MAX(0,H16*EXP(I16))) -> 0.0095241935 | K16: =-LN(1-J16) -> 0.0095698387 | L16: =EXP(-K16/Inputs!$B$6) -> 0.99920283 | M16: =M15*L16 -> 0.99055978 | N16: =IFERROR(INDEX(MonthlyCurve!$I:$I,MATCH(A16,MonthlyCurve!$A:$A,0)),"") -> 0.037003858 | O16: =IFERROR(INDEX(MonthlyCurve!$J:$J,MATCH(A16,MonthlyCurve!$A:$A,0)),"") -> 0.96070536 | P16: =F16*M16 -> 8254.6648 | Q16: =G16*M16 -> 24.763995 | R16: =P16+Q16 -> 8279.4288 | S16: =P16*O16 -> 7930.3008 | T16: =Q16*O16 -> 23.790902 | U16: =SUMPRODUCT(R17:R543,O17:O543)/(M16*O16) -> 1221549.9
A17: 14 | B17: =A17/Inputs!$B$6 -> 1.1666667 | C17: =Inputs!$B$3+B17 -> 66.166667 | D17: =INT(C17) -> 66 | E17: =Inputs!$B$7+1+INT((A17-1)/Inputs!$B$6) -> 2027 | F17: =Inputs!$B$16 -> 8333.3333 | G17: =Inputs!$B$12 -> 25 | H17: =IFERROR(INDEX(RP2014_Qx!$B:$B,MATCH(D17,RP2014_Qx!$A:$A,0)),"") -> 0.008821 | I17: =SUMIFS(MP2016_Long!$C:$C,MP2016_Long!$A:$A,D17,MP2016_Long!$B:$B,">=2014",MP2016_Long!$B:$B,"<"&E17) -> 0.0767 | J17: =MIN(0.999999,MAX(0,H17*EXP(I17))) -> 0.0095241935 | K17: =-LN(1-J17) -> 0.0095698387 | L17: =EXP(-K17/Inputs!$B$6) -> 0.99920283 | M17: =M16*L17 -> 0.98977014 | N17: =IFERROR(INDEX(MonthlyCurve!$I:$I,MATCH(A17,MonthlyCurve!$A:$A,0)),"") -> 0.037054017 | O17: =IFERROR(INDEX(MonthlyCurve!$J:$J,MATCH(A17,MonthlyCurve!$A:$A,0)),"") -> 0.9576914 | P17: =F17*M17 -> 8248.0845 | Q17: =G17*M17 -> 24.744253 | R17: =P17+Q17 -> 8272.8287 | S17: =P17*O17 -> 7899.1195 | T17: =Q17*O17 -> 23.697359 | U17: =SUMPRODUCT(R18:R543,O18:O543)/(M17*O17) -> 1218013.5
A18: 15 | B18: =A18/Inputs!$B$6 -> 1.25 | C18: =Inputs!$B$3+B18 -> 66.25 | D18: =INT(C18) -> 66 | E18: =Inputs!$B$7+1+INT((A18-1)/Inputs!$B$6) -> 2027 | F18: =Inputs!$B$16 -> 8333.3333 | G18: =Inputs!$B$12 -> 25 | H18: =IFERROR(INDEX(RP2014_Qx!$B:$B,MATCH(D18,RP2014_Qx!$A:$A,0)),"") -> 0.008821 | I18: =SUMIFS(MP2016_Long!$C:$C,MP2016_Long!$A:$A,D18,MP2016_Long!$B:$B,">=2014",MP2016_Long!$B:$B,"<"&E18) -> 0.0767 | J18: =MIN(0.999999,MAX(0,H18*EXP(I18))) -> 0.0095241935 | K18: =-LN(1-J18) -> 0.0095698387 | L18: =EXP(-K18/Inputs!$B$6) -> 0.99920283 | M18: =M17*L18 -> 0.98898112 | N18: =IFERROR(INDEX(MonthlyCurve!$I:$I,MATCH(A18,MonthlyCurve!$A:$A,0)),"") -> 0.037104175 | O18: =IFERROR(INDEX(MonthlyCurve!$J:$J,MATCH(A18,MonthlyCurve!$A:$A,0)),"") -> 0.95467891 | P18: =F18*M18 -> 8241.5094 | Q18: =G18*M18 -> 24.724528 | R18: =P18+Q18 -> 8266.2339 | S18: =P18*O18 -> 7867.9951 | T18: =Q18*O18 -> 23.603985 | U18: =SUMPRODUCT(R19:R543,O19:O543)/(M18*O18) -> 1214473.4
A19: 16 | B19: =A19/Inputs!$B$6 -> 1.3333333 | C19: =Inputs!$B$3+B19 -> 66.333333 | D19: =INT(C19) -> 66 | E19: =Inputs!$B$7+1+INT((A19-1)/Inputs!$B$6) -> 2027 | F19: =Inputs!$B$16 -> 8333.3333 | G19: =Inputs!$B$12 -> 25 | H19: =IFERROR(INDEX(RP2014_Qx!$B:$B,MATCH(D19,RP2014_Qx!$A:$A,0)),"") -> 0.008821 | I19: =SUMIFS(MP2016_Long!$C:$C,MP2016_Long!$A:$A,D19,MP2016_Long!$B:$B,">=2014",MP2016_Long!$B:$B,"<"&E19) -> 0.0767 | J19: =MIN(0.999999,MAX(0,H19*EXP(I19))) -> 0.0095241935 | K19: =-LN(1-J19) -> 0.0095698387 | L19: =EXP(-K19/Inputs!$B$6) -> 0.99920283 | M19: =M18*L19 -> 0.98819274 | N19: =IFERROR(INDEX(MonthlyCurve!$I:$I,MATCH(A19,MonthlyCurve!$A:$A,0)),"") -> 0.037154333 | O19: =IFERROR(INDEX(MonthlyCurve!$J:$J,MATCH(A19,MonthlyCurve!$A:$A,0)),"") -> 0.95166794 | P19: =F19*M19 -> 8234.9395 | Q19: =G19*M19 -> 24.704818 | R19: =P19+Q19 -> 8259.6443 | S19: =P19*O19 -> 7836.9279 | T19: =Q19*O19 -> 23.510784 | U19: =SUMPRODUCT(R20:R543,O20:O543)/(M19*O19) -> 1210929.5
A20: 17 | B20: =A20/Inputs!$B$6 -> 1.4166667 | C20: =Inputs!$B$3+B20 -> 66.416667 | D20: =INT(C20) -> 66 | E20: =Inputs!$B$7+1+INT((A20-1)/Inputs!$B$6) -> 2027 | F20: =Inputs!$B$16 -> 8333.3333 | G20: =Inputs!$B$12 -> 25 | H20: =IFERROR(INDEX(RP2014_Qx!$B:$B,MATCH(D20,RP2014_Qx!$A:$A,0)),"") -> 0.008821 | I20: =SUMIFS(MP2016_Long!$C:$C,MP2016_Long!$A:$A,D20,MP2016_Long!$B:$B,">=2014",MP2016_Long!$B:$B,"<"&E20) -> 0.0767 | J20: =MIN(0.999999,MAX(0,H20*EXP(I20))) -> 0.0095241935 | K20: =-LN(1-J20) -> 0.0095698387 | L20: =EXP(-K20/Inputs!$B$6) -> 0.99920283 | M20: =M19*L20 -> 0.98740498 | N20: =IFERROR(INDEX(MonthlyCurve!$I:$I,MATCH(A20,MonthlyCurve!$A:$A,0)),"") -> 0.037204492 | O20: =IFERROR(INDEX(MonthlyCurve!$J:$J,MATCH(A20,MonthlyCurve!$A:$A,0)),"") -> 0.94865853 | P20: =F20*M20 -> 8228.3749 | Q20: =G20*M20 -> 24.685125 | R20: =P20+Q20 -> 8253.06 | S20: =P20*O20 -> 7805.918 | T20: =Q20*O20 -> 23.417754 | U20: =SUMPRODUCT(R21:R543,O21:O543)/(M20*O20) -> 1207381.8
A21: 18 | B21: =A21/Inputs!$B$6 -> 1.5 | C21: =Inputs!$B$3+B21 -> 66.5 | D21: =INT(C21) -> 66 | E21: =Inputs!$B$7+1+INT((A21-1)/Inputs!$B$6) -> 2027 | F21: =Inputs!$B$16 -> 8333.3333 | G21: =Inputs!$B$12 -> 25 | H21: =IFERROR(INDEX(RP2014_Qx!$B:$B,MATCH(D21,RP2014_Qx!$A:$A,0)),"") -> 0.008821 | I21: =SUMIFS(MP2016_Long!$C:$C,MP2016_Long!$A:$A,D21,MP2016_Long!$B:$B,">=2014",MP2016_Long!$B:$B,"<"&E21) -> 0.0767 | J21: =MIN(0.999999,MAX(0,H21*EXP(I21))) -> 0.0095241935 | K21: =-LN(1-J21) -> 0.0095698387 | L21: =EXP(-K21/Inputs!$B$6) -> 0.99920283 | M21: =M20*L21 -> 0.98661785 | N21: =IFERROR(INDEX(MonthlyCurve!$I:$I,MATCH(A21,MonthlyCurve!$A:$A,0)),"") -> 0.03725465 | O21: =IFERROR(INDEX(MonthlyCurve!$J:$J,MATCH(A21,MonthlyCurve!$A:$A,0)),"") -> 0.94565074 | P21: =F21*M21 -> 8221.8155 | Q21: =G21*M21 -> 24.665446 | R21: =P21+Q21 -> 8246.4809 | S21: =P21*O21 -> 7774.9659 | T21: =Q21*O21 -> 23.324898 | U21: =SUMPRODUCT(R22:R543,O22:O543)/(M21*O21) -> 1203830
A22: 19 | B22: =A22/Inputs!$B$6 -> 1.5833333 | C22: =Inputs!$B$3+B22 -> 66.583333 | D22: =INT(C22) -> 66 | E22: =Inputs!$B$7+1+INT((A22-1)/Inputs!$B$6) -> 2027 | F22: =Inputs!$B$16 -> 8333.3333 | G22: =Inputs!$B$12 -> 25 | H22: =IFERROR(INDEX(RP2014_Qx!$B:$B,MATCH(D22,RP2014_Qx!$A:$A,0)),"") -> 0.008821 | I22: =SUMIFS(MP2016_Long!$C:$C,MP2016_Long!$A:$A,D22,MP2016_Long!$B:$B,">=2014",MP2016_Long!$B:$B,"<"&E22) -> 0.0767 | J22: =MIN(0.999999,MAX(0,H22*EXP(I22))) -> 0.0095241935 | K22: =-LN(1-J22) -> 0.0095698387 | L22: =EXP(-K22/Inputs!$B$6) -> 0.99920283 | M22: =M21*L22 -> 0.98583135 | N22: =IFERROR(INDEX(MonthlyCurve!$I:$I,MATCH(A22,MonthlyCurve!$A:$A,0)),"") -> 0.037304987 | O22: =IFERROR(INDEX(MonthlyCurve!$J:$J,MATCH(A22,MonthlyCurve!$A:$A,0)),"") -> 0.94264434 | P22: =F22*M22 -> 8215.2613 | Q22: =G22*M22 -> 24.645784 | R22: =P22+Q22 -> 8239.9071 | S22: =P22*O22 -> 7744.0695 | T22: =Q22*O22 -> 23.232209 | U22: =SUMPRODUCT(R23:R543,O23:O543)/(M22*O22) -> 1200274.6
A23: 20 | B23: =A23/Inputs!$B$6 -> 1.6666667 | C23: =Inputs!$B$3+B23 -> 66.666667 | D23: =INT(C23) -> 66 | E23: =Inputs!$B$7+1+INT((A23-1)/Inputs!$B$6) -> 2027 | F23: =Inputs!$B$16 -> 8333.3333 | G23: =Inputs!$B$12 -> 25 | H23: =IFERROR(INDEX(RP2014_Qx!$B:$B,MATCH(D23,RP2014_Qx!$A:$A,0)),"") -> 0.008821 | I23: =SUMIFS(MP2016_Long!$C:$C,MP2016_Long!$A:$A,D23,MP2016_Long!$B:$B,">=2014",MP2016_Long!$B:$B,"<"&E23) -> 0.0767 | J23: =MIN(0.999999,MAX(0,H23*EXP(I23))) -> 0.0095241935 | K23: =-LN(1-J23) -> 0.0095698387 | L23: =EXP(-K23/Inputs!$B$6) -> 0.99920283 | M23: =M22*L23 -> 0.98504548 | N23: =IFERROR(INDEX(MonthlyCurve!$I:$I,MATCH(A23,MonthlyCurve!$A:$A,0)),"") -> 0.037355323 | O23: =IFERROR(INDEX(MonthlyCurve!$J:$J,MATCH(A23,MonthlyCurve!$A:$A,0)),"") -> 0.93963961 | P23: =F23*M23 -> 8208.7123 | Q23: =G23*M23 -> 24.626137 | R23: =P23+Q23 -> 8233.3385 | S23: =P23*O23 -> 7713.2312 | T23: =Q23*O23 -> 23.139694 | U23: =SUMPRODUCT(R24:R543,O24:O543)/(M23*O23) -> 1196715.1
A24: 21 | B24: =A24/Inputs!$B$6 -> 1.75 | C24: =Inputs!$B$3+B24 -> 66.75 | D24: =INT(C24) -> 66 | E24: =Inputs!$B$7+1+INT((A24-1)/Inputs!$B$6) -> 2027 | F24: =Inputs!$B$16 -> 8333.3333 | G24: =Inputs!$B$12 -> 25 | H24: =IFERROR(INDEX(RP2014_Qx!$B:$B,MATCH(D24,RP2014_Qx!$A:$A,0)),"") -> 0.008821 | I24: =SUMIFS(MP2016_Long!$C:$C,MP2016_Long!$A:$A,D24,MP2016_Long!$B:$B,">=2014",MP2016_Long!$B:$B,"<"&E24) -> 0.0767 | J24: =MIN(0.999999,MAX(0,H24*EXP(I24))) -> 0.0095241935 | K24: =-LN(1-J24) -> 0.0095698387 | L24: =EXP(-K24/Inputs!$B$6) -> 0.99920283 | M24: =M23*L24 -> 0.98426023 | N24: =IFERROR(INDEX(MonthlyCurve!$I:$I,MATCH(A24,MonthlyCurve!$A:$A,0)),"") -> 0.03740566 | O24: =IFERROR(INDEX(MonthlyCurve!$J:$J,MATCH(A24,MonthlyCurve!$A:$A,0)),"") -> 0.9366366 | P24: =F24*M24 -> 8202.1686 | Q24: =G24*M24 -> 24.606506 | R24: =P24+Q24 -> 8226.7751 | S24: =P24*O24 -> 7682.4513 | T24: =Q24*O24 -> 23.047354 | U24: =SUMPRODUCT(R25:R543,O25:O543)/(M24*O24) -> 1193151.4
A25: 22 | B25: =A25/Inputs!$B$6 -> 1.8333333 | C25: =Inputs!$B$3+B25 -> 66.833333 | D25: =INT(C25) -> 66 | E25: =Inputs!$B$7+1+INT((A25-1)/Inputs!$B$6) -> 2027 | F25: =Inputs!$B$16 -> 8333.3333 | G25: =Inputs!$B$12 -> 25 | H25: =IFERROR(INDEX(RP2014_Qx!$B:$B,MATCH(D25,RP2014_Qx!$A:$A,0)),"") -> 0.008821 | I25: =SUMIFS(MP2016_Long!$C:$C,MP2016_Long!$A:$A,D25,MP2016_Long!$B:$B,">=2014",MP2016_Long!$B:$B,"<"&E25) -> 0.0767 | J25: =MIN(0.999999,MAX(0,H25*EXP(I25))) -> 0.0095241935 | K25: =-LN(1-J25) -> 0.0095698387 | L25: =EXP(-K25/Inputs!$B$6) -> 0.99920283 | M25: =M24*L25 -> 0.98347561 | N25: =IFERROR(INDEX(MonthlyCurve!$I:$I,MATCH(A25,MonthlyCurve!$A:$A,0)),"") -> 0.037455997 | O25: =IFERROR(INDEX(MonthlyCurve!$J:$J,MATCH(A25,MonthlyCurve!$A:$A,0)),"") -> 0.93363536 | P25: =F25*M25 -> 8195.6301 | Q25: =G25*M25 -> 24.58689 | R25: =P25+Q25 -> 8220.217 | S25: =P25*O25 -> 7651.73 | T25: =Q25*O25 -> 22.95519 | U25: =SUMPRODUCT(R26:R543,O26:O543)/(M25*O25) -> 1189583.5
A26: 23 | B26: =A26/Inputs!$B$6 -> 1.9166667 | C26: =Inputs!$B$3+B26 -> 66.916667 | D26: =INT(C26) -> 66 | E26: =Inputs!$B$7+1+INT((A26-1)/Inputs!$B$6) -> 2027 | F26: =Inputs!$B$16 -> 8333.3333 | G26: =Inputs!$B$12 -> 25 | H26: =IFERROR(INDEX(RP2014_Qx!$B:$B,MATCH(D26,RP2014_Qx!$A:$A,0)),"") -> 0.008821 | I26: =SUMIFS(MP2016_Long!$C:$C,MP2016_Long!$A:$A,D26,MP2016_Long!$B:$B,">=2014",MP2016_Long!$B:$B,"<"&E26) -> 0.0767 | J26: =MIN(0.999999,MAX(0,H26*EXP(I26))) -> 0.0095241935 | K26: =-LN(1-J26) -> 0.0095698387 | L26: =EXP(-K26/Inputs!$B$6) -> 0.99920283 | M26: =M25*L26 -> 0.98269162 | N26: =IFERROR(INDEX(MonthlyCurve!$I:$I,MATCH(A26,MonthlyCurve!$A:$A,0)),"") -> 0.037506333 | O26: =IFERROR(INDEX(MonthlyCurve!$J:$J,MATCH(A26,MonthlyCurve!$A:$A,0)),"") -> 0.93063592 | P26: =F26*M26 -> 8189.0968 | Q26: =G26*M26 -> 24.56729 | R26: =P26+Q26 -> 8213.6641 | S26: =P26*O26 -> 7621.0676 | T26: =Q26*O26 -> 22.863203 | U26: =SUMPRODUCT(R27:R543,O27:O543)/(M26*O26) -> 1186011.3
A27: 24 | B27: =A27/Inputs!$B$6 -> 2 | C27: =Inputs!$B$3+B27 -> 67 | D27: =INT(C27) -> 67 | E27: =Inputs!$B$7+1+INT((A27-1)/Inputs!$B$6) -> 2027 | F27: =Inputs!$B$16 -> 8333.3333 | G27: =Inputs!$B$12 -> 25 | H27: =IFERROR(INDEX(RP2014_Qx!$B:$B,MATCH(D27,RP2014_Qx!$A:$A,0)),"") -> 0.009679 | I27: =SUMIFS(MP2016_Long!$C:$C,MP2016_Long!$A:$A,D27,MP2016_Long!$B:$B,">=2014",MP2016_Long!$B:$B,"<"&E27) -> 0.0809 | J27: =MIN(0.999999,MAX(0,H27*EXP(I27))) -> 0.010494576 | K27: =-LN(1-J27) -> 0.010550033 | L27: =EXP(-K27/Inputs!$B$6) -> 0.99912122 | M27: =M26*L27 -> 0.98182804 | N27: =IFERROR(INDEX(MonthlyCurve!$I:$I,MATCH(A27,MonthlyCurve!$A:$A,0)),"") -> 0.03755667 | O27: =IFERROR(INDEX(MonthlyCurve!$J:$J,MATCH(A27,MonthlyCurve!$A:$A,0)),"") -> 0.92763834 | P27: =F27*M27 -> 8181.9004 | Q27: =G27*M27 -> 24.545701 | R27: =P27+Q27 -> 8206.4461 | S27: =P27*O27 -> 7589.8445 | T27: =Q27*O27 -> 22.769533 | U27: =SUMPRODUCT(R28:R543,O28:O543)/(M27*O27) -> 1182532
A28: 25 | B28: =A28/Inputs!$B$6 -> 2.0833333 | C28: =Inputs!$B$3+B28 -> 67.083333 | D28: =INT(C28) -> 67 | E28: =Inputs!$B$7+1+INT((A28-1)/Inputs!$B$6) -> 2028 | F28: =Inputs!$B$16 -> 8333.3333 | G28: =Inputs!$B$12 -> 25 | H28: =IFERROR(INDEX(RP2014_Qx!$B:$B,MATCH(D28,RP2014_Qx!$A:$A,0)),"") -> 0.009679 | I28: =SUMIFS(MP2016_Long!$C:$C,MP2016_Long!$A:$A,D28,MP2016_Long!$B:$B,">=2014",MP2016_Long!$B:$B,"<"&E28) -> 0.0909 | J28: =MIN(0.999999,MAX(0,H28*EXP(I28))) -> 0.010600049 | K28: =-LN(1-J28) -> 0.010656629 | L28: =EXP(-K28/Inputs!$B$6) -> 0.99911234 | M28: =M27*L28 -> 0.98095651 | N28: =IFERROR(INDEX(MonthlyCurve!$I:$I,MATCH(A28,MonthlyCurve!$A:$A,0)),"") -> 0.037556293 | O28: =IFERROR(INDEX(MonthlyCurve!$J:$J,MATCH(A28,MonthlyCurve!$A:$A,0)),"") -> 0.92474036 | P28: =F28*M28 -> 8174.6376 | Q28: =G28*M28 -> 24.523913 | R28: =P28+Q28 -> 8199.1615 | S28: =P28*O28 -> 7559.4173 | T28: =Q28*O28 -> 22.678252 | U28: =SUMPRODUCT(R29:R543,O29:O543)/(M28*O28) -> 1178933.4
A29: 26 | B29: =A29/Inputs!$B$6 -> 2.1666667 | C29: =Inputs!$B$3+B29 -> 67.166667 | D29: =INT(C29) -> 67 | E29: =Inputs!$B$7+1+INT((A29-1)/Inputs!$B$6) -> 2028 | F29: =Inputs!$B$16 -> 8333.3333 | G29: =Inputs!$B$12 -> 25 | H29: =IFERROR(INDEX(RP2014_Qx!$B:$B,MATCH(D29,RP2014_Qx!$A:$A,0)),"") -> 0.009679 | I29: =SUMIFS(MP2016_Long!$C:$C,MP2016_Long!$A:$A,D29,MP2016_Long!$B:$B,">=2014",MP2016_Long!$B:$B,"<"&E29) -> 0.0909 | J29: =MIN(0.999999,MAX(0,H29*EXP(I29))) -> 0.010600049 | K29: =-LN(1-J29) -> 0.010656629 | L29: =EXP(-K29/Inputs!$B$6) -> 0.99911234 | M29: =M28*L29 -> 0.98008576 | N29: =IFERROR(INDEX(MonthlyCurve!$I:$I,MATCH(A29,MonthlyCurve!$A:$A,0)),"") -> 0.037555917 | O29: =IFERROR(INDEX(MonthlyCurve!$J:$J,MATCH(A29,MonthlyCurve!$A:$A,0)),"") -> 0.92185148 | P29: =F29*M29 -> 8167.3813 | Q29: =G29*M29 -> 24.502144 | R29: =P29+Q29 -> 8191.8835 | S29: =P29*O29 -> 7529.1126 | T29: =Q29*O29 -> 22.587338 | U29: =SUMPRODUCT(R30:R543,O30:O543)/(M29*O29) -> 1175320.3
A30: 27 | B30: =A30/Inputs!$B$6 -> 2.25 | C30: =Inputs!$B$3+B30 -> 67.25 | D30: =INT(C30) -> 67 | E30: =Inputs!$B$7+1+INT((A30-1)/Inputs!$B$6) -> 2028 | F30: =Inputs!$B$16 -> 8333.3333 | G30: =Inputs!$B$12 -> 25 | H30: =IFERROR(INDEX(RP2014_Qx!$B:$B,MATCH(D30,RP2014_Qx!$A:$A,0)),"") -> 0.009679 | I30: =SUMIFS(MP2016_Long!$C:$C,MP2016_Long!$A:$A,D30,MP2016_Long!$B:$B,">=2014",MP2016_Long!$B:$B,"<"&E30) -> 0.0909 | J30: =MIN(0.999999,MAX(0,H30*EXP(I30))) -> 0.010600049 | K30: =-LN(1-J30) -> 0.010656629 | L30: =EXP(-K30/Inputs!$B$6) -> 0.99911234 | M30: =M29*L30 -> 0.97921578 | N30: =IFERROR(INDEX(MonthlyCurve!$I:$I,MATCH(A30,MonthlyCurve!$A:$A,0)),"") -> 0.03755554 | O30: =IFERROR(INDEX(MonthlyCurve!$J:$J,MATCH(A30,MonthlyCurve!$A:$A,0)),"") -> 0.91897169 | P30: =F30*M30 -> 8160.1315 | Q30: =G30*M30 -> 24.480394 | R30: =P30+Q30 -> 8184.6119 | S30: =P30*O30 -> 7498.9298 | T30: =Q30*O30 -> 22.496789 | U30: =SUMPRODUCT(R31:R543,O31:O543)/(M30*O30) -> 1171692.6
A31: 28 | B31: =A31/Inputs!$B$6 -> 2.3333333 | C31: =Inputs!$B$3+B31 -> 67.333333 | D31: =INT(C31) -> 67 | E31: =Inputs!$B$7+1+INT((A31-1)/Inputs!$B$6) -> 2028 | F31: =Inputs!$B$16 -> 8333.3333 | G31: =Inputs!$B$12 -> 25 | H31: =IFERROR(INDEX(RP2014_Qx!$B:$B,MATCH(D31,RP2014_Qx!$A:$A,0)),"") -> 0.009679 | I31: =SUMIFS(MP2016_Long!$C:$C,MP2016_Long!$A:$A,D31,MP2016_Long!$B:$B,">=2014",MP2016_Long!$B:$B,"<"&E31) -> 0.0909 | J31: =MIN(0.999999,MAX(0,H31*EXP(I31))) -> 0.010600049 | K31: =-LN(1-J31) -> 0.010656629 | L31: =EXP(-K31/Inputs!$B$6) -> 0.99911234 | M31: =M30*L31 -> 0.97834657 | N31: =IFERROR(INDEX(MonthlyCurve!$I:$I,MATCH(A31,MonthlyCurve!$A:$A,0)),"") -> 0.037555163 | O31: =IFERROR(INDEX(MonthlyCurve!$J:$J,MATCH(A31,MonthlyCurve!$A:$A,0)),"") -> 0.91610095 | P31: =F31*M31 -> 8152.8881 | Q31: =G31*M31 -> 24.458664 | R31: =P31+Q31 -> 8177.3468 | S31: =P31*O31 -> 7468.8685 | T31: =Q31*O31 -> 22.406606 | U31: =SUMPRODUCT(R32:R543,O32:O543)/(M31*O31) -> 1168050.2
A32: 29 | B32: =A32/Inputs!$B$6 -> 2.4166667 | C32: =Inputs!$B$3+B32 -> 67.416667 | D32: =INT(C32) -> 67 | E32: =Inputs!$B$7+1+INT((A32-1)/Inputs!$B$6) -> 2028 | F32: =Inputs!$B$16 -> 8333.3333 | G32: =Inputs!$B$12 -> 25 | H32: =IFERROR(INDEX(RP2014_Qx!$B:$B,MATCH(D32,RP2014_Qx!$A:$A,0)),"") -> 0.009679 | I32: =SUMIFS(MP2016_Long!$C:$C,MP2016_Long!$A:$A,D32,MP2016_Long!$B:$B,">=2014",MP2016_Long!$B:$B,"<"&E32) -> 0.0909 | J32: =MIN(0.999999,MAX(0,H32*EXP(I32))) -> 0.010600049 | K32: =-LN(1-J32) -> 0.010656629 | L32: =EXP(-K32/Inputs!$B$6) -> 0.99911234 | M32: =M31*L32 -> 0.97747813 | N32: =IFERROR(INDEX(MonthlyCurve!$I:$I,MATCH(A32,MonthlyCurve!$A:$A,0)),"") -> 0.037554787 | O32: =IFERROR(INDEX(MonthlyCurve!$J:$J,MATCH(A32,MonthlyCurve!$A:$A,0)),"") -> 0.91323923 | P32: =F32*M32 -> 8145.6511 | Q32: =G32*M32 -> 24.436953 | R32: =P32+Q32 -> 8170.0881 | S32: =P32*O32 -> 7438.9282 | T32: =Q32*O32 -> 22.316785 | U32: =SUMPRODUCT(R33:R543,O33:O543)/(M32*O32) -> 1164393
A33: 30 | B33: =A33/Inputs!$B$6 -> 2.5 | C33: =Inputs!$B$3+B33 -> 67.5 | D33: =INT(C33) -> 67 | E33: =Inputs!$B$7+1+INT((A33-1)/Inputs!$B$6) -> 2028 | F33: =Inputs!$B$16 -> 8333.3333 | G33: =Inputs!$B$12 -> 25 | H33: =IFERROR(INDEX(RP2014_Qx!$B:$B,MATCH(D33,RP2014_Qx!$A:$A,0)),"") -> 0.009679 | I33: =SUMIFS(MP2016_Long!$C:$C,MP2016_Long!$A:$A,D33,MP2016_Long!$B:$B,">=2014",MP2016_Long!$B:$B,"<"&E33) -> 0.0909 | J33: =MIN(0.999999,MAX(0,H33*EXP(I33))) -> 0.010600049 | K33: =-LN(1-J33) -> 0.010656629 | L33: =EXP(-K33/Inputs!$B$6) -> 0.99911234 | M33: =M32*L33 -> 0.97661047 | N33: =IFERROR(INDEX(MonthlyCurve!$I:$I,MATCH(A33,MonthlyCurve!$A:$A,0)),"") -> 0.03755441 | O33: =IFERROR(INDEX(MonthlyCurve!$J:$J,MATCH(A33,MonthlyCurve!$A:$A,0)),"") -> 0.91038652 | P33: =F33*M33 -> 8138.4206 | Q33: =G33*M33 -> 24.415262 | R33: =P33+Q33 -> 8162.8358 | S33: =P33*O33 -> 7409.1083 | T33: =Q33*O33 -> 22.227325 | U33: =SUMPRODUCT(R34:R543,O34:O543)/(M33*O33) -> 1160721.1
A34: 31 | B34: =A34/Inputs!$B$6 -> 2.5833333 | C34: =Inputs!$B$3+B34 -> 67.583333 | D34: =INT(C34) -> 67 | E34: =Inputs!$B$7+1+INT((A34-1)/Inputs!$B$6) -> 2028 | F34: =Inputs!$B$16 -> 8333.3333 | G34: =Inputs!$B$12 -> 25 | H34: =IFERROR(INDEX(RP2014_Qx!$B:$B,MATCH(D34,RP2014_Qx!$A:$A,0)),"") -> 0.009679 | I34: =SUMIFS(MP2016_Long!$C:$C,MP2016_Long!$A:$A,D34,MP2016_Long!$B:$B,">=2014",MP2016_Long!$B:$B,"<"&E34) -> 0.0909 | J34: =MIN(0.999999,MAX(0,H34*EXP(I34))) -> 0.010600049 | K34: =-LN(1-J34) -> 0.010656629 | L34: =EXP(-K34/Inputs!$B$6) -> 0.99911234 | M34: =M33*L34 -> 0.97574357 | N34: =IFERROR(INDEX(MonthlyCurve!$I:$I,MATCH(A34,MonthlyCurve!$A:$A,0)),"") -> 0.037554158 | O34: =IFERROR(INDEX(MonthlyCurve!$J:$J,MATCH(A34,MonthlyCurve!$A:$A,0)),"") -> 0.90754248 | P34: =F34*M34 -> 8131.1964 | Q34: =G34*M34 -> 24.393589 | R34: =P34+Q34 -> 8155.59 | S34: =P34*O34 -> 7379.4061 | T34: =Q34*O34 -> 22.138218 | U34: =SUMPRODUCT(R35:R543,O35:O543)/(M34*O34) -> 1157034.7
A35: 32 | B35: =A35/Inputs!$B$6 -> 2.6666667 | C35: =Inputs!$B$3+B35 -> 67.666667 | D35: =INT(C35) -> 67 | E35: =Inputs!$B$7+1+INT((A35-1)/Inputs!$B$6) -> 2028 | F35: =Inputs!$B$16 -> 8333.3333 | G35: =Inputs!$B$12 -> 25 | H35: =IFERROR(INDEX(RP2014_Qx!$B:$B,MATCH(D35,RP2014_Qx!$A:$A,0)),"") -> 0.009679 | I35: =SUMIFS(MP2016_Long!$C:$C,MP2016_Long!$A:$A,D35,MP2016_Long!$B:$B,">=2014",MP2016_Long!$B:$B,"<"&E35) -> 0.0909 | J35: =MIN(0.999999,MAX(0,H35*EXP(I35))) -> 0.010600049 | K35: =-LN(1-J35) -> 0.010656629 | L35: =EXP(-K35/Inputs!$B$6) -> 0.99911234 | M35: =M34*L35 -> 0.97487744 | N35: =IFERROR(INDEX(MonthlyCurve!$I:$I,MATCH(A35,MonthlyCurve!$A:$A,0)),"") -> 0.037553907 | O35: =IFERROR(INDEX(MonthlyCurve!$J:$J,MATCH(A35,MonthlyCurve!$A:$A,0)),"") -> 0.90470736 | P35: =F35*M35 -> 8123.9787 | Q35: =G35*M35 -> 24.371936 | R35: =P35+Q35 -> 8148.3506 | S35: =P35*O35 -> 7349.8233 | T35: =Q35*O35 -> 22.04947 | U35: =SUMPRODUCT(R36:R543,O36:O543)/(M35*O35) -> 1153333.4
A36: 33 | B36: =A36/Inputs!$B$6 -> 2.75 | C36: =Inputs!$B$3+B36 -> 67.75 | D36: =INT(C36) -> 67 | E36: =Inputs!$B$7+1+INT((A36-1)/Inputs!$B$6) -> 2028 | F36: =Inputs!$B$16 -> 8333.3333 | G36: =Inputs!$B$12 -> 25 | H36: =IFERROR(INDEX(RP2014_Qx!$B:$B,MATCH(D36,RP2014_Qx!$A:$A,0)),"") -> 0.009679 | I36: =SUMIFS(MP2016_Long!$C:$C,MP2016_Long!$A:$A,D36,MP2016_Long!$B:$B,">=2014",MP2016_Long!$B:$B,"<"&E36) -> 0.0909 | J36: =MIN(0.999999,MAX(0,H36*EXP(I36))) -> 0.010600049 | K36: =-LN(1-J36) -> 0.010656629 | L36: =EXP(-K36/Inputs!$B$6) -> 0.99911234 | M36: =M35*L36 -> 0.97401209 | N36: =IFERROR(INDEX(MonthlyCurve!$I:$I,MATCH(A36,MonthlyCurve!$A:$A,0)),"") -> 0.037553655 | O36: =IFERROR(INDEX(MonthlyCurve!$J:$J,MATCH(A36,MonthlyCurve!$A:$A,0)),"") -> 0.90188113 | P36: =F36*M36 -> 8116.7674 | Q36: =G36*M36 -> 24.350302 | R36: =P36+Q36 -> 8141.1177 | S36: =P36*O36 -> 7320.3593 | T36: =Q36*O36 -> 21.961078 | U36: =SUMPRODUCT(R37:R543,O37:O543)/(M36*O36) -> 1149617.1
A37: 34 | B37: =A37/Inputs!$B$6 -> 2.8333333 | C37: =Inputs!$B$3+B37 -> 67.833333 | D37: =INT(C37) -> 67 | E37: =Inputs!$B$7+1+INT((A37-1)/Inputs!$B$6) -> 2028 | F37: =Inputs!$B$16 -> 8333.3333 | G37: =Inputs!$B$12 -> 25 | H37: =IFERROR(INDEX(RP2014_Qx!$B:$B,MATCH(D37,RP2014_Qx!$A:$A,0)),"") -> 0.009679 | I37: =SUMIFS(MP2016_Long!$C:$C,MP2016_Long!$A:$A,D37,MP2016_Long!$B:$B,">=2014",MP2016_Long!$B:$B,"<"&E37) -> 0.0909 | J37: =MIN(0.999999,MAX(0,H37*EXP(I37))) -> 0.010600049 | K37: =-LN(1-J37) -> 0.010656629 | L37: =EXP(-K37/Inputs!$B$6) -> 0.99911234 | M37: =M36*L37 -> 0.9731475 | N37: =IFERROR(INDEX(MonthlyCurve!$I:$I,MATCH(A37,MonthlyCurve!$A:$A,0)),"") -> 0.037553403 | O37: =IFERROR(INDEX(MonthlyCurve!$J:$J,MATCH(A37,MonthlyCurve!$A:$A,0)),"") -> 0.89906377 | P37: =F37*M37 -> 8109.5625 | Q37: =G37*M37 -> 24.328687 | R37: =P37+Q37 -> 8133.8912 | S37: =P37*O37 -> 7291.0138 | T37: =Q37*O37 -> 21.873041 | U37: =SUMPRODUCT(R38:R543,O38:O543)/(M37*O37) -> 1145885.9
A38: 35 | B38: =A38/Inputs!$B$6 -> 2.9166667 | C38: =Inputs!$B$3+B38 -> 67.916667 | D38: =INT(C38) -> 67 | E38: =Inputs!$B$7+1+INT((A38-1)/Inputs!$B$6) -> 2028 | F38: =Inputs!$B$16 -> 8333.3333 | G38: =Inputs!$B$12 -> 25 | H38: =IFERROR(INDEX(RP2014_Qx!$B:$B,MATCH(D38,RP2014_Qx!$A:$A,0)),"") -> 0.009679 | I38: =SUMIFS(MP2016_Long!$C:$C,MP2016_Long!$A:$A,D38,MP2016_Long!$B:$B,">=2014",MP2016_Long!$B:$B,"<"&E38) -> 0.0909 | J38: =MIN(0.999999,MAX(0,H38*EXP(I38))) -> 0.010600049 | K38: =-LN(1-J38) -> 0.010656629 | L38: =EXP(-K38/Inputs!$B$6) -> 0.99911234 | M38: =M37*L38 -> 0.97228367 | N38: =IFERROR(INDEX(MonthlyCurve!$I:$I,MATCH(A38,MonthlyCurve!$A:$A,0)),"") -> 0.037553152 | O38: =IFERROR(INDEX(MonthlyCurve!$J:$J,MATCH(A38,MonthlyCurve!$A:$A,0)),"") -> 0.89625525 | P38: =F38*M38 -> 8102.3639 | Q38: =G38*M38 -> 24.307092 | R38: =P38+Q38 -> 8126.671 | S38: =P38*O38 -> 7261.7862 | T38: =Q38*O38 -> 21.785359 | U38: =SUMPRODUCT(R39:R543,O39:O543)/(M38*O38) -> 1142139.6
A39: 36 | B39: =A39/Inputs!$B$6 -> 3 | C39: =Inputs!$B$3+B39 -> 68 | D39: =INT(C39) -> 68 | E39: =Inputs!$B$7+1+INT((A39-1)/Inputs!$B$6) -> 2028 | F39: =Inputs!$B$16 -> 8333.3333 | G39: =Inputs!$B$12 -> 25 | H39: =IFERROR(INDEX(RP2014_Qx!$B:$B,MATCH(D39,RP2014_Qx!$A:$A,0)),"") -> 0.010633 | I39: =SUMIFS(MP2016_Long!$C:$C,MP2016_Long!$A:$A,D39,MP2016_Long!$B:$B,">=2014",MP2016_Long!$B:$B,"<"&E39) -> 0.096 | J39: =MIN(0.999999,MAX(0,H39*EXP(I39))) -> 0.011704371 | K39: =-LN(1-J39) -> 0.011773406 | L39: =EXP(-K39/Inputs!$B$6) -> 0.99901936 | M39: =M38*L39 -> 0.97133022 | N39: =IFERROR(INDEX(MonthlyCurve!$I:$I,MATCH(A39,MonthlyCurve!$A:$A,0)),"") -> 0.0375529 | O39: =IFERROR(INDEX(MonthlyCurve!$J:$J,MATCH(A39,MonthlyCurve!$A:$A,0)),"") -> 0.89345554 | P39: =F39*M39 -> 8094.4185 | Q39: =G39*M39 -> 24.283255 | R39: =P39+Q39 -> 8118.7017 | S39: =P39*O39 -> 7232.0031 | T39: =Q39*O39 -> 21.696009 | U39: =SUMPRODUCT(R40:R543,O40:O543)/(M39*O39) -> 1138484.8
A40: 37 | B40: =A40/Inputs!$B$6 -> 3.0833333 | C40: =Inputs!$B$3+B40 -> 68.083333 | D40: =INT(C40) -> 68 | E40: =Inputs!$B$7+1+INT((A40-1)/Inputs!$B$6) -> 2029 | F40: =Inputs!$B$16 -> 8333.3333 | G40: =Inputs!$B$12 -> 25 | H40: =IFERROR(INDEX(RP2014_Qx!$B:$B,MATCH(D40,RP2014_Qx!$A:$A,0)),"") -> 0.010633 | I40: =SUMIFS(MP2016_Long!$C:$C,MP2016_Long!$A:$A,D40,MP2016_Long!$B:$B,">=2014",MP2016_Long!$B:$B,"<"&E40) -> 0.106 | J40: =MIN(0.999999,MAX(0,H40*EXP(I40))) -> 0.011822002 | K40: =-LN(1-J40) -> 0.011892438 | L40: =EXP(-K40/Inputs!$B$6) -> 0.99900945 | M40: =M39*L40 -> 0.97036807 | N40: =IFERROR(INDEX(MonthlyCurve!$I:$I,MATCH(A40,MonthlyCurve!$A:$A,0)),"") -> 0.037591702 | O40: =IFERROR(INDEX(MonthlyCurve!$J:$J,MATCH(A40,MonthlyCurve!$A:$A,0)),"") -> 0.89055738 | P40: =F40*M40 -> 8086.4006 | Q40: =G40*M40 -> 24.259202 | R40: =P40+Q40 -> 8110.6598 | S40: =P40*O40 -> 7201.4037 | T40: =Q40*O40 -> 21.604211 | U40: =SUMPRODUCT(R41:R543,O41:O543)/(M40*O40) -> 1134964
A41: 38 | B41: =A41/Inputs!$B$6 -> 3.1666667 | C41: =Inputs!$B$3+B41 -> 68.166667 | D41: =INT(C41) -> 68 | E41: =Inputs!$B$7+1+INT((A41-1)/Inputs!$B$6) -> 2029 | F41: =Inputs!$B$16 -> 8333.3333 | G41: =Inputs!$B$12 -> 25 | H41: =IFERROR(INDEX(RP2014_Qx!$B:$B,MATCH(D41,RP2014_Qx!$A:$A,0)),"") -> 0.010633 | I41: =SUMIFS(MP2016_Long!$C:$C,MP2016_Long!$A:$A,D41,MP2016_Long!$B:$B,">=2014",MP2016_Long!$B:$B,"<"&E41) -> 0.106 | J41: =MIN(0.999999,MAX(0,H41*EXP(I41))) -> 0.011822002 | K41: =-LN(1-J41) -> 0.011892438 | L41: =EXP(-K41/Inputs!$B$6) -> 0.99900945 | M41: =M40*L41 -> 0.96940688 | N41: =IFERROR(INDEX(MonthlyCurve!$I:$I,MATCH(A41,MonthlyCurve!$A:$A,0)),"") -> 0.037630503 | O41: =IFERROR(INDEX(MonthlyCurve!$J:$J,MATCH(A41,MonthlyCurve!$A:$A,0)),"") -> 0.88766287 | P41: =F41*M41 -> 8078.3906 | Q41: =G41*M41 -> 24.235172 | R41: =P41+Q41 -> 8102.6258 | S41: =P41*O41 -> 7170.8874 | T41: =Q41*O41 -> 21.512662 | U41: =SUMPRODUCT(R42:R543,O42:O543)/(M41*O41) -> 1131435.6
A42: 39 | B42: =A42/Inputs!$B$6 -> 3.25 | C42: =Inputs!$B$3+B42 -> 68.25 | D42: =INT(C42) -> 68 | E42: =Inputs!$B$7+1+INT((A42-1)/Inputs!$B$6) -> 2029 | F42: =Inputs!$B$16 -> 8333.3333 | G42: =Inputs!$B$12 -> 25 | H42: =IFERROR(INDEX(RP2014_Qx!$B:$B,MATCH(D42,RP2014_Qx!$A:$A,0)),"") -> 0.010633 | I42: =SUMIFS(MP2016_Long!$C:$C,MP2016_Long!$A:$A,D42,MP2016_Long!$B:$B,">=2014",MP2016_Long!$B:$B,"<"&E42) -> 0.106 | J42: =MIN(0.999999,MAX(0,H42*EXP(I42))) -> 0.011822002 | K42: =-LN(1-J42) -> 0.011892438 | L42: =EXP(-K42/Inputs!$B$6) -> 0.99900945 | M42: =M41*L42 -> 0.96844663 | N42: =IFERROR(INDEX(MonthlyCurve!$I:$I,MATCH(A42,MonthlyCurve!$A:$A,0)),"") -> 0.037669305 | O42: =IFERROR(INDEX(MonthlyCurve!$J:$J,MATCH(A42,MonthlyCurve!$A:$A,0)),"") -> 0.88477205 | P42: =F42*M42 -> 8070.3886 | Q42: =G42*M42 -> 24.211166 | R42: =P42+Q42 -> 8094.5998 | S42: =P42*O42 -> 7140.4543 | T42: =Q42*O42 -> 21.421363 | U42: =SUMPRODUCT(R43:R543,O43:O543)/(M42*O42) -> 1127899.6
A43: 40 | B43: =A43/Inputs!$B$6 -> 3.3333333 | C43: =Inputs!$B$3+B43 -> 68.333333 | D43: =INT(C43) -> 68 | E43: =Inputs!$B$7+1+INT((A43-1)/Inputs!$B$6) -> 2029 | F43: =Inputs!$B$16 -> 8333.3333 | G43: =Inputs!$B$12 -> 25 | H43: =IFERROR(INDEX(RP2014_Qx!$B:$B,MATCH(D43,RP2014_Qx!$A:$A,0)),"") -> 0.010633 | I43: =SUMIFS(MP2016_Long!$C:$C,MP2016_Long!$A:$A,D43,MP2016_Long!$B:$B,">=2014",MP2016_Long!$B:$B,"<"&E43) -> 0.106 | J43: =MIN(0.999999,MAX(0,H43*EXP(I43))) -> 0.011822002 | K43: =-LN(1-J43) -> 0.011892438 | L43: =EXP(-K43/Inputs!$B$6) -> 0.99900945 | M43: =M42*L43 -> 0.96748734 | N43: =IFERROR(INDEX(MonthlyCurve!$I:$I,MATCH(A43,MonthlyCurve!$A:$A,0)),"") -> 0.037708107 | O43: =IFERROR(INDEX(MonthlyCurve!$J:$J,MATCH(A43,MonthlyCurve!$A:$A,0)),"") -> 0.88188494 | P43: =F43*M43 -> 8062.3945 | Q43: =G43*M43 -> 24.187184 | R43: =P43+Q43 -> 8086.5817 | S43: =P43*O43 -> 7110.1043 | T43: =Q43*O43 -> 21.330313 | U43: =SUMPRODUCT(R44:R543,O44:O543)/(M43*O43) -> 1124355.7
A44: 41 | B44: =A44/Inputs!$B$6 -> 3.4166667 | C44: =Inputs!$B$3+B44 -> 68.416667 | D44: =INT(C44) -> 68 | E44: =Inputs!$B$7+1+INT((A44-1)/Inputs!$B$6) -> 2029 | F44: =Inputs!$B$16 -> 8333.3333 | G44: =Inputs!$B$12 -> 25 | H44: =IFERROR(INDEX(RP2014_Qx!$B:$B,MATCH(D44,RP2014_Qx!$A:$A,0)),"") -> 0.010633 | I44: =SUMIFS(MP2016_Long!$C:$C,MP2016_Long!$A:$A,D44,MP2016_Long!$B:$B,">=2014",MP2016_Long!$B:$B,"<"&E44) -> 0.106 | J44: =MIN(0.999999,MAX(0,H44*EXP(I44))) -> 0.011822002 | K44: =-LN(1-J44) -> 0.011892438 | L44: =EXP(-K44/Inputs!$B$6) -> 0.99900945 | M44: =M43*L44 -> 0.966529 | N44: =IFERROR(INDEX(MonthlyCurve!$I:$I,MATCH(A44,MonthlyCurve!$A:$A,0)),"") -> 0.037746908 | O44: =IFERROR(INDEX(MonthlyCurve!$J:$J,MATCH(A44,MonthlyCurve!$A:$A,0)),"") -> 0.87900156 | P44: =F44*M44 -> 8054.4084 | Q44: =G44*M44 -> 24.163225 | R44: =P44+Q44 -> 8078.5716 | S44: =P44*O44 -> 7079.8375 | T44: =Q44*O44 -> 21.239513 | U44: =SUMPRODUCT(R45:R543,O45:O543)/(M44*O44) -> 1120804.1
A45: 42 | B45: =A45/Inputs!$B$6 -> 3.5 | C45: =Inputs!$B$3+B45 -> 68.5 | D45: =INT(C45) -> 68 | E45: =Inputs!$B$7+1+INT((A45-1)/Inputs!$B$6) -> 2029 | F45: =Inputs!$B$16 -> 8333.3333 | G45: =Inputs!$B$12 -> 25 | H45: =IFERROR(INDEX(RP2014_Qx!$B:$B,MATCH(D45,RP2014_Qx!$A:$A,0)),"") -> 0.010633 | I45: =SUMIFS(MP2016_Long!$C:$C,MP2016_Long!$A:$A,D45,MP2016_Long!$B:$B,">=2014",MP2016_Long!$B:$B,"<"&E45) -> 0.106 | J45: =MIN(0.999999,MAX(0,H45*EXP(I45))) -> 0.011822002 | K45: =-LN(1-J45) -> 0.011892438 | L45: =EXP(-K45/Inputs!$B$6) -> 0.99900945 | M45: =M44*L45 -> 0.96557161 | N45: =IFERROR(INDEX(MonthlyCurve!$I:$I,MATCH(A45,MonthlyCurve!$A:$A,0)),"") -> 0.03778571 | O45: =IFERROR(INDEX(MonthlyCurve!$J:$J,MATCH(A45,MonthlyCurve!$A:$A,0)),"") -> 0.87612195 | P45: =F45*M45 -> 8046.4301 | Q45: =G45*M45 -> 24.13929 | R45: =P45+Q45 -> 8070.5694 | S45: =P45*O45 -> 7049.654 | T45: =Q45*O45 -> 21.148962 | U45: =SUMPRODUCT(R46:R543,O46:O543)/(M45*O45) -> 1117244.6
A46: 43 | B46: =A46/Inputs!$B$6 -> 3.5833333 | C46: =Inputs!$B$3+B46 -> 68.583333 | D46: =INT(C46) -> 68 | E46: =Inputs!$B$7+1+INT((A46-1)/Inputs!$B$6) -> 2029 | F46: =Inputs!$B$16 -> 8333.3333 | G46: =Inputs!$B$12 -> 25 | H46: =IFERROR(INDEX(RP2014_Qx!$B:$B,MATCH(D46,RP2014_Qx!$A:$A,0)),"") -> 0.010633 | I46: =SUMIFS(MP2016_Long!$C:$C,MP2016_Long!$A:$A,D46,MP2016_Long!$B:$B,">=2014",MP2016_Long!$B:$B,"<"&E46) -> 0.106 | J46: =MIN(0.999999,MAX(0,H46*EXP(I46))) -> 0.011822002 | K46: =-LN(1-J46) -> 0.011892438 | L46: =EXP(-K46/Inputs!$B$6) -> 0.99900945 | M46: =M45*L46 -> 0.96461517 | N46: =IFERROR(INDEX(MonthlyCurve!$I:$I,MATCH(A46,MonthlyCurve!$A:$A,0)),"") -> 0.037824687 | O46: =IFERROR(INDEX(MonthlyCurve!$J:$J,MATCH(A46,MonthlyCurve!$A:$A,0)),"") -> 0.87324558 | P46: =F46*M46 -> 8038.4598 | Q46: =G46*M46 -> 24.115379 | R46: =P46+Q46 -> 8062.5751 | S46: =P46*O46 -> 7019.5494 | T46: =Q46*O46 -> 21.058648 | U46: =SUMPRODUCT(R47:R543,O47:O543)/(M46*O46) -> 1113677.7
A47: 44 | B47: =A47/Inputs!$B$6 -> 3.6666667 | C47: =Inputs!$B$3+B47 -> 68.666667 | D47: =INT(C47) -> 68 | E47: =Inputs!$B$7+1+INT((A47-1)/Inputs!$B$6) -> 2029 | F47: =Inputs!$B$16 -> 8333.3333 | G47: =Inputs!$B$12 -> 25 | H47: =IFERROR(INDEX(RP2014_Qx!$B:$B,MATCH(D47,RP2014_Qx!$A:$A,0)),"") -> 0.010633 | I47: =SUMIFS(MP2016_Long!$C:$C,MP2016_Long!$A:$A,D47,MP2016_Long!$B:$B,">=2014",MP2016_Long!$B:$B,"<"&E47) -> 0.106 | J47: =MIN(0.999999,MAX(0,H47*EXP(I47))) -> 0.011822002 | K47: =-LN(1-J47) -> 0.011892438 | L47: =EXP(-K47/Inputs!$B$6) -> 0.99900945 | M47: =M46*L47 -> 0.96365967 | N47: =IFERROR(INDEX(MonthlyCurve!$I:$I,MATCH(A47,MonthlyCurve!$A:$A,0)),"") -> 0.037863663 | O47: =IFERROR(INDEX(MonthlyCurve!$J:$J,MATCH(A47,MonthlyCurve!$A:$A,0)),"") -> 0.87037299 | P47: =F47*M47 -> 8030.4973 | Q47: =G47*M47 -> 24.091492 | R47: =P47+Q47 -> 8054.5888 | S47: =P47*O47 -> 6989.528 | T47: =Q47*O47 -> 20.968584 | U47: =SUMPRODUCT(R48:R543,O48:O543)/(M47*O47) -> 1110102.9
A48: 45 | B48: =A48/Inputs!$B$6 -> 3.75 | C48: =Inputs!$B$3+B48 -> 68.75 | D48: =INT(C48) -> 68 | E48: =Inputs!$B$7+1+INT((A48-1)/Inputs!$B$6) -> 2029 | F48: =Inputs!$B$16 -> 8333.3333 | G48: =Inputs!$B$12 -> 25 | H48: =IFERROR(INDEX(RP2014_Qx!$B:$B,MATCH(D48,RP2014_Qx!$A:$A,0)),"") -> 0.010633 | I48: =SUMIFS(MP2016_Long!$C:$C,MP2016_Long!$A:$A,D48,MP2016_Long!$B:$B,">=2014",MP2016_Long!$B:$B,"<"&E48) -> 0.106 | J48: =MIN(0.999999,MAX(0,H48*EXP(I48))) -> 0.011822002 | K48: =-LN(1-J48) -> 0.011892438 | L48: =EXP(-K48/Inputs!$B$6) -> 0.99900945 | M48: =M47*L48 -> 0.96270513 | N48: =IFERROR(INDEX(MonthlyCurve!$I:$I,MATCH(A48,MonthlyCurve!$A:$A,0)),"") -> 0.03790264 | O48: =IFERROR(INDEX(MonthlyCurve!$J:$J,MATCH(A48,MonthlyCurve!$A:$A,0)),"") -> 0.86750422 | P48: =F48*M48 -> 8022.5427 | Q48: =G48*M48 -> 24.067628 | R48: =P48+Q48 -> 8046.6103 | S48: =P48*O48 -> 6959.5897 | T48: =Q48*O48 -> 20.878769 | U48: =SUMPRODUCT(R49:R543,O49:O543)/(M48*O48) -> 1106519.9
A49: 46 | B49: =A49/Inputs!$B$6 -> 3.8333333 | C49: =Inputs!$B$3+B49 -> 68.833333 | D49: =INT(C49) -> 68 | E49: =Inputs!$B$7+1+INT((A49-1)/Inputs!$B$6) -> 2029 | F49: =Inputs!$B$16 -> 8333.3333 | G49: =Inputs!$B$12 -> 25 | H49: =IFERROR(INDEX(RP2014_Qx!$B:$B,MATCH(D49,RP2014_Qx!$A:$A,0)),"") -> 0.010633 | I49: =SUMIFS(MP2016_Long!$C:$C,MP2016_Long!$A:$A,D49,MP2016_Long!$B:$B,">=2014",MP2016_Long!$B:$B,"<"&E49) -> 0.106 | J49: =MIN(0.999999,MAX(0,H49*EXP(I49))) -> 0.011822002 | K49: =-LN(1-J49) -> 0.011892438 | L49: =EXP(-K49/Inputs!$B$6) -> 0.99900945 | M49: =M48*L49 -> 0.96175152 | N49: =IFERROR(INDEX(MonthlyCurve!$I:$I,MATCH(A49,MonthlyCurve!$A:$A,0)),"") -> 0.037941617 | O49: =IFERROR(INDEX(MonthlyCurve!$J:$J,MATCH(A49,MonthlyCurve!$A:$A,0)),"") -> 0.86463929 | P49: =F49*M49 -> 8014.596 | Q49: =G49*M49 -> 24.043788 | R49: =P49+Q49 -> 8038.6398 | S49: =P49*O49 -> 6929.7346 | T49: =Q49*O49 -> 20.789204 | U49: =SUMPRODUCT(R50:R543,O50:O543)/(M49*O49) -> 1102928.7
A50: 47 | B50: =A50/Inputs!$B$6 -> 3.9166667 | C50: =Inputs!$B$3+B50 -> 68.916667 | D50: =INT(C50) -> 68 | E50: =Inputs!$B$7+1+INT((A50-1)/Inputs!$B$6) -> 2029 | F50: =Inputs!$B$16 -> 8333.3333 | G50: =Inputs!$B$12 -> 25 | H50: =IFERROR(INDEX(RP2014_Qx!$B:$B,MATCH(D50,RP2014_Qx!$A:$A,0)),"") -> 0.010633 | I50: =SUMIFS(MP2016_Long!$C:$C,MP2016_Long!$A:$A,D50,MP2016_Long!$B:$B,">=2014",MP2016_Long!$B:$B,"<"&E50) -> 0.106 | J50: =MIN(0.999999,MAX(0,H50*EXP(I50))) -> 0.011822002 | K50: =-LN(1-J50) -> 0.011892438 | L50: =EXP(-K50/Inputs!$B$6) -> 0.99900945 | M50: =M49*L50 -> 0.96079886 | N50: =IFERROR(INDEX(MonthlyCurve!$I:$I,MATCH(A50,MonthlyCurve!$A:$A,0)),"") -> 0.037980593 | O50: =IFERROR(INDEX(MonthlyCurve!$J:$J,MATCH(A50,MonthlyCurve!$A:$A,0)),"") -> 0.86177822 | P50: =F50*M50 -> 8006.6572 | Q50: =G50*M50 -> 24.019972 | R50: =P50+Q50 -> 8030.6772 | S50: =P50*O50 -> 6899.9628 | T50: =Q50*O50 -> 20.699888 | U50: =SUMPRODUCT(R51:R543,O51:O543)/(M50*O50) -> 1099329.3
A51: 48 | B51: =A51/Inputs!$B$6 -> 4 | C51: =Inputs!$B$3+B51 -> 69 | D51: =INT(C51) -> 69 | E51: =Inputs!$B$7+1+INT((A51-1)/Inputs!$B$6) -> 2029 | F51: =Inputs!$B$16 -> 8333.3333 | G51: =Inputs!$B$12 -> 25 | H51: =IFERROR(INDEX(RP2014_Qx!$B:$B,MATCH(D51,RP2014_Qx!$A:$A,0)),"") -> 0.011692 | I51: =SUMIFS(MP2016_Long!$C:$C,MP2016_Long!$A:$A,D51,MP2016_Long!$B:$B,">=2014",MP2016_Long!$B:$B,"<"&E51) -> 0.112 | J51: =MIN(0.999999,MAX(0,H51*EXP(I51))) -> 0.013077652 | K51: =-LN(1-J51) -> 0.013163918 | L51: =EXP(-K51/Inputs!$B$6) -> 0.99890361 | M51: =M50*L51 -> 0.95974545 | N51: =IFERROR(INDEX(MonthlyCurve!$I:$I,MATCH(A51,MonthlyCurve!$A:$A,0)),"") -> 0.03801957 | O51: =IFERROR(INDEX(MonthlyCurve!$J:$J,MATCH(A51,MonthlyCurve!$A:$A,0)),"") -> 0.85892104 | P51: =F51*M51 -> 7997.8788 | Q51: =G51*M51 -> 23.993636 | R51: =P51+Q51 -> 8021.8724 | S51: =P51*O51 -> 6869.5464 | T51: =Q51*O51 -> 20.608639 | U51: =SUMPRODUCT(R52:R543,O52:O543)/(M51*O51) -> 1095838.5
A52: 49 | B52: =A52/Inputs!$B$6 -> 4.0833333 | C52: =Inputs!$B$3+B52 -> 69.083333 | D52: =INT(C52) -> 69 | E52: =Inputs!$B$7+1+INT((A52-1)/Inputs!$B$6) -> 2030 | F52: =Inputs!$B$16 -> 8333.3333 | G52: =Inputs!$B$12 -> 25 | H52: =IFERROR(INDEX(RP2014_Qx!$B:$B,MATCH(D52,RP2014_Qx!$A:$A,0)),"") -> 0.011692 | I52: =SUMIFS(MP2016_Long!$C:$C,MP2016_Long!$A:$A,D52,MP2016_Long!$B:$B,">=2014",MP2016_Long!$B:$B,"<"&E52) -> 0.122 | J52: =MIN(0.999999,MAX(0,H52*EXP(I52))) -> 0.013209085 | K52: =-LN(1-J52) -> 0.013297101 | L52: =EXP(-K52/Inputs!$B$6) -> 0.99889252 | M52: =M51*L52 -> 0.95868256 | N52: =IFERROR(INDEX(MonthlyCurve!$I:$I,MATCH(A52,MonthlyCurve!$A:$A,0)),"") -> 0.038058762 | O52: =IFERROR(INDEX(MonthlyCurve!$J:$J,MATCH(A52,MonthlyCurve!$A:$A,0)),"") -> 0.85606702 | P52: =F52*M52 -> 7989.0213 | Q52: =G52*M52 -> 23.967064 | R52: =P52+Q52 -> 8012.9884 | S52: =P52*O52 -> 6839.1377 | T52: =Q52*O52 -> 20.517413 | U52: =SUMPRODUCT(R53:R543,O53:O543)/(M52*O52) -> 1092352.6
A53: 50 | B53: =A53/Inputs!$B$6 -> 4.1666667 | C53: =Inputs!$B$3+B53 -> 69.166667 | D53: =INT(C53) -> 69 | E53: =Inputs!$B$7+1+INT((A53-1)/Inputs!$B$6) -> 2030 | F53: =Inputs!$B$16 -> 8333.3333 | G53: =Inputs!$B$12 -> 25 | H53: =IFERROR(INDEX(RP2014_Qx!$B:$B,MATCH(D53,RP2014_Qx!$A:$A,0)),"") -> 0.011692 | I53: =SUMIFS(MP2016_Long!$C:$C,MP2016_Long!$A:$A,D53,MP2016_Long!$B:$B,">=2014",MP2016_Long!$B:$B,"<"&E53) -> 0.122 | J53: =MIN(0.999999,MAX(0,H53*EXP(I53))) -> 0.013209085 | K53: =-LN(1-J53) -> 0.013297101 | L53: =EXP(-K53/Inputs!$B$6) -> 0.99889252 | M53: =M52*L53 -> 0.95762084 | N53: =IFERROR(INDEX(MonthlyCurve!$I:$I,MATCH(A53,MonthlyCurve!$A:$A,0)),"") -> 0.038097953 | O53: =IFERROR(INDEX(MonthlyCurve!$J:$J,MATCH(A53,MonthlyCurve!$A:$A,0)),"") -> 0.85321691 | P53: =F53*M53 -> 7980.1736 | Q53: =G53*M53 -> 23.940521 | R53: =P53+Q53 -> 8004.1141 | S53: =P53*O53 -> 6808.8191 | T53: =Q53*O53 -> 20.426457 | U53: =SUMPRODUCT(R54:R543,O54:O543)/(M53*O53) -> 1088858.3
A54: 51 | B54: =A54/Inputs!$B$6 -> 4.25 | C54: =Inputs!$B$3+B54 -> 69.25 | D54: =INT(C54) -> 69 | E54: =Inputs!$B$7+1+INT((A54-1)/Inputs!$B$6) -> 2030 | F54: =Inputs!$B$16 -> 8333.3333 | G54: =Inputs!$B$12 -> 25 | H54: =IFERROR(INDEX(RP2014_Qx!$B:$B,MATCH(D54,RP2014_Qx!$A:$A,0)),"") -> 0.011692 | I54: =SUMIFS(MP2016_Long!$C:$C,MP2016_Long!$A:$A,D54,MP2016_Long!$B:$B,">=2014",MP2016_Long!$B:$B,"<"&E54) -> 0.122 | J54: =MIN(0.999999,MAX(0,H54*EXP(I54))) -> 0.013209085 | K54: =-LN(1-J54) -> 0.013297101 | L54: =EXP(-K54/Inputs!$B$6) -> 0.99889252 | M54: =M53*L54 -> 0.95656029 | N54: =IFERROR(INDEX(MonthlyCurve!$I:$I,MATCH(A54,MonthlyCurve!$A:$A,0)),"") -> 0.038137145 | O54: =IFERROR(INDEX(MonthlyCurve!$J:$J,MATCH(A54,MonthlyCurve!$A:$A,0)),"") -> 0.85037073 | P54: =F54*M54 -> 7971.3358 | Q54: =G54*M54 -> 23.914007 | R54: =P54+Q54 -> 7995.2498 | S54: =P54*O54 -> 6778.5906 | T54: =Q54*O54 -> 20.335772 | U54: =SUMPRODUCT(R55:R543,O55:O543)/(M54*O54) -> 1085355.6
A55: 52 | B55: =A55/Inputs!$B$6 -> 4.3333333 | C55: =Inputs!$B$3+B55 -> 69.333333 | D55: =INT(C55) -> 69 | E55: =Inputs!$B$7+1+INT((A55-1)/Inputs!$B$6) -> 2030 | F55: =Inputs!$B$16 -> 8333.3333 | G55: =Inputs!$B$12 -> 25 | H55: =IFERROR(INDEX(RP2014_Qx!$B:$B,MATCH(D55,RP2014_Qx!$A:$A,0)),"") -> 0.011692 | I55: =SUMIFS(MP2016_Long!$C:$C,MP2016_Long!$A:$A,D55,MP2016_Long!$B:$B,">=2014",MP2016_Long!$B:$B,"<"&E55) -> 0.122 | J55: =MIN(0.999999,MAX(0,H55*EXP(I55))) -> 0.013209085 | K55: =-LN(1-J55) -> 0.013297101 | L55: =EXP(-K55/Inputs!$B$6) -> 0.99889252 | M55: =M54*L55 -> 0.95550092 | N55: =IFERROR(INDEX(MonthlyCurve!$I:$I,MATCH(A55,MonthlyCurve!$A:$A,0)),"") -> 0.038176337 | O55: =IFERROR(INDEX(MonthlyCurve!$J:$J,MATCH(A55,MonthlyCurve!$A:$A,0)),"") -> 0.84752852 | P55: =F55*M55 -> 7962.5077 | Q55: =G55*M55 -> 23.887523 | R55: =P55+Q55 -> 7986.3952 | S55: =P55*O55 -> 6748.4523 | T55: =Q55*O55 -> 20.245357 | U55: =SUMPRODUCT(R56:R543,O56:O543)/(M55*O55) -> 1081844.4
A56: 53 | B56: =A56/Inputs!$B$6 -> 4.4166667 | C56: =Inputs!$B$3+B56 -> 69.416667 | D56: =INT(C56) -> 69 | E56: =Inputs!$B$7+1+INT((A56-1)/Inputs!$B$6) -> 2030 | F56: =Inputs!$B$16 -> 8333.3333 | G56: =Inputs!$B$12 -> 25 | H56: =IFERROR(INDEX(RP2014_Qx!$B:$B,MATCH(D56,RP2014_Qx!$A:$A,0)),"") -> 0.011692 | I56: =SUMIFS(MP2016_Long!$C:$C,MP2016_Long!$A:$A,D56,MP2016_Long!$B:$B,">=2014",MP2016_Long!$B:$B,"<"&E56) -> 0.122 | J56: =MIN(0.999999,MAX(0,H56*EXP(I56))) -> 0.013209085 | K56: =-LN(1-J56) -> 0.013297101 | L56: =EXP(-K56/Inputs!$B$6) -> 0.99889252 | M56: =M55*L56 -> 0.95444273 | N56: =IFERROR(INDEX(MonthlyCurve!$I:$I,MATCH(A56,MonthlyCurve!$A:$A,0)),"") -> 0.038215528 | O56: =IFERROR(INDEX(MonthlyCurve!$J:$J,MATCH(A56,MonthlyCurve!$A:$A,0)),"") -> 0.84469028 | P56: =F56*M56 -> 7953.6894 | Q56: =G56*M56 -> 23.861068 | R56: =P56+Q56 -> 7977.5504 | S56: =P56*O56 -> 6718.4041 | T56: =Q56*O56 -> 20.155212 | U56: =SUMPRODUCT(R57:R543,O57:O543)/(M56*O56) -> 1078324.7
A57: 54 | B57: =A57/Inputs!$B$6 -> 4.5 | C57: =Inputs!$B$3+B57 -> 69.5 | D57: =INT(C57) -> 69 | E57: =Inputs!$B$7+1+INT((A57-1)/Inputs!$B$6) -> 2030 | F57: =Inputs!$B$16 -> 8333.3333 | G57: =Inputs!$B$12 -> 25 | H57: =IFERROR(INDEX(RP2014_Qx!$B:$B,MATCH(D57,RP2014_Qx!$A:$A,0)),"") -> 0.011692 | I57: =SUMIFS(MP2016_Long!$C:$C,MP2016_Long!$A:$A,D57,MP2016_Long!$B:$B,">=2014",MP2016_Long!$B:$B,"<"&E57) -> 0.122 | J57: =MIN(0.999999,MAX(0,H57*EXP(I57))) -> 0.013209085 | K57: =-LN(1-J57) -> 0.013297101 | L57: =EXP(-K57/Inputs!$B$6) -> 0.99889252 | M57: =M56*L57 -> 0.9533857 | N57: =IFERROR(INDEX(MonthlyCurve!$I:$I,MATCH(A57,MonthlyCurve!$A:$A,0)),"") -> 0.03825472 | O57: =IFERROR(INDEX(MonthlyCurve!$J:$J,MATCH(A57,MonthlyCurve!$A:$A,0)),"") -> 0.84185605 | P57: =F57*M57 -> 7944.8808 | Q57: =G57*M57 -> 23.834643 | R57: =P57+Q57 -> 7968.7155 | S57: =P57*O57 -> 6688.446 | T57: =Q57*O57 -> 20.065338 | U57: =SUMPRODUCT(R58:R543,O58:O543)/(M57*O57) -> 1074796.2
A58: 55 | B58: =A58/Inputs!$B$6 -> 4.5833333 | C58: =Inputs!$B$3+B58 -> 69.583333 | D58: =INT(C58) -> 69 | E58: =Inputs!$B$7+1+INT((A58-1)/Inputs!$B$6) -> 2030 | F58: =Inputs!$B$16 -> 8333.3333 | G58: =Inputs!$B$12 -> 25 | H58: =IFERROR(INDEX(RP2014_Qx!$B:$B,MATCH(D58,RP2014_Qx!$A:$A,0)),"") -> 0.011692 | I58: =SUMIFS(MP2016_Long!$C:$C,MP2016_Long!$A:$A,D58,MP2016_Long!$B:$B,">=2014",MP2016_Long!$B:$B,"<"&E58) -> 0.122 | J58: =MIN(0.999999,MAX(0,H58*EXP(I58))) -> 0.013209085 | K58: =-LN(1-J58) -> 0.013297101 | L58: =EXP(-K58/Inputs!$B$6) -> 0.99889252 | M58: =M57*L58 -> 0.95232985 | N58: =IFERROR(INDEX(MonthlyCurve!$I:$I,MATCH(A58,MonthlyCurve!$A:$A,0)),"") -> 0.038294158 | O58: =IFERROR(INDEX(MonthlyCurve!$J:$J,MATCH(A58,MonthlyCurve!$A:$A,0)),"") -> 0.8390249 | P58: =F58*M58 -> 7936.0821 | Q58: =G58*M58 -> 23.808246 | R58: =P58+Q58 -> 7959.8903 | S58: =P58*O58 -> 6658.5705 | T58: =Q58*O58 -> 19.975711 | U58: =SUMPRODUCT(R59:R543,O59:O543)/(M58*O58) -> 1071260.3
A59: 56 | B59: =A59/Inputs!$B$6 -> 4.6666667 | C59: =Inputs!$B$3+B59 -> 69.666667 | D59: =INT(C59) -> 69 | E59: =Inputs!$B$7+1+INT((A59-1)/Inputs!$B$6) -> 2030 | F59: =Inputs!$B$16 -> 8333.3333 | G59: =Inputs!$B$12 -> 25 | H59: =IFERROR(INDEX(RP2014_Qx!$B:$B,MATCH(D59,RP2014_Qx!$A:$A,0)),"") -> 0.011692 | I59: =SUMIFS(MP2016_Long!$C:$C,MP2016_Long!$A:$A,D59,MP2016_Long!$B:$B,">=2014",MP2016_Long!$B:$B,"<"&E59) -> 0.122 | J59: =MIN(0.999999,MAX(0,H59*EXP(I59))) -> 0.013209085 | K59: =-LN(1-J59) -> 0.013297101 | L59: =EXP(-K59/Inputs!$B$6) -> 0.99889252 | M59: =M58*L59 -> 0.95127516 | N59: =IFERROR(INDEX(MonthlyCurve!$I:$I,MATCH(A59,MonthlyCurve!$A:$A,0)),"") -> 0.038333597 | O59: =IFERROR(INDEX(MonthlyCurve!$J:$J,MATCH(A59,MonthlyCurve!$A:$A,0)),"") -> 0.83619778 | P59: =F59*M59 -> 7927.293 | Q59: =G59*M59 -> 23.781879 | R59: =P59+Q59 -> 7951.0749 | S59: =P59*O59 -> 6628.7848 | T59: =Q59*O59 -> 19.886354 | U59: =SUMPRODUCT(R60:R543,O60:O543)/(M59*O59) -> 1067715.5
A60: 57 | B60: =A60/Inputs!$B$6 -> 4.75 | C60: =Inputs!$B$3+B60 -> 69.75 | D60: =INT(C60) -> 69 | E60: =Inputs!$B$7+1+INT((A60-1)/Inputs!$B$6) -> 2030 | F60: =Inputs!$B$16 -> 8333.3333 | G60: =Inputs!$B$12 -> 25 | H60: =IFERROR(INDEX(RP2014_Qx!$B:$B,MATCH(D60,RP2014_Qx!$A:$A,0)),"") -> 0.011692 | I60: =SUMIFS(MP2016_Long!$C:$C,MP2016_Long!$A:$A,D60,MP2016_Long!$B:$B,">=2014",MP2016_Long!$B:$B,"<"&E60) -> 0.122 | J60: =MIN(0.999999,MAX(0,H60*EXP(I60))) -> 0.013209085 | K60: =-LN(1-J60) -> 0.013297101 | L60: =EXP(-K60/Inputs!$B$6) -> 0.99889252 | M60: =M59*L60 -> 0.95022165 | N60: =IFERROR(INDEX(MonthlyCurve!$I:$I,MATCH(A60,MonthlyCurve!$A:$A,0)),"") -> 0.038373035 | O60: =IFERROR(INDEX(MonthlyCurve!$J:$J,MATCH(A60,MonthlyCurve!$A:$A,0)),"") -> 0.8333747 | P60: =F60*M60 -> 7918.5137 | Q60: =G60*M60 -> 23.755541 | R60: =P60+Q60 -> 7942.2693 | S60: =P60*O60 -> 6599.089 | T60: =Q60*O60 -> 19.797267 | U60: =SUMPRODUCT(R61:R543,O61:O543)/(M60*O60) -> 1064161.9
A61: 58 | B61: =A61/Inputs!$B$6 -> 4.8333333 | C61: =Inputs!$B$3+B61 -> 69.833333 | D61: =INT(C61) -> 69 | E61: =Inputs!$B$7+1+INT((A61-1)/Inputs!$B$6) -> 2030 | F61: =Inputs!$B$16 -> 8333.3333 | G61: =Inputs!$B$12 -> 25 | H61: =IFERROR(INDEX(RP2014_Qx!$B:$B,MATCH(D61,RP2014_Qx!$A:$A,0)),"") -> 0.011692 | I61: =SUMIFS(MP2016_Long!$C:$C,MP2016_Long!$A:$A,D61,MP2016_Long!$B:$B,">=2014",MP2016_Long!$B:$B,"<"&E61) -> 0.122 | J61: =MIN(0.999999,MAX(0,H61*EXP(I61))) -> 0.013209085 | K61: =-LN(1-J61) -> 0.013297101 | L61: =EXP(-K61/Inputs!$B$6) -> 0.99889252 | M61: =M60*L61 -> 0.9491693 | N61: =IFERROR(INDEX(MonthlyCurve!$I:$I,MATCH(A61,MonthlyCurve!$A:$A,0)),"") -> 0.038412473 | O61: =IFERROR(INDEX(MonthlyCurve!$J:$J,MATCH(A61,MonthlyCurve!$A:$A,0)),"") -> 0.8305557 | P61: =F61*M61 -> 7909.7441 | Q61: =G61*M61 -> 23.729232 | R61: =P61+Q61 -> 7933.4734 | S61: =P61*O61 -> 6569.4831 | T61: =Q61*O61 -> 19.708449 | U61: =SUMPRODUCT(R62:R543,O62:O543)/(M61*O61) -> 1060599.3
A62: 59 | B62: =A62/Inputs!$B$6 -> 4.9166667 | C62: =Inputs!$B$3+B62 -> 69.916667 | D62: =INT(C62) -> 69 | E62: =Inputs!$B$7+1+INT((A62-1)/Inputs!$B$6) -> 2030 | F62: =Inputs!$B$16 -> 8333.3333 | G62: =Inputs!$B$12 -> 25 | H62: =IFERROR(INDEX(RP2014_Qx!$B:$B,MATCH(D62,RP2014_Qx!$A:$A,0)),"") -> 0.011692 | I62: =SUMIFS(MP2016_Long!$C:$C,MP2016_Long!$A:$A,D62,MP2016_Long!$B:$B,">=2014",MP2016_Long!$B:$B,"<"&E62) -> 0.122 | J62: =MIN(0.999999,MAX(0,H62*EXP(I62))) -> 0.013209085 | K62: =-LN(1-J62) -> 0.013297101 | L62: =EXP(-K62/Inputs!$B$6) -> 0.99889252 | M62: =M61*L62 -> 0.94811811 | N62: =IFERROR(INDEX(MonthlyCurve!$I:$I,MATCH(A62,MonthlyCurve!$A:$A,0)),"") -> 0.038451912 | O62: =IFERROR(INDEX(MonthlyCurve!$J:$J,MATCH(A62,MonthlyCurve!$A:$A,0)),"") -> 0.82774079 | P62: =F62*M62 -> 7900.9843 | Q62: =G62*M62 -> 23.702953 | R62: =P62+Q62 -> 7924.6872 | S62: =P62*O62 -> 6539.9669 | T62: =Q62*O62 -> 19.619901 | U62: =SUMPRODUCT(R63:R543,O63:O543)/(M62*O62) -> 1057027.7
A63: 60 | B63: =A63/Inputs!$B$6 -> 5 | C63: =Inputs!$B$3+B63 -> 70 | D63: =INT(C63) -> 70 | E63: =Inputs!$B$7+1+INT((A63-1)/Inputs!$B$6) -> 2030 | F63: =Inputs!$B$16 -> 8333.3333 | G63: =Inputs!$B$12 -> 25 | H63: =IFERROR(INDEX(RP2014_Qx!$B:$B,MATCH(D63,RP2014_Qx!$A:$A,0)),"") -> 0.012868 | I63: =SUMIFS(MP2016_Long!$C:$C,MP2016_Long!$A:$A,D63,MP2016_Long!$B:$B,">=2014",MP2016_Long!$B:$B,"<"&E63) -> 0.1277 | J63: =MIN(0.999999,MAX(0,H63*EXP(I63))) -> 0.014620777 | K63: =-LN(1-J63) -> 0.014728714 | L63: =EXP(-K63/Inputs!$B$6) -> 0.99877336 | M63: =M62*L63 -> 0.94695511 | N63: =IFERROR(INDEX(MonthlyCurve!$I:$I,MATCH(A63,MonthlyCurve!$A:$A,0)),"") -> 0.03849135 | O63: =IFERROR(INDEX(MonthlyCurve!$J:$J,MATCH(A63,MonthlyCurve!$A:$A,0)),"") -> 0.82493 | P63: =F63*M63 -> 7891.2926 | Q63: =G63*M63 -> 23.673878 | R63: =P63+Q63 -> 7914.9665 | S63: =P63*O63 -> 6509.764 | T63: =Q63*O63 -> 19.529292 | U63: =SUMPRODUCT(R64:R543,O64:O543)/(M63*O63) -> 1053573.6
A64: 61 | B64: =A64/Inputs!$B$6 -> 5.0833333 | C64: =Inputs!$B$3+B64 -> 70.083333 | D64: =INT(C64) -> 70 | E64: =Inputs!$B$7+1+INT((A64-1)/Inputs!$B$6) -> 2031 | F64: =Inputs!$B$16 -> 8333.3333 | G64: =Inputs!$B$12 -> 25 | H64: =IFERROR(INDEX(RP2014_Qx!$B:$B,MATCH(D64,RP2014_Qx!$A:$A,0)),"") -> 0.012868 | I64: =SUMIFS(MP2016_Long!$C:$C,MP2016_Long!$A:$A,D64,MP2016_Long!$B:$B,">=2014",MP2016_Long!$B:$B,"<"&E64) -> 0.1377 | J64: =MIN(0.999999,MAX(0,H64*EXP(I64))) -> 0.014767718 | K64: =-LN(1-J64) -> 0.014877847 | L64: =EXP(-K64/Inputs!$B$6) -> 0.99876095 | M64: =M63*L64 -> 0.94578179 | N64: =IFERROR(INDEX(MonthlyCurve!$I:$I,MATCH(A64,MonthlyCurve!$A:$A,0)),"") -> 0.038571763 | O64: =IFERROR(INDEX(MonthlyCurve!$J:$J,MATCH(A64,MonthlyCurve!$A:$A,0)),"") -> 0.82195212 | P64: =F64*M64 -> 7881.5149 | Q64: =G64*M64 -> 23.644545 | R64: =P64+Q64 -> 7905.1594 | S64: =P64*O64 -> 6478.2279 | T64: =Q64*O64 -> 19.434684 | U64: =SUMPRODUCT(R65:R543,O65:O543)/(M64*O64) -> 1050344
A65: 62 | B65: =A65/Inputs!$B$6 -> 5.1666667 | C65: =Inputs!$B$3+B65 -> 70.166667 | D65: =INT(C65) -> 70 | E65: =Inputs!$B$7+1+INT((A65-1)/Inputs!$B$6) -> 2031 | F65: =Inputs!$B$16 -> 8333.3333 | G65: =Inputs!$B$12 -> 25 | H65: =IFERROR(INDEX(RP2014_Qx!$B:$B,MATCH(D65,RP2014_Qx!$A:$A,0)),"") -> 0.012868 | I65: =SUMIFS(MP2016_Long!$C:$C,MP2016_Long!$A:$A,D65,MP2016_Long!$B:$B,">=2014",MP2016_Long!$B:$B,"<"&E65) -> 0.1377 | J65: =MIN(0.999999,MAX(0,H65*EXP(I65))) -> 0.014767718 | K65: =-LN(1-J65) -> 0.014877847 | L65: =EXP(-K65/Inputs!$B$6) -> 0.99876095 | M65: =M64*L65 -> 0.94460991 | N65: =IFERROR(INDEX(MonthlyCurve!$I:$I,MATCH(A65,MonthlyCurve!$A:$A,0)),"") -> 0.038652177 | O65: =IFERROR(INDEX(MonthlyCurve!$J:$J,MATCH(A65,MonthlyCurve!$A:$A,0)),"") -> 0.81897402 | P65: =F65*M65 -> 7871.7493 | Q65: =G65*M65 -> 23.615248 | R65: =P65+Q65 -> 7895.3645 | S65: =P65*O65 -> 6446.7582 | T65: =Q65*O65 -> 19.340275 | U65: =SUMPRODUCT(R66:R543,O66:O543)/(M65*O65) -> 1047112.9
A66: 63 | B66: =A66/Inputs!$B$6 -> 5.25 | C66: =Inputs!$B$3+B66 -> 70.25 | D66: =INT(C66) -> 70 | E66: =Inputs!$B$7+1+INT((A66-1)/Inputs!$B$6) -> 2031 | F66: =Inputs!$B$16 -> 8333.3333 | G66: =Inputs!$B$12 -> 25 | H66: =IFERROR(INDEX(RP2014_Qx!$B:$B,MATCH(D66,RP2014_Qx!$A:$A,0)),"") -> 0.012868 | I66: =SUMIFS(MP2016_Long!$C:$C,MP2016_Long!$A:$A,D66,MP2016_Long!$B:$B,">=2014",MP2016_Long!$B:$B,"<"&E66) -> 0.1377 | J66: =MIN(0.999999,MAX(0,H66*EXP(I66))) -> 0.014767718 | K66: =-LN(1-J66) -> 0.014877847 | L66: =EXP(-K66/Inputs!$B$6) -> 0.99876095 | M66: =M65*L66 -> 0.94343949 | N66: =IFERROR(INDEX(MonthlyCurve!$I:$I,MATCH(A66,MonthlyCurve!$A:$A,0)),"") -> 0.03873259 | O66: =IFERROR(INDEX(MonthlyCurve!$J:$J,MATCH(A66,MonthlyCurve!$A:$A,0)),"") -> 0.81599578 | P66: =F66*M66 -> 7861.9958 | Q66: =G66*M66 -> 23.585987 | R66: =P66+Q66 -> 7885.5818 | S66: =P66*O66 -> 6415.3554 | T66: =Q66*O66 -> 19.246066 | U66: =SUMPRODUCT(R67:R543,O67:O543)/(M66*O66) -> 1043880.2
A67: 64 | B67: =A67/Inputs!$B$6 -> 5.3333333 | C67: =Inputs!$B$3+B67 -> 70.333333 | D67: =INT(C67) -> 70 | E67: =Inputs!$B$7+1+INT((A67-1)/Inputs!$B$6) -> 2031 | F67: =Inputs!$B$16 -> 8333.3333 | G67: =Inputs!$B$12 -> 25 | H67: =IFERROR(INDEX(RP2014_Qx!$B:$B,MATCH(D67,RP2014_Qx!$A:$A,0)),"") -> 0.012868 | I67: =SUMIFS(MP2016_Long!$C:$C,MP2016_Long!$A:$A,D67,MP2016_Long!$B:$B,">=2014",MP2016_Long!$B:$B,"<"&E67) -> 0.1377 | J67: =MIN(0.999999,MAX(0,H67*EXP(I67))) -> 0.014767718 | K67: =-LN(1-J67) -> 0.014877847 | L67: =EXP(-K67/Inputs!$B$6) -> 0.99876095 | M67: =M66*L67 -> 0.94227052 | N67: =IFERROR(INDEX(MonthlyCurve!$I:$I,MATCH(A67,MonthlyCurve!$A:$A,0)),"") -> 0.038813003 | O67: =IFERROR(INDEX(MonthlyCurve!$J:$J,MATCH(A67,MonthlyCurve!$A:$A,0)),"") -> 0.81301747 | P67: =F67*M67 -> 7852.2543 | Q67: =G67*M67 -> 23.556763 | R67: =P67+Q67 -> 7875.8111 | S67: =P67*O67 -> 6384.0199 | T67: =Q67*O67 -> 19.15206 | U67: =SUMPRODUCT(R68:R543,O68:O543)/(M67*O67) -> 1040645.6
A68: 65 | B68: =A68/Inputs!$B$6 -> 5.4166667 | C68: =Inputs!$B$3+B68 -> 70.416667 | D68: =INT(C68) -> 70 | E68: =Inputs!$B$7+1+INT((A68-1)/Inputs!$B$6) -> 2031 | F68: =Inputs!$B$16 -> 8333.3333 | G68: =Inputs!$B$12 -> 25 | H68: =IFERROR(INDEX(RP2014_Qx!$B:$B,MATCH(D68,RP2014_Qx!$A:$A,0)),"") -> 0.012868 | I68: =SUMIFS(MP2016_Long!$C:$C,MP2016_Long!$A:$A,D68,MP2016_Long!$B:$B,">=2014",MP2016_Long!$B:$B,"<"&E68) -> 0.1377 | J68: =MIN(0.999999,MAX(0,H68*EXP(I68))) -> 0.014767718 | K68: =-LN(1-J68) -> 0.014877847 | L68: =EXP(-K68/Inputs!$B$6) -> 0.99876095 | M68: =M67*L68 -> 0.941103 | N68: =IFERROR(INDEX(MonthlyCurve!$I:$I,MATCH(A68,MonthlyCurve!$A:$A,0)),"") -> 0.038893417 | O68: =IFERROR(INDEX(MonthlyCurve!$J:$J,MATCH(A68,MonthlyCurve!$A:$A,0)),"") -> 0.81003917 | P68: =F68*M68 -> 7842.525 | Q68: =G68*M68 -> 23.527575 | R68: =P68+Q68 -> 7866.0526 | S68: =P68*O68 -> 6352.7524 | T68: =Q68*O68 -> 19.058257 | U68: =SUMPRODUCT(R69:R543,O69:O543)/(M68*O68) -> 1037409.2
A69: 66 | B69: =A69/Inputs!$B$6 -> 5.5 | C69: =Inputs!$B$3+B69 -> 70.5 | D69: =INT(C69) -> 70 | E69: =Inputs!$B$7+1+INT((A69-1)/Inputs!$B$6) -> 2031 | F69: =Inputs!$B$16 -> 8333.3333 | G69: =Inputs!$B$12 -> 25 | H69: =IFERROR(INDEX(RP2014_Qx!$B:$B,MATCH(D69,RP2014_Qx!$A:$A,0)),"") -> 0.012868 | I69: =SUMIFS(MP2016_Long!$C:$C,MP2016_Long!$A:$A,D69,MP2016_Long!$B:$B,">=2014",MP2016_Long!$B:$B,"<"&E69) -> 0.1377 | J69: =MIN(0.999999,MAX(0,H69*EXP(I69))) -> 0.014767718 | K69: =-LN(1-J69) -> 0.014877847 | L69: =EXP(-K69/Inputs!$B$6) -> 0.99876095 | M69: =M68*L69 -> 0.93993692 | N69: =IFERROR(INDEX(MonthlyCurve!$I:$I,MATCH(A69,MonthlyCurve!$A:$A,0)),"") -> 0.03897383 | O69: =IFERROR(INDEX(MonthlyCurve!$J:$J,MATCH(A69,MonthlyCurve!$A:$A,0)),"") -> 0.80706097 | P69: =F69*M69 -> 7832.8077 | Q69: =G69*M69 -> 23.498423 | R69: =P69+Q69 -> 7856.3061 | S69: =P69*O69 -> 6321.5534 | T69: =Q69*O69 -> 18.96466 | U69: =SUMPRODUCT(R70:R543,O70:O543)/(M69*O69) -> 1034170.9
A70: 67 | B70: =A70/Inputs!$B$6 -> 5.5833333 | C70: =Inputs!$B$3+B70 -> 70.583333 | D70: =INT(C70) -> 70 | E70: =Inputs!$B$7+1+INT((A70-1)/Inputs!$B$6) -> 2031 | F70: =Inputs!$B$16 -> 8333.3333 | G70: =Inputs!$B$12 -> 25 | H70: =IFERROR(INDEX(RP2014_Qx!$B:$B,MATCH(D70,RP2014_Qx!$A:$A,0)),"") -> 0.012868 | I70: =SUMIFS(MP2016_Long!$C:$C,MP2016_Long!$A:$A,D70,MP2016_Long!$B:$B,">=2014",MP2016_Long!$B:$B,"<"&E70) -> 0.1377 | J70: =MIN(0.999999,MAX(0,H70*EXP(I70))) -> 0.014767718 | K70: =-LN(1-J70) -> 0.014877847 | L70: =EXP(-K70/Inputs!$B$6) -> 0.99876095 | M70: =M69*L70 -> 0.93877229 | N70: =IFERROR(INDEX(MonthlyCurve!$I:$I,MATCH(A70,MonthlyCurve!$A:$A,0)),"") -> 0.039054755 | O70: =IFERROR(INDEX(MonthlyCurve!$J:$J,MATCH(A70,MonthlyCurve!$A:$A,0)),"") -> 0.80408064 | P70: =F70*M70 -> 7823.1024 | Q70: =G70*M70 -> 23.469307 | R70: =P70+Q70 -> 7846.5717 | S70: =P70*O70 -> 6290.4052 | T70: =Q70*O70 -> 18.871216 | U70: =SUMPRODUCT(R71:R543,O71:O543)/(M70*O70) -> 1030933.4
A71: 68 | B71: =A71/Inputs!$B$6 -> 5.6666667 | C71: =Inputs!$B$3+B71 -> 70.666667 | D71: =INT(C71) -> 70 | E71: =Inputs!$B$7+1+INT((A71-1)/Inputs!$B$6) -> 2031 | F71: =Inputs!$B$16 -> 8333.3333 | G71: =Inputs!$B$12 -> 25 | H71: =IFERROR(INDEX(RP2014_Qx!$B:$B,MATCH(D71,RP2014_Qx!$A:$A,0)),"") -> 0.012868 | I71: =SUMIFS(MP2016_Long!$C:$C,MP2016_Long!$A:$A,D71,MP2016_Long!$B:$B,">=2014",MP2016_Long!$B:$B,"<"&E71) -> 0.1377 | J71: =MIN(0.999999,MAX(0,H71*EXP(I71))) -> 0.014767718 | K71: =-LN(1-J71) -> 0.014877847 | L71: =EXP(-K71/Inputs!$B$6) -> 0.99876095 | M71: =M70*L71 -> 0.9376091 | N71: =IFERROR(INDEX(MonthlyCurve!$I:$I,MATCH(A71,MonthlyCurve!$A:$A,0)),"") -> 0.03913568 | O71: =IFERROR(INDEX(MonthlyCurve!$J:$J,MATCH(A71,MonthlyCurve!$A:$A,0)),"") -> 0.80110051 | P71: =F71*M71 -> 7813.4092 | Q71: =G71*M71 -> 23.440228 | R71: =P71+Q71 -> 7836.8494 | S71: =P71*O71 -> 6259.3261 | T71: =Q71*O71 -> 18.777978 | U71: =SUMPRODUCT(R72:R543,O72:O543)/(M71*O71) -> 1027693.9
A72: 69 | B72: =A72/Inputs!$B$6 -> 5.75 | C72: =Inputs!$B$3+B72 -> 70.75 | D72: =INT(C72) -> 70 | E72: =Inputs!$B$7+1+INT((A72-1)/Inputs!$B$6) -> 2031 | F72: =Inputs!$B$16 -> 8333.3333 | G72: =Inputs!$B$12 -> 25 | H72: =IFERROR(INDEX(RP2014_Qx!$B:$B,MATCH(D72,RP2014_Qx!$A:$A,0)),"") -> 0.012868 | I72: =SUMIFS(MP2016_Long!$C:$C,MP2016_Long!$A:$A,D72,MP2016_Long!$B:$B,">=2014",MP2016_Long!$B:$B,"<"&E72) -> 0.1377 | J72: =MIN(0.999999,MAX(0,H72*EXP(I72))) -> 0.014767718 | K72: =-LN(1-J72) -> 0.014877847 | L72: =EXP(-K72/Inputs!$B$6) -> 0.99876095 | M72: =M71*L72 -> 0.93644736 | N72: =IFERROR(INDEX(MonthlyCurve!$I:$I,MATCH(A72,MonthlyCurve!$A:$A,0)),"") -> 0.039216605 | O72: =IFERROR(INDEX(MonthlyCurve!$J:$J,MATCH(A72,MonthlyCurve!$A:$A,0)),"") -> 0.79812067 | P72: =F72*M72 -> 7803.728 | Q72: =G72*M72 -> 23.411184 | R72: =P72+Q72 -> 7827.1392 | S72: =P72*O72 -> 6228.3166 | T72: =Q72*O72 -> 18.68495 | U72: =SUMPRODUCT(R73:R543,O73:O543)/(M72*O72) -> 1024452.3
A73: 70 | B73: =A73/Inputs!$B$6 -> 5.8333333 | C73: =Inputs!$B$3+B73 -> 70.833333 | D73: =INT(C73) -> 70 | E73: =Inputs!$B$7+1+INT((A73-1)/Inputs!$B$6) -> 2031 | F73: =Inputs!$B$16 -> 8333.3333 | G73: =Inputs!$B$12 -> 25 | H73: =IFERROR(INDEX(RP2014_Qx!$B:$B,MATCH(D73,RP2014_Qx!$A:$A,0)),"") -> 0.012868 | I73: =SUMIFS(MP2016_Long!$C:$C,MP2016_Long!$A:$A,D73,MP2016_Long!$B:$B,">=2014",MP2016_Long!$B:$B,"<"&E73) -> 0.1377 | J73: =MIN(0.999999,MAX(0,H73*EXP(I73))) -> 0.014767718 | K73: =-LN(1-J73) -> 0.014877847 | L73: =EXP(-K73/Inputs!$B$6) -> 0.99876095 | M73: =M72*L73 -> 0.93528705 | N73: =IFERROR(INDEX(MonthlyCurve!$I:$I,MATCH(A73,MonthlyCurve!$A:$A,0)),"") -> 0.03929753 | O73: =IFERROR(INDEX(MonthlyCurve!$J:$J,MATCH(A73,MonthlyCurve!$A:$A,0)),"") -> 0.79514118 | P73: =F73*M73 -> 7794.0588 | Q73: =G73*M73 -> 23.382176 | R73: =P73+Q73 -> 7817.4409 | S73: =P73*O73 -> 6197.3771 | T73: =Q73*O73 -> 18.592131 | U73: =SUMPRODUCT(R74:R543,O74:O543)/(M73*O73) -> 1021208.4
A74: 71 | B74: =A74/Inputs!$B$6 -> 5.9166667 | C74: =Inputs!$B$3+B74 -> 70.916667 | D74: =INT(C74) -> 70 | E74: =Inputs!$B$7+1+INT((A74-1)/Inputs!$B$6) -> 2031 | F74: =Inputs!$B$16 -> 8333.3333 | G74: =Inputs!$B$12 -> 25 | H74: =IFERROR(INDEX(RP2014_Qx!$B:$B,MATCH(D74,RP2014_Qx!$A:$A,0)),"") -> 0.012868 | I74: =SUMIFS(MP2016_Long!$C:$C,MP2016_Long!$A:$A,D74,MP2016_Long!$B:$B,">=2014",MP2016_Long!$B:$B,"<"&E74) -> 0.1377 | J74: =MIN(0.999999,MAX(0,H74*EXP(I74))) -> 0.014767718 | K74: =-LN(1-J74) -> 0.014877847 | L74: =EXP(-K74/Inputs!$B$6) -> 0.99876095 | M74: =M73*L74 -> 0.93412818 | N74: =IFERROR(INDEX(MonthlyCurve!$I:$I,MATCH(A74,MonthlyCurve!$A:$A,0)),"") -> 0.039378455 | O74: =IFERROR(INDEX(MonthlyCurve!$J:$J,MATCH(A74,MonthlyCurve!$A:$A,0)),"") -> 0.79216214 | P74: =F74*M74 -> 7784.4015 | Q74: =G74*M74 -> 23.353205 | R74: =P74+Q74 -> 7807.7547 | S74: =P74*O74 -> 6166.5081 | T74: =Q74*O74 -> 18.499524 | U74: =SUMPRODUCT(R75:R543,O75:O543)/(M74*O74) -> 1017962.1
A75: 72 | B75: =A75/Inputs!$B$6 -> 6 | C75: =Inputs!$B$3+B75 -> 71 | D75: =INT(C75) -> 71 | E75: =Inputs!$B$7+1+INT((A75-1)/Inputs!$B$6) -> 2031 | F75: =Inputs!$B$16 -> 8333.3333 | G75: =Inputs!$B$12 -> 25 | H75: =IFERROR(INDEX(RP2014_Qx!$B:$B,MATCH(D75,RP2014_Qx!$A:$A,0)),"") -> 0.014171 | I75: =SUMIFS(MP2016_Long!$C:$C,MP2016_Long!$A:$A,D75,MP2016_Long!$B:$B,">=2014",MP2016_Long!$B:$B,"<"&E75) -> 0.1438 | J75: =MIN(0.999999,MAX(0,H75*EXP(I75))) -> 0.01636259 | K75: =-LN(1-J75) -> 0.016497935 | L75: =EXP(-K75/Inputs!$B$6) -> 0.99862612 | M75: =M74*L75 -> 0.9328448 | N75: =IFERROR(INDEX(MonthlyCurve!$I:$I,MATCH(A75,MonthlyCurve!$A:$A,0)),"") -> 0.03945938 | O75: =IFERROR(INDEX(MonthlyCurve!$J:$J,MATCH(A75,MonthlyCurve!$A:$A,0)),"") -> 0.7891836 | P75: =F75*M75 -> 7773.7066 | Q75: =G75*M75 -> 23.32112 | R75: =P75+Q75 -> 7797.0278 | S75: =P75*O75 -> 6134.8818 | T75: =Q75*O75 -> 18.404645 | U75: =SUMPRODUCT(R76:R543,O76:O543)/(M75*O75) -> 1014851.5
A76: 73 | B76: =A76/Inputs!$B$6 -> 6.0833333 | C76: =Inputs!$B$3+B76 -> 71.083333 | D76: =INT(C76) -> 71 | E76: =Inputs!$B$7+1+INT((A76-1)/Inputs!$B$6) -> 2032 | F76: =Inputs!$B$16 -> 8333.3333 | G76: =Inputs!$B$12 -> 25 | H76: =IFERROR(INDEX(RP2014_Qx!$B:$B,MATCH(D76,RP2014_Qx!$A:$A,0)),"") -> 0.014171 | I76: =SUMIFS(MP2016_Long!$C:$C,MP2016_Long!$A:$A,D76,MP2016_Long!$B:$B,">=2014",MP2016_Long!$B:$B,"<"&E76) -> 0.1538 | J76: =MIN(0.999999,MAX(0,H76*EXP(I76))) -> 0.016527037 | K76: =-LN(1-J76) -> 0.016665132 | L76: =EXP(-K76/Inputs!$B$6) -> 0.9986122 | M76: =M75*L76 -> 0.9315502 | N76: =IFERROR(INDEX(MonthlyCurve!$I:$I,MATCH(A76,MonthlyCurve!$A:$A,0)),"") -> 0.039540892 | O76: =IFERROR(INDEX(MonthlyCurve!$J:$J,MATCH(A76,MonthlyCurve!$A:$A,0)),"") -> 0.78620286 | P76: =F76*M76 -> 7762.9183 | Q76: =G76*M76 -> 23.288755 | R76: =P76+Q76 -> 7786.2071 | S76: =P76*O76 -> 6103.2286 | T76: =Q76*O76 -> 18.309686 | U76: =SUMPRODUCT(R77:R543,O77:O543)/(M76*O76) -> 1011756.5
A77: 74 | B77: =A77/Inputs!$B$6 -> 6.1666667 | C77: =Inputs!$B$3+B77 -> 71.166667 | D77: =INT(C77) -> 71 | E77: =Inputs!$B$7+1+INT((A77-1)/Inputs!$B$6) -> 2032 | F77: =Inputs!$B$16 -> 8333.3333 | G77: =Inputs!$B$12 -> 25 | H77: =IFERROR(INDEX(RP2014_Qx!$B:$B,MATCH(D77,RP2014_Qx!$A:$A,0)),"") -> 0.014171 | I77: =SUMIFS(MP2016_Long!$C:$C,MP2016_Long!$A:$A,D77,MP2016_Long!$B:$B,">=2014",MP2016_Long!$B:$B,"<"&E77) -> 0.1538 | J77: =MIN(0.999999,MAX(0,H77*EXP(I77))) -> 0.016527037 | K77: =-LN(1-J77) -> 0.016665132 | L77: =EXP(-K77/Inputs!$B$6) -> 0.9986122 | M77: =M76*L77 -> 0.9302574 | N77: =IFERROR(INDEX(MonthlyCurve!$I:$I,MATCH(A77,MonthlyCurve!$A:$A,0)),"") -> 0.039622403 | O77: =IFERROR(INDEX(MonthlyCurve!$J:$J,MATCH(A77,MonthlyCurve!$A:$A,0)),"") -> 0.78322274 | P77: =F77*M77 -> 7752.145 | Q77: =G77*M77 -> 23.256435 | R77: =P77+Q77 -> 7775.4014 | S77: =P77*O77 -> 6071.6562 | T77: =Q77*O77 -> 18.214969 | U77: =SUMPRODUCT(R78:R543,O78:O543)/(M77*O77) -> 1008659.3
A78: 75 | B78: =A78/Inputs!$B$6 -> 6.25 | C78: =Inputs!$B$3+B78 -> 71.25 | D78: =INT(C78) -> 71 | E78: =Inputs!$B$7+1+INT((A78-1)/Inputs!$B$6) -> 2032 | F78: =Inputs!$B$16 -> 8333.3333 | G78: =Inputs!$B$12 -> 25 | H78: =IFERROR(INDEX(RP2014_Qx!$B:$B,MATCH(D78,RP2014_Qx!$A:$A,0)),"") -> 0.014171 | I78: =SUMIFS(MP2016_Long!$C:$C,MP2016_Long!$A:$A,D78,MP2016_Long!$B:$B,">=2014",MP2016_Long!$B:$B,"<"&E78) -> 0.1538 | J78: =MIN(0.999999,MAX(0,H78*EXP(I78))) -> 0.016527037 | K78: =-LN(1-J78) -> 0.016665132 | L78: =EXP(-K78/Inputs!$B$6) -> 0.9986122 | M78: =M77*L78 -> 0.92896639 | N78: =IFERROR(INDEX(MonthlyCurve!$I:$I,MATCH(A78,MonthlyCurve!$A:$A,0)),"") -> 0.039703915 | O78: =IFERROR(INDEX(MonthlyCurve!$J:$J,MATCH(A78,MonthlyCurve!$A:$A,0)),"") -> 0.78024331 | P78: =F78*M78 -> 7741.3866 | Q78: =G78*M78 -> 23.22416 | R78: =P78+Q78 -> 7764.6107 | S78: =P78*O78 -> 6040.1651 | T78: =Q78*O78 -> 18.120495 | U78: =SUMPRODUCT(R79:R543,O79:O543)/(M78*O78) -> 1005559.7
A79: 76 | B79: =A79/Inputs!$B$6 -> 6.3333333 | C79: =Inputs!$B$3+B79 -> 71.333333 | D79: =INT(C79) -> 71 | E79: =Inputs!$B$7+1+INT((A79-1)/Inputs!$B$6) -> 2032 | F79: =Inputs!$B$16 -> 8333.3333 | G79: =Inputs!$B$12 -> 25 | H79: =IFERROR(INDEX(RP2014_Qx!$B:$B,MATCH(D79,RP2014_Qx!$A:$A,0)),"") -> 0.014171 | I79: =SUMIFS(MP2016_Long!$C:$C,MP2016_Long!$A:$A,D79,MP2016_Long!$B:$B,">=2014",MP2016_Long!$B:$B,"<"&E79) -> 0.1538 | J79: =MIN(0.999999,MAX(0,H79*EXP(I79))) -> 0.016527037 | K79: =-LN(1-J79) -> 0.016665132 | L79: =EXP(-K79/Inputs!$B$6) -> 0.9986122 | M79: =M78*L79 -> 0.92767717 | N79: =IFERROR(INDEX(MonthlyCurve!$I:$I,MATCH(A79,MonthlyCurve!$A:$A,0)),"") -> 0.039785427 | O79: =IFERROR(INDEX(MonthlyCurve!$J:$J,MATCH(A79,MonthlyCurve!$A:$A,0)),"") -> 0.77726466 | P79: =F79*M79 -> 7730.6431 | Q79: =G79*M79 -> 23.191929 | R79: =P79+Q79 -> 7753.835 | S79: =P79*O79 -> 6008.7557 | T79: =Q79*O79 -> 18.026267 | U79: =SUMPRODUCT(R80:R543,O80:O543)/(M79*O79) -> 1002457.7
A80: 77 | B80: =A80/Inputs!$B$6 -> 6.4166667 | C80: =Inputs!$B$3+B80 -> 71.416667 | D80: =INT(C80) -> 71 | E80: =Inputs!$B$7+1+INT((A80-1)/Inputs!$B$6) -> 2032 | F80: =Inputs!$B$16 -> 8333.3333 | G80: =Inputs!$B$12 -> 25 | H80: =IFERROR(INDEX(RP2014_Qx!$B:$B,MATCH(D80,RP2014_Qx!$A:$A,0)),"") -> 0.014171 | I80: =SUMIFS(MP2016_Long!$C:$C,MP2016_Long!$A:$A,D80,MP2016_Long!$B:$B,">=2014",MP2016_Long!$B:$B,"<"&E80) -> 0.1538 | J80: =MIN(0.999999,MAX(0,H80*EXP(I80))) -> 0.016527037 | K80: =-LN(1-J80) -> 0.016665132 | L80: =EXP(-K80/Inputs!$B$6) -> 0.9986122 | M80: =M79*L80 -> 0.92638974 | N80: =IFERROR(INDEX(MonthlyCurve!$I:$I,MATCH(A80,MonthlyCurve!$A:$A,0)),"") -> 0.039866938 | O80: =IFERROR(INDEX(MonthlyCurve!$J:$J,MATCH(A80,MonthlyCurve!$A:$A,0)),"") -> 0.77428686 | P80: =F80*M80 -> 7719.9145 | Q80: =G80*M80 -> 23.159744 | R80: =P80+Q80 -> 7743.0743 | S80: =P80*O80 -> 5977.4284 | T80: =Q80*O80 -> 17.932285 | U80: =SUMPRODUCT(R81:R543,O81:O543)/(M80*O80) -> 999353.22
A81: 78 | B81: =A81/Inputs!$B$6 -> 6.5 | C81: =Inputs!$B$3+B81 -> 71.5 | D81: =INT(C81) -> 71 | E81: =Inputs!$B$7+1+INT((A81-1)/Inputs!$B$6) -> 2032 | F81: =Inputs!$B$16 -> 8333.3333 | G81: =Inputs!$B$12 -> 25 | H81: =IFERROR(INDEX(RP2014_Qx!$B:$B,MATCH(D81,RP2014_Qx!$A:$A,0)),"") -> 0.014171 | I81: =SUMIFS(MP2016_Long!$C:$C,MP2016_Long!$A:$A,D81,MP2016_Long!$B:$B,">=2014",MP2016_Long!$B:$B,"<"&E81) -> 0.1538 | J81: =MIN(0.999999,MAX(0,H81*EXP(I81))) -> 0.016527037 | K81: =-LN(1-J81) -> 0.016665132 | L81: =EXP(-K81/Inputs!$B$6) -> 0.9986122 | M81: =M80*L81 -> 0.9251041 | N81: =IFERROR(INDEX(MonthlyCurve!$I:$I,MATCH(A81,MonthlyCurve!$A:$A,0)),"") -> 0.03994845 | O81: =IFERROR(INDEX(MonthlyCurve!$J:$J,MATCH(A81,MonthlyCurve!$A:$A,0)),"") -> 0.77130999 | P81: =F81*M81 -> 7709.2008 | Q81: =G81*M81 -> 23.127603 | R81: =P81+Q81 -> 7732.3284 | S81: =P81*O81 -> 5946.1836 | T81: =Q81*O81 -> 17.838551 | U81: =SUMPRODUCT(R82:R543,O82:O543)/(M81*O81) -> 996246.08
A82: 79 | B82: =A82/Inputs!$B$6 -> 6.5833333 | C82: =Inputs!$B$3+B82 -> 71.583333 | D82: =INT(C82) -> 71 | E82: =Inputs!$B$7+1+INT((A82-1)/Inputs!$B$6) -> 2032 | F82: =Inputs!$B$16 -> 8333.3333 | G82: =Inputs!$B$12 -> 25 | H82: =IFERROR(INDEX(RP2014_Qx!$B:$B,MATCH(D82,RP2014_Qx!$A:$A,0)),"") -> 0.014171 | I82: =SUMIFS(MP2016_Long!$C:$C,MP2016_Long!$A:$A,D82,MP2016_Long!$B:$B,">=2014",MP2016_Long!$B:$B,"<"&E82) -> 0.1538 | J82: =MIN(0.999999,MAX(0,H82*EXP(I82))) -> 0.016527037 | K82: =-LN(1-J82) -> 0.016665132 | L82: =EXP(-K82/Inputs!$B$6) -> 0.9986122 | M82: =M81*L82 -> 0.92382024 | N82: =IFERROR(INDEX(MonthlyCurve!$I:$I,MATCH(A82,MonthlyCurve!$A:$A,0)),"") -> 0.04003062 | O82: =IFERROR(INDEX(MonthlyCurve!$J:$J,MATCH(A82,MonthlyCurve!$A:$A,0)),"") -> 0.7683308 | P82: =F82*M82 -> 7698.502 | Q82: =G82*M82 -> 23.095506 | R82: =P82+Q82 -> 7721.5975 | S82: =P82*O82 -> 5914.9962 | T82: =Q82*O82 -> 17.744989 | U82: =SUMPRODUCT(R83:R543,O83:O543)/(M82*O82) -> 993140.55
A83: 80 | B83: =A83/Inputs!$B$6 -> 6.6666667 | C83: =Inputs!$B$3+B83 -> 71.666667 | D83: =INT(C83) -> 71 | E83: =Inputs!$B$7+1+INT((A83-1)/Inputs!$B$6) -> 2032 | F83: =Inputs!$B$16 -> 8333.3333 | G83: =Inputs!$B$12 -> 25 | H83: =IFERROR(INDEX(RP2014_Qx!$B:$B,MATCH(D83,RP2014_Qx!$A:$A,0)),"") -> 0.014171 | I83: =SUMIFS(MP2016_Long!$C:$C,MP2016_Long!$A:$A,D83,MP2016_Long!$B:$B,">=2014",MP2016_Long!$B:$B,"<"&E83) -> 0.1538 | J83: =MIN(0.999999,MAX(0,H83*EXP(I83))) -> 0.016527037 | K83: =-LN(1-J83) -> 0.016665132 | L83: =EXP(-K83/Inputs!$B$6) -> 0.9986122 | M83: =M82*L83 -> 0.92253817 | N83: =IFERROR(INDEX(MonthlyCurve!$I:$I,MATCH(A83,MonthlyCurve!$A:$A,0)),"") -> 0.04011279 | O83: =IFERROR(INDEX(MonthlyCurve!$J:$J,MATCH(A83,MonthlyCurve!$A:$A,0)),"") -> 0.76535263 | P83: =F83*M83 -> 7687.8181 | Q83: =G83*M83 -> 23.063454 | R83: =P83+Q83 -> 7710.8815 | S83: =P83*O83 -> 5883.8918 | T83: =Q83*O83 -> 17.651675 | U83: =SUMPRODUCT(R84:R543,O84:O543)/(M83*O83) -> 990032.33
A84: 81 | B84: =A84/Inputs!$B$6 -> 6.75 | C84: =Inputs!$B$3+B84 -> 71.75 | D84: =INT(C84) -> 71 | E84: =Inputs!$B$7+1+INT((A84-1)/Inputs!$B$6) -> 2032 | F84: =Inputs!$B$16 -> 8333.3333 | G84: =Inputs!$B$12 -> 25 | H84: =IFERROR(INDEX(RP2014_Qx!$B:$B,MATCH(D84,RP2014_Qx!$A:$A,0)),"") -> 0.014171 | I84: =SUMIFS(MP2016_Long!$C:$C,MP2016_Long!$A:$A,D84,MP2016_Long!$B:$B,">=2014",MP2016_Long!$B:$B,"<"&E84) -> 0.1538 | J84: =MIN(0.999999,MAX(0,H84*EXP(I84))) -> 0.016527037 | K84: =-LN(1-J84) -> 0.016665132 | L84: =EXP(-K84/Inputs!$B$6) -> 0.9986122 | M84: =M83*L84 -> 0.92125787 | N84: =IFERROR(INDEX(MonthlyCurve!$I:$I,MATCH(A84,MonthlyCurve!$A:$A,0)),"") -> 0.04019496 | O84: =IFERROR(INDEX(MonthlyCurve!$J:$J,MATCH(A84,MonthlyCurve!$A:$A,0)),"") -> 0.76237556 | P84: =F84*M84 -> 7677.1489 | Q84: =G84*M84 -> 23.031447 | R84: =P84+Q84 -> 7700.1804 | S84: =P84*O84 -> 5852.8708 | T84: =Q84*O84 -> 17.558612 | U84: =SUMPRODUCT(R85:R543,O85:O543)/(M84*O84) -> 986921.3
A85: 82 | B85: =A85/Inputs!$B$6 -> 6.8333333 | C85: =Inputs!$B$3+B85 -> 71.833333 | D85: =INT(C85) -> 71 | E85: =Inputs!$B$7+1+INT((A85-1)/Inputs!$B$6) -> 2032 | F85: =Inputs!$B$16 -> 8333.3333 | G85: =Inputs!$B$12 -> 25 | H85: =IFERROR(INDEX(RP2014_Qx!$B:$B,MATCH(D85,RP2014_Qx!$A:$A,0)),"") -> 0.014171 | I85: =SUMIFS(MP2016_Long!$C:$C,MP2016_Long!$A:$A,D85,MP2016_Long!$B:$B,">=2014",MP2016_Long!$B:$B,"<"&E85) -> 0.1538 | J85: =MIN(0.999999,MAX(0,H85*EXP(I85))) -> 0.016527037 | K85: =-LN(1-J85) -> 0.016665132 | L85: =EXP(-K85/Inputs!$B$6) -> 0.9986122 | M85: =M84*L85 -> 0.91997935 | N85: =IFERROR(INDEX(MonthlyCurve!$I:$I,MATCH(A85,MonthlyCurve!$A:$A,0)),"") -> 0.04027713 | O85: =IFERROR(INDEX(MonthlyCurve!$J:$J,MATCH(A85,MonthlyCurve!$A:$A,0)),"") -> 0.75939968 | P85: =F85*M85 -> 7666.4946 | Q85: =G85*M85 -> 22.999484 | R85: =P85+Q85 -> 7689.4941 | S85: =P85*O85 -> 5821.9335 | T85: =Q85*O85 -> 17.465801 | U85: =SUMPRODUCT(R86:R543,O86:O543)/(M85*O85) -> 983807.37
A86: 83 | B86: =A86/Inputs!$B$6 -> 6.9166667 | C86: =Inputs!$B$3+B86 -> 71.916667 | D86: =INT(C86) -> 71 | E86: =Inputs!$B$7+1+INT((A86-1)/Inputs!$B$6) -> 2032 | F86: =Inputs!$B$16 -> 8333.3333 | G86: =Inputs!$B$12 -> 25 | H86: =IFERROR(INDEX(RP2014_Qx!$B:$B,MATCH(D86,RP2014_Qx!$A:$A,0)),"") -> 0.014171 | I86: =SUMIFS(MP2016_Long!$C:$C,MP2016_Long!$A:$A,D86,MP2016_Long!$B:$B,">=2014",MP2016_Long!$B:$B,"<"&E86) -> 0.1538 | J86: =MIN(0.999999,MAX(0,H86*EXP(I86))) -> 0.016527037 | K86: =-LN(1-J86) -> 0.016665132 | L86: =EXP(-K86/Inputs!$B$6) -> 0.9986122 | M86: =M85*L86 -> 0.91870261 | N86: =IFERROR(INDEX(MonthlyCurve!$I:$I,MATCH(A86,MonthlyCurve!$A:$A,0)),"") -> 0.0403593 | O86: =IFERROR(INDEX(MonthlyCurve!$J:$J,MATCH(A86,MonthlyCurve!$A:$A,0)),"") -> 0.75642505 | P86: =F86*M86 -> 7655.8551 | Q86: =G86*M86 -> 22.967565 | R86: =P86+Q86 -> 7678.8227 | S86: =P86*O86 -> 5791.0806 | T86: =Q86*O86 -> 17.373242 | U86: =SUMPRODUCT(R87:R543,O87:O543)/(M86*O86) -> 980690.45
A87: 84 | B87: =A87/Inputs!$B$6 -> 7 | C87: =Inputs!$B$3+B87 -> 72 | D87: =INT(C87) -> 72 | E87: =Inputs!$B$7+1+INT((A87-1)/Inputs!$B$6) -> 2032 | F87: =Inputs!$B$16 -> 8333.3333 | G87: =Inputs!$B$12 -> 25 | H87: =IFERROR(INDEX(RP2014_Qx!$B:$B,MATCH(D87,RP2014_Qx!$A:$A,0)),"") -> 0.015614 | I87: =SUMIFS(MP2016_Long!$C:$C,MP2016_Long!$A:$A,D87,MP2016_Long!$B:$B,">=2014",MP2016_Long!$B:$B,"<"&E87) -> 0.1604 | J87: =MIN(0.999999,MAX(0,H87*EXP(I87))) -> 0.018330529 | K87: =-LN(1-J87) -> 0.018500615 | L87: =EXP(-K87/Inputs!$B$6) -> 0.99845947 | M87: =M86*L87 -> 0.91728732 | N87: =IFERROR(INDEX(MonthlyCurve!$I:$I,MATCH(A87,MonthlyCurve!$A:$A,0)),"") -> 0.04044147 | O87: =IFERROR(INDEX(MonthlyCurve!$J:$J,MATCH(A87,MonthlyCurve!$A:$A,0)),"") -> 0.75345176 | P87: =F87*M87 -> 7644.061 | Q87: =G87*M87 -> 22.932183 | R87: =P87+Q87 -> 7666.9932 | S87: =P87*O87 -> 5759.4312 | T87: =Q87*O87 -> 17.278294 | U87: =SUMPRODUCT(R88:R543,O88:O543)/(M87*O87) -> 977721.23
A88: 85 | B88: =A88/Inputs!$B$6 -> 7.0833333 | C88: =Inputs!$B$3+B88 -> 72.083333 | D88: =INT(C88) -> 72 | E88: =Inputs!$B$7+1+INT((A88-1)/Inputs!$B$6) -> 2033 | F88: =Inputs!$B$16 -> 8333.3333 | G88: =Inputs!$B$12 -> 25 | H88: =IFERROR(INDEX(RP2014_Qx!$B:$B,MATCH(D88,RP2014_Qx!$A:$A,0)),"") -> 0.015614 | I88: =SUMIFS(MP2016_Long!$C:$C,MP2016_Long!$A:$A,D88,MP2016_Long!$B:$B,">=2014",MP2016_Long!$B:$B,"<"&E88) -> 0.1604 | J88: =MIN(0.999999,MAX(0,H88*EXP(I88))) -> 0.018330529 | K88: =-LN(1-J88) -> 0.018500615 | L88: =EXP(-K88/Inputs!$B$6) -> 0.99845947 | M88: =M87*L88 -> 0.91587421 | N88: =IFERROR(INDEX(MonthlyCurve!$I:$I,MATCH(A88,MonthlyCurve!$A:$A,0)),"") -> 0.040498952 | O88: =IFERROR(INDEX(MonthlyCurve!$J:$J,MATCH(A88,MonthlyCurve!$A:$A,0)),"") -> 0.75061112 | P88: =F88*M88 -> 7632.2851 | Q88: =G88*M88 -> 22.896855 | R88: =P88+Q88 -> 7655.182 | S88: =P88*O88 -> 5728.8781 | T88: =Q88*O88 -> 17.186634 | U88: =SUMPRODUCT(R89:R543,O89:O543)/(M88*O88) -> 974577.25
A89: 86 | B89: =A89/Inputs!$B$6 -> 7.1666667 | C89: =Inputs!$B$3+B89 -> 72.166667 | D89: =INT(C89) -> 72 | E89: =Inputs!$B$7+1+INT((A89-1)/Inputs!$B$6) -> 2033 | F89: =Inputs!$B$16 -> 8333.3333 | G89: =Inputs!$B$12 -> 25 | H89: =IFERROR(INDEX(RP2014_Qx!$B:$B,MATCH(D89,RP2014_Qx!$A:$A,0)),"") -> 0.015614 | I89: =SUMIFS(MP2016_Long!$C:$C,MP2016_Long!$A:$A,D89,MP2016_Long!$B:$B,">=2014",MP2016_Long!$B:$B,"<"&E89) -> 0.1604 | J89: =MIN(0.999999,MAX(0,H89*EXP(I89))) -> 0.018330529 | K89: =-LN(1-J89) -> 0.018500615 | L89: =EXP(-K89/Inputs!$B$6) -> 0.99845947 | M89: =M88*L89 -> 0.91446328 | N89: =IFERROR(INDEX(MonthlyCurve!$I:$I,MATCH(A89,MonthlyCurve!$A:$A,0)),"") -> 0.040556433 | O89: =IFERROR(INDEX(MonthlyCurve!$J:$J,MATCH(A89,MonthlyCurve!$A:$A,0)),"") -> 0.74777404 | P89: =F89*M89 -> 7620.5273 | Q89: =G89*M89 -> 22.861582 | R89: =P89+Q89 -> 7643.3889 | S89: =P89*O89 -> 5698.4325 | T89: =Q89*O89 -> 17.095297 | U89: =SUMPRODUCT(R90:R543,O90:O543)/(M89*O89) -> 971425.89
A90: 87 | B90: =A90/Inputs!$B$6 -> 7.25 | C90: =Inputs!$B$3+B90 -> 72.25 | D90: =INT(C90) -> 72 | E90: =Inputs!$B$7+1+INT((A90-1)/Inputs!$B$6) -> 2033 | F90: =Inputs!$B$16 -> 8333.3333 | G90: =Inputs!$B$12 -> 25 | H90: =IFERROR(INDEX(RP2014_Qx!$B:$B,MATCH(D90,RP2014_Qx!$A:$A,0)),"") -> 0.015614 | I90: =SUMIFS(MP2016_Long!$C:$C,MP2016_Long!$A:$A,D90,MP2016_Long!$B:$B,">=2014",MP2016_Long!$B:$B,"<"&E90) -> 0.1604 | J90: =MIN(0.999999,MAX(0,H90*EXP(I90))) -> 0.018330529 | K90: =-LN(1-J90) -> 0.018500615 | L90: =EXP(-K90/Inputs!$B$6) -> 0.99845947 | M90: =M89*L90 -> 0.91305452 | N90: =IFERROR(INDEX(MonthlyCurve!$I:$I,MATCH(A90,MonthlyCurve!$A:$A,0)),"") -> 0.040613915 | O90: =IFERROR(INDEX(MonthlyCurve!$J:$J,MATCH(A90,MonthlyCurve!$A:$A,0)),"") -> 0.74494053 | P90: =F90*M90 -> 7608.7877 | Q90: =G90*M90 -> 22.826363 | R90: =P90+Q90 -> 7631.614 | S90: =P90*O90 -> 5668.0944 | T90: =Q90*O90 -> 17.004283 | U90: =SUMPRODUCT(R91:R543,O91:O543)/(M90*O90) -> 968267.06
A91: 88 | B91: =A91/Inputs!$B$6 -> 7.3333333 | C91: =Inputs!$B$3+B91 -> 72.333333 | D91: =INT(C91) -> 72 | E91: =Inputs!$B$7+1+INT((A91-1)/Inputs!$B$6) -> 2033 | F91: =Inputs!$B$16 -> 8333.3333 | G91: =Inputs!$B$12 -> 25 | H91: =IFERROR(INDEX(RP2014_Qx!$B:$B,MATCH(D91,RP2014_Qx!$A:$A,0)),"") -> 0.015614 | I91: =SUMIFS(MP2016_Long!$C:$C,MP2016_Long!$A:$A,D91,MP2016_Long!$B:$B,">=2014",MP2016_Long!$B:$B,"<"&E91) -> 0.1604 | J91: =MIN(0.999999,MAX(0,H91*EXP(I91))) -> 0.018330529 | K91: =-LN(1-J91) -> 0.018500615 | L91: =EXP(-K91/Inputs!$B$6) -> 0.99845947 | M91: =M90*L91 -> 0.91164793 | N91: =IFERROR(INDEX(MonthlyCurve!$I:$I,MATCH(A91,MonthlyCurve!$A:$A,0)),"") -> 0.040671397 | O91: =IFERROR(INDEX(MonthlyCurve!$J:$J,MATCH(A91,MonthlyCurve!$A:$A,0)),"") -> 0.74211066 | P91: =F91*M91 -> 7597.0661 | Q91: =G91*M91 -> 22.791198 | R91: =P91+Q91 -> 7619.8573 | S91: =P91*O91 -> 5637.8638 | T91: =Q91*O91 -> 16.913591 | U91: =SUMPRODUCT(R92:R543,O92:O543)/(M91*O91) -> 965100.64
A92: 89 | B92: =A92/Inputs!$B$6 -> 7.4166667 | C92: =Inputs!$B$3+B92 -> 72.416667 | D92: =INT(C92) -> 72 | E92: =Inputs!$B$7+1+INT((A92-1)/Inputs!$B$6) -> 2033 | F92: =Inputs!$B$16 -> 8333.3333 | G92: =Inputs!$B$12 -> 25 | H92: =IFERROR(INDEX(RP2014_Qx!$B:$B,MATCH(D92,RP2014_Qx!$A:$A,0)),"") -> 0.015614 | I92: =SUMIFS(MP2016_Long!$C:$C,MP2016_Long!$A:$A,D92,MP2016_Long!$B:$B,">=2014",MP2016_Long!$B:$B,"<"&E92) -> 0.1604 | J92: =MIN(0.999999,MAX(0,H92*EXP(I92))) -> 0.018330529 | K92: =-LN(1-J92) -> 0.018500615 | L92: =EXP(-K92/Inputs!$B$6) -> 0.99845947 | M92: =M91*L92 -> 0.91024351 | N92: =IFERROR(INDEX(MonthlyCurve!$I:$I,MATCH(A92,MonthlyCurve!$A:$A,0)),"") -> 0.040728878 | O92: =IFERROR(INDEX(MonthlyCurve!$J:$J,MATCH(A92,MonthlyCurve!$A:$A,0)),"") -> 0.73928445 | P92: =F92*M92 -> 7585.3626 | Q92: =G92*M92 -> 22.756088 | R92: =P92+Q92 -> 7608.1187 | S92: =P92*O92 -> 5607.7407 | T92: =Q92*O92 -> 16.823222 | U92: =SUMPRODUCT(R93:R543,O93:O543)/(M92*O92) -> 961926.53
A93: 90 | B93: =A93/Inputs!$B$6 -> 7.5 | C93: =Inputs!$B$3+B93 -> 72.5 | D93: =INT(C93) -> 72 | E93: =Inputs!$B$7+1+INT((A93-1)/Inputs!$B$6) -> 2033 | F93: =Inputs!$B$16 -> 8333.3333 | G93: =Inputs!$B$12 -> 25 | H93: =IFERROR(INDEX(RP2014_Qx!$B:$B,MATCH(D93,RP2014_Qx!$A:$A,0)),"") -> 0.015614 | I93: =SUMIFS(MP2016_Long!$C:$C,MP2016_Long!$A:$A,D93,MP2016_Long!$B:$B,">=2014",MP2016_Long!$B:$B,"<"&E93) -> 0.1604 | J93: =MIN(0.999999,MAX(0,H93*EXP(I93))) -> 0.018330529 | K93: =-LN(1-J93) -> 0.018500615 | L93: =EXP(-K93/Inputs!$B$6) -> 0.99845947 | M93: =M92*L93 -> 0.90884126 | N93: =IFERROR(INDEX(MonthlyCurve!$I:$I,MATCH(A93,MonthlyCurve!$A:$A,0)),"") -> 0.04078636 | O93: =IFERROR(INDEX(MonthlyCurve!$J:$J,MATCH(A93,MonthlyCurve!$A:$A,0)),"") -> 0.73646196 | P93: =F93*M93 -> 7573.6771 | Q93: =G93*M93 -> 22.721031 | R93: =P93+Q93 -> 7596.3982 | S93: =P93*O93 -> 5577.7251 | T93: =Q93*O93 -> 16.733175 | U93: =SUMPRODUCT(R94:R543,O94:O543)/(M93*O93) -> 958744.65
A94: 91 | B94: =A94/Inputs!$B$6 -> 7.5833333 | C94: =Inputs!$B$3+B94 -> 72.583333 | D94: =INT(C94) -> 72 | E94: =Inputs!$B$7+1+INT((A94-1)/Inputs!$B$6) -> 2033 | F94: =Inputs!$B$16 -> 8333.3333 | G94: =Inputs!$B$12 -> 25 | H94: =IFERROR(INDEX(RP2014_Qx!$B:$B,MATCH(D94,RP2014_Qx!$A:$A,0)),"") -> 0.015614 | I94: =SUMIFS(MP2016_Long!$C:$C,MP2016_Long!$A:$A,D94,MP2016_Long!$B:$B,">=2014",MP2016_Long!$B:$B,"<"&E94) -> 0.1604 | J94: =MIN(0.999999,MAX(0,H94*EXP(I94))) -> 0.018330529 | K94: =-LN(1-J94) -> 0.018500615 | L94: =EXP(-K94/Inputs!$B$6) -> 0.99845947 | M94: =M93*L94 -> 0.90744116 | N94: =IFERROR(INDEX(MonthlyCurve!$I:$I,MATCH(A94,MonthlyCurve!$A:$A,0)),"") -> 0.040844425 | O94: =IFERROR(INDEX(MonthlyCurve!$J:$J,MATCH(A94,MonthlyCurve!$A:$A,0)),"") -> 0.73363996 | P94: =F94*M94 -> 7562.0097 | Q94: =G94*M94 -> 22.686029 | R94: =P94+Q94 -> 7584.6957 | S94: =P94*O94 -> 5547.7925 | T94: =Q94*O94 -> 16.643377 | U94: =SUMPRODUCT(R95:R543,O95:O543)/(M94*O94) -> 955559.13
A95: 92 | B95: =A95/Inputs!$B$6 -> 7.6666667 | C95: =Inputs!$B$3+B95 -> 72.666667 | D95: =INT(C95) -> 72 | E95: =Inputs!$B$7+1+INT((A95-1)/Inputs!$B$6) -> 2033 | F95: =Inputs!$B$16 -> 8333.3333 | G95: =Inputs!$B$12 -> 25 | H95: =IFERROR(INDEX(RP2014_Qx!$B:$B,MATCH(D95,RP2014_Qx!$A:$A,0)),"") -> 0.015614 | I95: =SUMIFS(MP2016_Long!$C:$C,MP2016_Long!$A:$A,D95,MP2016_Long!$B:$B,">=2014",MP2016_Long!$B:$B,"<"&E95) -> 0.1604 | J95: =MIN(0.999999,MAX(0,H95*EXP(I95))) -> 0.018330529 | K95: =-LN(1-J95) -> 0.018500615 | L95: =EXP(-K95/Inputs!$B$6) -> 0.99845947 | M95: =M94*L95 -> 0.90604322 | N95: =IFERROR(INDEX(MonthlyCurve!$I:$I,MATCH(A95,MonthlyCurve!$A:$A,0)),"") -> 0.04090249 | O95: =IFERROR(INDEX(MonthlyCurve!$J:$J,MATCH(A95,MonthlyCurve!$A:$A,0)),"") -> 0.7308217 | P95: =F95*M95 -> 7550.3602 | Q95: =G95*M95 -> 22.65108 | R95: =P95+Q95 -> 7573.0112 | S95: =P95*O95 -> 5517.9671 | T95: =Q95*O95 -> 16.553901 | U95: =SUMPRODUCT(R96:R543,O96:O543)/(M95*O95) -> 952365.73
A96: 93 | B96: =A96/Inputs!$B$6 -> 7.75 | C96: =Inputs!$B$3+B96 -> 72.75 | D96: =INT(C96) -> 72 | E96: =Inputs!$B$7+1+INT((A96-1)/Inputs!$B$6) -> 2033 | F96: =Inputs!$B$16 -> 8333.3333 | G96: =Inputs!$B$12 -> 25 | H96: =IFERROR(INDEX(RP2014_Qx!$B:$B,MATCH(D96,RP2014_Qx!$A:$A,0)),"") -> 0.015614 | I96: =SUMIFS(MP2016_Long!$C:$C,MP2016_Long!$A:$A,D96,MP2016_Long!$B:$B,">=2014",MP2016_Long!$B:$B,"<"&E96) -> 0.1604 | J96: =MIN(0.999999,MAX(0,H96*EXP(I96))) -> 0.018330529 | K96: =-LN(1-J96) -> 0.018500615 | L96: =EXP(-K96/Inputs!$B$6) -> 0.99845947 | M96: =M95*L96 -> 0.90464743 | N96: =IFERROR(INDEX(MonthlyCurve!$I:$I,MATCH(A96,MonthlyCurve!$A:$A,0)),"") -> 0.040960555 | O96: =IFERROR(INDEX(MonthlyCurve!$J:$J,MATCH(A96,MonthlyCurve!$A:$A,0)),"") -> 0.72800723 | P96: =F96*M96 -> 7538.7286 | Q96: =G96*M96 -> 22.616186 | R96: =P96+Q96 -> 7561.3448 | S96: =P96*O96 -> 5488.2489 | T96: =Q96*O96 -> 16.464747 | U96: =SUMPRODUCT(R97:R543,O97:O543)/(M96*O96) -> 949164.33
A97: 94 | B97: =A97/Inputs!$B$6 -> 7.8333333 | C97: =Inputs!$B$3+B97 -> 72.833333 | D97: =INT(C97) -> 72 | E97: =Inputs!$B$7+1+INT((A97-1)/Inputs!$B$6) -> 2033 | F97: =Inputs!$B$16 -> 8333.3333 | G97: =Inputs!$B$12 -> 25 | H97: =IFERROR(INDEX(RP2014_Qx!$B:$B,MATCH(D97,RP2014_Qx!$A:$A,0)),"") -> 0.015614 | I97: =SUMIFS(MP2016_Long!$C:$C,MP2016_Long!$A:$A,D97,MP2016_Long!$B:$B,">=2014",MP2016_Long!$B:$B,"<"&E97) -> 0.1604 | J97: =MIN(0.999999,MAX(0,H97*EXP(I97))) -> 0.018330529 | K97: =-LN(1-J97) -> 0.018500615 | L97: =EXP(-K97/Inputs!$B$6) -> 0.99845947 | M97: =M96*L97 -> 0.90325379 | N97: =IFERROR(INDEX(MonthlyCurve!$I:$I,MATCH(A97,MonthlyCurve!$A:$A,0)),"") -> 0.04101862 | O97: =IFERROR(INDEX(MonthlyCurve!$J:$J,MATCH(A97,MonthlyCurve!$A:$A,0)),"") -> 0.72519657 | P97: =F97*M97 -> 7527.115 | Q97: =G97*M97 -> 22.581345 | R97: =P97+Q97 -> 7549.6963 | S97: =P97*O97 -> 5458.638 | T97: =Q97*O97 -> 16.375914 | U97: =SUMPRODUCT(R98:R543,O98:O543)/(M97*O97) -> 945954.84
A98: 95 | B98: =A98/Inputs!$B$6 -> 7.9166667 | C98: =Inputs!$B$3+B98 -> 72.916667 | D98: =INT(C98) -> 72 | E98: =Inputs!$B$7+1+INT((A98-1)/Inputs!$B$6) -> 2033 | F98: =Inputs!$B$16 -> 8333.3333 | G98: =Inputs!$B$12 -> 25 | H98: =IFERROR(INDEX(RP2014_Qx!$B:$B,MATCH(D98,RP2014_Qx!$A:$A,0)),"") -> 0.015614 | I98: =SUMIFS(MP2016_Long!$C:$C,MP2016_Long!$A:$A,D98,MP2016_Long!$B:$B,">=2014",MP2016_Long!$B:$B,"<"&E98) -> 0.1604 | J98: =MIN(0.999999,MAX(0,H98*EXP(I98))) -> 0.018330529 | K98: =-LN(1-J98) -> 0.018500615 | L98: =EXP(-K98/Inputs!$B$6) -> 0.99845947 | M98: =M97*L98 -> 0.9018623 | N98: =IFERROR(INDEX(MonthlyCurve!$I:$I,MATCH(A98,MonthlyCurve!$A:$A,0)),"") -> 0.041076685 | O98: =IFERROR(INDEX(MonthlyCurve!$J:$J,MATCH(A98,MonthlyCurve!$A:$A,0)),"") -> 0.72238978 | P98: =F98*M98 -> 7515.5192 | Q98: =G98*M98 -> 22.546558 | R98: =P98+Q98 -> 7538.0658 | S98: =P98*O98 -> 5429.1343 | T98: =Q98*O98 -> 16.287403 | U98: =SUMPRODUCT(R99:R543,O99:O543)/(M98*O98) -> 942737.14
A99: 96 | B99: =A99/Inputs!$B$6 -> 8 | C99: =Inputs!$B$3+B99 -> 73 | D99: =INT(C99) -> 73 | E99: =Inputs!$B$7+1+INT((A99-1)/Inputs!$B$6) -> 2033 | F99: =Inputs!$B$16 -> 8333.3333 | G99: =Inputs!$B$12 -> 25 | H99: =IFERROR(INDEX(RP2014_Qx!$B:$B,MATCH(D99,RP2014_Qx!$A:$A,0)),"") -> 0.01721 | I99: =SUMIFS(MP2016_Long!$C:$C,MP2016_Long!$A:$A,D99,MP2016_Long!$B:$B,">=2014",MP2016_Long!$B:$B,"<"&E99) -> 0.1661 | J99: =MIN(0.999999,MAX(0,H99*EXP(I99))) -> 0.020319695 | K99: =-LN(1-J99) -> 0.02052898 | L99: =EXP(-K99/Inputs!$B$6) -> 0.99829071 | M99: =M98*L99 -> 0.90032076 | N99: =IFERROR(INDEX(MonthlyCurve!$I:$I,MATCH(A99,MonthlyCurve!$A:$A,0)),"") -> 0.04113475 | O99: =IFERROR(INDEX(MonthlyCurve!$J:$J,MATCH(A99,MonthlyCurve!$A:$A,0)),"") -> 0.71958689 | P99: =F99*M99 -> 7502.673 | Q99: =G99*M99 -> 22.508019 | R99: =P99+Q99 -> 7525.1811 | S99: =P99*O99 -> 5398.8251 | T99: =Q99*O99 -> 16.196475 | U99: =SUMPRODUCT(R100:R543,O100:O543)/(M99*O99) -> 939671.35
A100: 97 | B100: =A100/Inputs!$B$6 -> 8.0833333 | C100: =Inputs!$B$3+B100 -> 73.083333 | D100: =INT(C100) -> 73 | E100: =Inputs!$B$7+1+INT((A100-1)/Inputs!$B$6) -> 2034 | F100: =Inputs!$B$16 -> 8333.3333 | G100: =Inputs!$B$12 -> 25 | H100: =IFERROR(INDEX(RP2014_Qx!$B:$B,MATCH(D100,RP2014_Qx!$A:$A,0)),"") -> 0.01721 | I100: =SUMIFS(MP2016_Long!$C:$C,MP2016_Long!$A:$A,D100,MP2016_Long!$B:$B,">=2014",MP2016_Long!$B:$B,"<"&E100) -> 0.1661 | J100: =MIN(0.999999,MAX(0,H100*EXP(I100))) -> 0.020319695 | K100: =-LN(1-J100) -> 0.02052898 | L100: =EXP(-K100/Inputs!$B$6) -> 0.99829071 | M100: =M99*L100 -> 0.89878186 | N100: =IFERROR(INDEX(MonthlyCurve!$I:$I,MATCH(A100,MonthlyCurve!$A:$A,0)),"") -> 0.041193417 | O100: =IFERROR(INDEX(MonthlyCurve!$J:$J,MATCH(A100,MonthlyCurve!$A:$A,0)),"") -> 0.71678445 | P100: =F100*M100 -> 7489.8488 | Q100: =G100*M100 -> 22.469546 | R100: =P100+Q100 -> 7512.3184 | S100: =P100*O100 -> 5368.6071 | T100: =Q100*O100 -> 16.105821 | U100: =SUMPRODUCT(R101:R543,O101:O543)/(M100*O100) -> 936602.1
...

Sheet Dashboard
A1: SPIA Policy Projection Dashboard
A3: Policy Inputs | D3: Expense Assumptions
A4: Issue Age | B4: =Inputs!B3 -> 65 | D4: Policy Expense ($) | E4: =Inputs!B10 -> 250
A5: Sex | B5: =Inputs!B4 -> male | D5: Premium Expense Rate | E5: =Inputs!B11 -> 0.01
A6: Annual Benefit | B6: =Inputs!B5 -> 100000 | D6: Monthly Expense ($) | E6: =Inputs!B12 -> 25
A7: Valuation Year (12/31) | B7: =Inputs!B7 -> 2025
A8: Horizon Age | B8: =Inputs!B8 -> 110
A9: Spread | B9: =Inputs!B9 -> 0
A11: Pricing & Reserve Summary
A12: Single Premium | B12: =Projection!X8 -> 1281342.4
A13: PV Benefits | B13: =Projection!X4 -> 1264485.5
A14: PV Monthly Expenses | B14: =Projection!X5 -> 3793.4566
A15: PV Monthly Total | B15: =Projection!X7 -> 1268279
A16: Annuity Factor | B16: =Projection!X6 -> 151.73826
A17: Economic Reserve at t=0 | B17: =Projection!U2 -> 1268279
A54: Checkpoint Metrics (Nearest Monthly Projection Point)
A55: Target Age | B55: Projection Row | C55: Survival | D55: Exp Benefit ($) | E55: Exp Expense ($) | F55: Reserve ($)
A56: 65 | B56: =IFERROR(MATCH(A56,Projection!$C$4:$C$543,0)+3,IF(A56<INDEX(Projection!$C$4:$C$543,1),4,MATCH(A56,Projection!$C$4:$C$543,1)+3)) -> 4 | C56: =INDEX(Projection!$M:$M,B56) -> 0.99928225 | D56: =INDEX(Projection!$P:$P,B56) -> 8327.3521 | E56: =INDEX(Projection!$Q:$Q,B56) -> 24.982056 | F56: =INDEX(Projection!$U:$U,B56) -> 1264777.6
A57: 70 | B57: =IFERROR(MATCH(A57,Projection!$C$4:$C$543,0)+3,IF(A57<INDEX(Projection!$C$4:$C$543,1),4,MATCH(A57,Projection!$C$4:$C$543,1)+3)) -> 63 | C57: =INDEX(Projection!$M:$M,B57) -> 0.94695511 | D57: =INDEX(Projection!$P:$P,B57) -> 7891.2926 | E57: =INDEX(Projection!$Q:$Q,B57) -> 23.673878 | F57: =INDEX(Projection!$U:$U,B57) -> 1053573.6
A58: 75 | B58: =IFERROR(MATCH(A58,Projection!$C$4:$C$543,0)+3,IF(A58<INDEX(Projection!$C$4:$C$543,1),4,MATCH(A58,Projection!$C$4:$C$543,1)+3)) -> 123 | C58: =INDEX(Projection!$M:$M,B58) -> 0.86181019 | D58: =INDEX(Projection!$P:$P,B58) -> 7181.7516 | E58: =INDEX(Projection!$Q:$Q,B58) -> 21.545255 | F58: =INDEX(Projection!$U:$U,B58) -> 866218.58
A59: 80 | B59: =IFERROR(MATCH(A59,Projection!$C$4:$C$543,0)+3,IF(A59<INDEX(Projection!$C$4:$C$543,1),4,MATCH(A59,Projection!$C$4:$C$543,1)+3)) -> 183 | C59: =INDEX(Projection!$M:$M,B59) -> 0.73484967 | D59: =INDEX(Projection!$P:$P,B59) -> 6123.7473 | E59: =INDEX(Projection!$Q:$Q,B59) -> 18.371242 | F59: =INDEX(Projection!$U:$U,B59) -> 695260.79
A60: 85 | B60: =IFERROR(MATCH(A60,Projection!$C$4:$C$543,0)+3,IF(A60<INDEX(Projection!$C$4:$C$543,1),4,MATCH(A60,Projection!$C$4:$C$543,1)+3)) -> 243 | C60: =INDEX(Projection!$M:$M,B60) -> 0.55815242 | D60: =INDEX(Projection!$P:$P,B60) -> 4651.2701 | E60: =INDEX(Projection!$Q:$Q,B60) -> 13.95381 | F60: =INDEX(Projection!$U:$U,B60) -> 559243.09
A61: 90 | B61: =IFERROR(MATCH(A61,Projection!$C$4:$C$543,0)+3,IF(A61<INDEX(Projection!$C$4:$C$543,1),4,MATCH(A61,Projection!$C$4:$C$543,1)+3)) -> 303 | C61: =INDEX(Projection!$M:$M,B61) -> 0.34251823 | D61: =INDEX(Projection!$P:$P,B61) -> 2854.3186 | E61: =INDEX(Projection!$Q:$Q,B61) -> 8.5629558 | F61: =INDEX(Projection!$U:$U,B61) -> 408366.5
A62: 100 | B62: =IFERROR(MATCH(A62,Projection!$C$4:$C$543,0)+3,IF(A62<INDEX(Projection!$C$4:$C$543,1),4,MATCH(A62,Projection!$C$4:$C$543,1)+3)) -> 423 | C62: =INDEX(Projection!$M:$M,B62) -> 0.034570343 | D62: =INDEX(Projection!$P:$P,B62) -> 288.08619 | E62: =INDEX(Projection!$Q:$Q,B62) -> 0.86425857 | F62: =INDEX(Projection!$U:$U,B62) -> 213792.44
A63: 110 | B63: =IFERROR(MATCH(A63,Projection!$C$4:$C$543,0)+3,IF(A63<INDEX(Projection!$C$4:$C$543,1),4,MATCH(A63,Projection!$C$4:$C$543,1)+3)) -> 543 | C63: =INDEX(Projection!$M:$M,B63) -> 0.00023178081 | D63: =INDEX(Projection!$P:$P,B63) -> 1.9315068 | E63: =INDEX(Projection!$Q:$Q,B63) -> 0.0057945203 | F63: =INDEX(Projection!$U:$U,B63) -> 0

Sheet Python_Runbook
A1: Python Runbook / Repro Steps
A3: Purpose | B3: This tab documents how to run and regenerate the SPIA Python model artifacts.
A4: Working folder | B4: annuity_model
A5: Python version | B5: Use Python 3.11+ recommended.
A6: Dependencies | B6: numpy, pandas, openpyxl, matplotlib
A8: Core commands | B8: From the annuity_model folder run:
A9: 1 | B9: python spia_projection.py
A10: 2 | B10: python illustrate_spia_projection.py
A11: 3 | B11: python build_spia_excel_workbook.py
A13: Inputs used by Python | B13: treasury_zero_rate_curve_latest.csv
B14: rp2014_mort_tab_rates_exposure.xlsx
B15: mp2016_rates.xlsx
B16: expenses_assumptions_us_placeholders.csv
A18: Outputs generated by Python | B18: spia_projection_model.xlsx
B19: illustrations/*.png
B20: rp2014_male_healthy_annuitant_qx_2014.csv
B21: mp2016_male_improvement_rates.csv
A23: Python in Excel note | B23: If your Excel has Python-in-Excel, you can use =PY() cells.
A24: Example | B24: {=_xlfn._xlws.PY(0,1)} -> import pandas as pd; pd.read_csv('treasury_zero_rate_curve_latest.csv').head()
A25: Example | B25: {=_xlfn._xlws.PY(1,1)} -> from spia_projection import _example_usage; _example_usage()
A27: Caveat | B27: Python-in-Excel runs in Microsoft sandbox; local file access may be restricted.
A28: Recommendation | B28: Use terminal commands above for production reproducibility.
A35: spia_projection.py (excerpt)
A36: """ Single Premium Immediate Annuity (SPIA) projection scaffolding. Contract assumptions (set from the conversation): - Single life - Level monthly payments, benefit is provided as an annual amount (default: 100_000) - Payment timing: end of period - Payments stop at death (i.e., pay at time t_k iff alive at that payment date) Pricing (single premium): Premium = sum_{k=1..N} (B_annual/12) * P(alive at t_k) * DF(t_k) Interest: - Uses continuous-compounding "zero rates" z(t). Discount factors: DF(t) = exp(-(z(t) + spread) * t) - Risk-free by default: spread = 0. US industry mortality (table selection, data must be supplied): - RP-2014 Healthy Annuitant Male base table - MP-2016 mortality improvement scale Important: - RP-2014 and MP-2016 are proprietary to SOA. - This code does NOT embed the table rates. - Provide annual one-year death probabilities q_x (or equivalent) in a CSV. """ from __future__ import annotations from dataclasses import dataclass from typing import Literal, Optional, Sequence, Tuple import math import numpy as np import pandas as pd Compounding = Literal["continuous"] DEFAULT_ZERO_CURVE_CSV = "treasury_zero_rate_curve_latest.csv" DEFAULT_PAR_CURVE_CSV = "treasury_par_yield_curve_latest.csv" DEFAULT_MORTALITY_QX_CSV = "rp2014_male_annuitant_qx.csv" DEFAULT_RP2014_XLSX = "rp2014_mort_tab_rates_exposure.xlsx" DEFAULT_MP2016_XLSX = "mp2016_rates.xlsx" DEFAULT_RP2014_MALE_HEALTHY_QX_CSV = "rp2014_male_healthy_annuitant_qx_2014.csv" DEFAULT_MP2016_MALE_IMPROVEMENT_CSV = "mp2016_male_improvement_rates.csv" DEFAULT_EXPENSES_CSV = "expenses_assumptions_us_placeholders.csv" @dataclass(frozen=True) class YieldCurve: """ Continuous-compounding zero curve. Attributes ---------- maturities_years: Array of curve node maturities in years (e.g., [0.5, 1.0, 1.5, ...]). zero_rates: Corresponding continuously-compounded spot/zero rates z(t). """ maturities_years: np.ndarray zero_rates: np.ndarray @staticmethod def from_flat_rate(flat_zero_rate: float) -> "YieldCurve": mats = np.array([0.0, 1.0], dtype=float) zeros = np.array([flat_zero_rate, flat_zero_rate], dtype=float) return YieldCurve(mats, zeros) @staticmethod def load_zero_curve_csv( path: str, *, maturity_col: str = "maturity_years", rate_col: str = "zero_rate", ) -> "YieldCurve": df = pd.read_csv(path) mats = df[maturity_col].to_numpy(dtype=float) zeros = df[rate_col].to_numpy(dtype=float) order = np.argsort(mats) return YieldCurve(mats[order], zeros[order]) @staticmethod def load_par_yield_csv_and_bootstrap( path: str, *, maturity_col: str = "maturity_years", par_rate_col: str = "par_yield", coupon_freq: int = 2, interpolation: Literal["linear"] = "linear", ) -> "YieldCurve": """ Bootstrap discount factors from a par-yield curve. Inputs note: - Treasury par yields are commonly quoted with semiannual coupons. - To bootstrap discount factors on the coupon grid, this function will linearly interpolate the par yields onto each coupon date. - This is sufficient for a scaffold; later you can replace with a more faithful bootstrapping approach as needed. """ df = pd.read_csv(path) maturities = df[maturity_col].to_numpy(dtype=float) par_yields = df[par_rate_col].to_numpy(dtype=float) order = np.argsort(maturities) maturities = maturities[order] par_yields = par_yields[order] zero_mats, zero_rates = bootstrap_zero_rates_from_par_yields( par_maturities_years=maturities, par_yields=par_yields, coupon_freq=coupon_freq, ) return YieldCurve(zero_mats, zero_rates) def discount_factors( self, times_years: np.ndarray, *, spread: float = 0.0, compounding: Compounding = "continuous", ) -> np.ndarray: """ Convert the stored zero curve into discount factors at arbitrary times. Uses log-linear interpolation on discount factors (stable). """ if compounding != "continuous": raise ValueError("Only continuous compounding is implemented.") t = np.asarray(times_years, dtype=float) if t.ndim != 1: raise ValueError("times_years must be a 1D array.") # Ensure increasing curve times. mats = np.asarray(self.maturities_years, dtype=float)
A95: illustrate_spia_projection.py (excerpt)
A96: import numpy as np import matplotlib.pyplot as plt from spia_projection import ( SPIAContract, YieldCurve, MortalityTableRP2014MP2016, ensure_mp2016_male_improvement_csv, ensure_rp2014_male_healthy_annuitant_qx_csv, price_spia_single_premium, ExpenseAssumptions, ) def _safe_mkdir(path: str) -> None: import os os.makedirs(path, exist_ok=True) def main() -> None: # Policy inputs (from conversation) contract = SPIAContract(issue_age=65, sex="male", benefit_annual=100_000.0) horizon_age = 110 spread = 0.0 valuation_year = 2025 # 12/31/2025 valuation date # Files in working folder zero_curve_csv = "treasury_zero_rate_curve_latest.csv" rp2014_xlsx = "rp2014_mort_tab_rates_exposure.xlsx" mp2016_xlsx = "mp2016_rates.xlsx" out_dir = "illustrations" _safe_mkdir(out_dir) # Load curves / mortality yc = YieldCurve.load_zero_curve_csv(zero_curve_csv) base_qx = ensure_rp2014_male_healthy_annuitant_qx_csv( rp2014_xlsx_path=rp2014_xlsx, out_csv_path="rp2014_male_healthy_annuitant_qx_2014.csv", ) mp_ages, mp_years, mp_i = ensure_mp2016_male_improvement_csv( mp2016_xlsx_path=mp2016_xlsx, out_csv_path="mp2016_male_improvement_rates.csv", ) mortality = MortalityTableRP2014MP2016( base_qx_2014=base_qx, mp2016_ages=mp_ages, mp2016_years=mp_years, mp2016_i_matrix=mp_i, base_year=2014, ) # Compute projection res = price_spia_single_premium( contract=contract, yield_curve=yc, mortality=mortality, horizon_age=horizon_age, spread=spread, valuation_year=valuation_year, ) dt = 1.0 / 12.0 b_month = contract.benefit_annual / 12.0 expected_payment_pv = b_month * res.survival_to_payment * res.discount_factors expected_benefit_cashflows = res.expected_benefit_cashflows expected_expense_cashflows = res.expected_expense_cashflows expected_total_cashflows = res.expected_total_cashflows # Economic reserves are stored at t=0 plus each monthly payment date. ages_at_reserve = contract.issue_age + res.reserve_times_years # Plot 1: survival plt.figure(figsize=(9, 5)) plt.plot(res.ages_at_payment, res.survival_to_payment, linewidth=2) plt.title("SPIA: Survival Probability to Each Monthly Payment Date") plt.xlabel("Attained Age at Payment") plt.ylabel("P(alive at payment)") plt.grid(True, alpha=0.3) plt.tight_layout() plt.savefig(f"{out_dir}/spia_survival_vs_age.png", dpi=160) plt.close() # Plot 2: expected PV contribution per payment date plt.figure(figsize=(9, 5)) plt.plot(res.ages_at_payment, expected_payment_pv, linewidth=2) plt.title("SPIA: Expected PV Contribution per Monthly Payment") plt.xlabel("Attained Age at Payment") plt.ylabel("Expected Present Value of Payment ($)") plt.grid(True, alpha=0.3) plt.tight_layout() plt.savefig(f"{out_dir}/spia_expected_pv_contribution_vs_age.png", dpi=160) plt.close() # Plot 3: cumulative PV cumulative_pv = np.cumsum(expected_payment_pv) plt.figure(figsize=(9, 5)) plt.plot(res.ages_at_payment, cumulative_pv, linewidth=2) plt.title("SPIA: Cumulative PV of Expected Payments") plt.xlabel("Attained Age at Payment") plt.ylabel("Cumulative Present Value ($)") plt.grid(True, alpha=0.3) plt.tight_layout() plt.savefig(f"{out_dir}/spia_cumulative_pv_vs_age.png", dpi=160) plt.close() # Plot 4: projected monthly benefit cashflows (expected nominal) plt.figure(figsize=(9, 5)) plt.plot(res.ages_at_payment, expected_benefit_cashflows, linewidth=2, color="tab:blue") plt.title("SPIA: Expected Monthly Benefit Payments (Nominal)") plt.xlabel("Attained Age at Payment") plt.ylabel("Expected Benefit Payment ($)") plt.grid(True, alpha=0.3) plt.tight_layout() plt.savefig(f"{out_dir}/spia_expected_benefit_cashflows_vs_age.png", dpi=160) plt.close() # Plot 5: projected monthly expense cashflows (expected nominal) plt.figure(figsize=(9, 5))
